<?xml version="1.0" encoding="UTF-8"?>
<model xmlns="http://www.opengroup.org/xsd/archimate/3.0/" xmlns:xsi="http://www.w3.org/2001/XMLSchema-instance" xsi:schemaLocation="http://www.opengroup.org/xsd/archimate/3.0/ http://www.opengroup.org/xsd/archimate/3.1/archimate3_Diagram.xsd" identifier="id-2f8ace2e5534460cbbdb7e44710c8ce9">
  <name>patterns</name>
  <elements>
    <element identifier="id-1ed0b6680a954e9196691162796cea8c" xsi:type="Capability">
      <name>Exploitation Capability</name>
    </element>
    <element identifier="id-65fb95b4944f4c21814e7033a53c2ce5" xsi:type="Resource">
      <name>«AssetAtRisk» Private Data</name>
    </element>
    <element identifier="id-9a438febac894ec1ae6c43ff080fbbec" xsi:type="Resource">
      <name>Software Code</name>
    </element>
    <element identifier="id-db2b88e2589a442fab3bca7fa6f44ce5" xsi:type="Capability">
      <name>«Vulnerability» Weakness</name>
    </element>
    <element identifier="id-cdbb414a60b246b3a399fcac8d377dff" xsi:type="Capability">
      <name>Exploitation Capability</name>
    </element>
    <element identifier="id-94a5a202efbf4c8c872c1cd66131fd97" xsi:type="Resource">
      <name>Software Code</name>
    </element>
    <element identifier="id-b361a52bf17d4200bda0489abc710423" xsi:type="Resource">
      <name>«AssetAtRisk» Private Data</name>
    </element>
    <element identifier="id-238287d9d98b452f8efb4ab654006ca9" xsi:type="Resource">
      <name>«SecurityMechanism»Autoupdater Piece of Software</name>
    </element>
    <element identifier="id-1d7a475888e74b40aeb9155845cbf97f" xsi:type="Capability">
      <name>Autoupdate Software Capacity</name>
    </element>
    <element identifier="id-0d2bcec545154a5e8c7163d94a7028cc" xsi:type="BusinessEvent">
      <name>«ThreatEvent» Vulnerability Exploitation</name>
    </element>
    <element identifier="id-f203326e4119417cb9fb495a9bf26e2c" xsi:type="BusinessEvent">
      <name>«LossEvent» Data Breach</name>
    </element>
    <element identifier="id-8eb5880c7679453f8d6b7b93414a7fd7" xsi:type="BusinessActor">
      <name>«ThreatAgent»Hacker</name>
    </element>
    <element identifier="id-dc6d70f7397348ec8cd606e8ce0a374d" xsi:type="BusinessRole">
      <name>«SecurityDesigner» IT Security Team</name>
    </element>
    <element identifier="id-ce1a9420d2ff493e83a06af94a8de497" xsi:type="BusinessActor">
      <name>«ThreatAgent»Hacker</name>
    </element>
    <element identifier="id-c6dbbd23314e4cb4af45423bceab84a3" xsi:type="BusinessEvent">
      <name>«LossEvent» Data Breach</name>
    </element>
    <element identifier="id-8abfc6fc96b94ec987298cb4e70f9534" xsi:type="BusinessEvent">
      <name>«ThreatEvent» Vulnerability Exploitation (copy)</name>
    </element>
    <element identifier="id-b2a86896d88f43b48a6879cfa827f00c" xsi:type="BusinessRole">
      <name>«SecurityDesigner» IT Security Team</name>
    </element>
    <element identifier="id-7a8da4358ecd4a9d8364a1a1163a99dd" xsi:type="BusinessEvent">
      <name>Autoupdate</name>
    </element>
    <element identifier="id-72f90fbcbde249d1b7d9cb629e28ba96" xsi:type="Goal">
      <name>Exploitation Intention</name>
    </element>
    <element identifier="id-066062762cb040ac9ee67b6de7637daf" xsi:type="Assessment">
      <name>«HazardAssessment» Lack of Software Update by the Users</name>
    </element>
    <element identifier="id-4639cd91bdf144f69f0553a0ffdd8449" xsi:type="Assessment">
      <name>«Likelihood» 50%</name>
    </element>
    <element identifier="id-5448b50b6a3e413294c52a46d1671dc3" xsi:type="Goal">
      <name>Data Protection</name>
    </element>
    <element identifier="id-30966f8647ca4a76876a928272644c73" xsi:type="Stakeholder">
      <name>Company</name>
    </element>
    <element identifier="id-aaf0583fdf6a4bb5be6e2f2869fdd2a4" xsi:type="Goal">
      <name>«ControlObjective»Preventing Data Breach</name>
    </element>
    <element identifier="id-4458db07e6f640369b4dfab03b672d5d" xsi:type="Requirement">
      <name>«ControlMeasure» Autoupdates</name>
    </element>
    <element identifier="id-cd9f5a3f32124302841f16a30b36721d" xsi:type="Driver">
      <name>«Risk» Data Breach</name>
    </element>
    <element identifier="id-44a9acf5b71f4fcf9be0da6022d7e6f1" xsi:type="Assessment">
      <name>Risk of Data Breach is Unacceptable</name>
    </element>
    <element identifier="id-fadbd167f34b46cb9a3b8f9c56874e35" xsi:type="Assessment">
      <name>«HazardAssessment» Lack of Software Update by the Users</name>
    </element>
    <element identifier="id-137f794b34ff45c0b3365865a74b7697" xsi:type="Driver">
      <name>«Risk» Data Breach (copy)</name>
    </element>
    <element identifier="id-9861aa39153f46779719dc9a4219c557" xsi:type="Goal">
      <name>Data Protection</name>
    </element>
    <element identifier="id-5f5ee5c36d384ce281bbce484364abb7" xsi:type="Goal">
      <name>Exploitation Intention</name>
    </element>
    <element identifier="id-0587c21ebdb94b308a326a435c143214" xsi:type="Stakeholder">
      <name>Company</name>
    </element>
    <element identifier="id-8db2e104c8274bd69ace60e25e6bab68" xsi:type="Goal">
      <name>«ControlObjective»Preventing Data Breach</name>
    </element>
    <element identifier="id-925b9cfd6e4843a393a18ba344e845d1" xsi:type="Assessment">
      <name>Risk of Data Breach is acceptable</name>
    </element>
    <element identifier="id-ae0ad30a07c74aab9cb454cd53e490c9" xsi:type="Assessment">
      <name>«Likelihood» 5%</name>
    </element>
    <element identifier="id-8dc4a1723df74d67bc914b77b2ff159c" xsi:type="Requirement">
      <name>«ControlMeasure» Check Autoupdater regularly</name>
    </element>
    <element identifier="id-4f87a140b4a44ee9bde7eb8d808fdc1e" xsi:type="Gap">
      <name>Guarantee Users Update the Software</name>
    </element>
    <element identifier="id-cdc80a27cc9f426c95564ea7df035ee9" xsi:type="ImplementationEvent">
      <name>Implementation of Autoupdater Piece of Software</name>
    </element>
    <element identifier="id-8779269d947848f0bd7a5e1c0dacf0b3" xsi:type="WorkPackage">
      <name>Software Improvement</name>
    </element>
    <element identifier="id-a9b7e3d685194071b70f08ca20736933" xsi:type="Plateau">
      <name>Baseline Architecture</name>
    </element>
    <element identifier="id-c4eb396033474ce8bd2a05a4d0cde67b" xsi:type="Plateau">
      <name>Target Architecture</name>
    </element>
  </elements>
  <relationships>
    <relationship identifier="id-51a163be51604b4d8915a4bdb987eba1" source="id-0d2bcec545154a5e8c7163d94a7028cc" target="id-f203326e4119417cb9fb495a9bf26e2c" xsi:type="Triggering" />
    <relationship identifier="id-8c665d1c707146a1b7a2e4d935049ceb" source="id-8eb5880c7679453f8d6b7b93414a7fd7" target="id-0d2bcec545154a5e8c7163d94a7028cc" xsi:type="Assignment" />
    <relationship identifier="id-75db1a1a34b34bf4b3ac0bda16b19866" source="id-8eb5880c7679453f8d6b7b93414a7fd7" target="id-72f90fbcbde249d1b7d9cb629e28ba96" xsi:type="Association" />
    <relationship identifier="id-00762873943a4e71a8b386f6e6e7a235" source="id-8eb5880c7679453f8d6b7b93414a7fd7" target="id-1ed0b6680a954e9196691162796cea8c" xsi:type="Association" />
    <relationship identifier="id-a0cb8839341c4c37a3aed6d81bfc1d2e" source="id-9a438febac894ec1ae6c43ff080fbbec" target="id-db2b88e2589a442fab3bca7fa6f44ce5" xsi:type="Association" />
    <relationship identifier="id-41a483a81dbd4d96afeabdd570bf62e1" source="id-0d2bcec545154a5e8c7163d94a7028cc" target="id-db2b88e2589a442fab3bca7fa6f44ce5" xsi:type="Association" />
    <relationship identifier="id-fe9d61c86d864d7993f1541258d205af" source="id-72f90fbcbde249d1b7d9cb629e28ba96" target="id-db2b88e2589a442fab3bca7fa6f44ce5" xsi:type="Association" />
    <relationship identifier="id-4afb5763897b47f0a3cafad3a6458fc0" source="id-72f90fbcbde249d1b7d9cb629e28ba96" target="id-1ed0b6680a954e9196691162796cea8c" xsi:type="Association" />
    <relationship identifier="id-feab20f73b824c3981362ec28d1f265a" source="id-db2b88e2589a442fab3bca7fa6f44ce5" target="id-1ed0b6680a954e9196691162796cea8c" xsi:type="Association" />
    <relationship identifier="id-9018cf164cf44c7e86635cfa05817822" source="id-066062762cb040ac9ee67b6de7637daf" target="id-0d2bcec545154a5e8c7163d94a7028cc" xsi:type="Association" />
    <relationship identifier="id-d428cba899b74983abe9e038b99c566b" source="id-4639cd91bdf144f69f0553a0ffdd8449" target="id-9018cf164cf44c7e86635cfa05817822" xsi:type="Association" />
    <relationship identifier="id-4c8260c3eb9f44d5b897ed413873d606" source="id-f203326e4119417cb9fb495a9bf26e2c" target="id-65fb95b4944f4c21814e7033a53c2ce5" xsi:type="Association" />
    <relationship identifier="id-9508b116a7e9403fa829aea08e195bf2" source="id-f203326e4119417cb9fb495a9bf26e2c" target="id-5448b50b6a3e413294c52a46d1671dc3" xsi:type="Influence" />
    <relationship identifier="id-0c0916161df24ce08bf63290d9eadc79" source="id-5448b50b6a3e413294c52a46d1671dc3" target="id-30966f8647ca4a76876a928272644c73" xsi:type="Association" />
    <relationship identifier="id-4c24075255034d328340f97aa6f18f63" source="id-4458db07e6f640369b4dfab03b672d5d" target="id-aaf0583fdf6a4bb5be6e2f2869fdd2a4" xsi:type="Realization" />
    <relationship identifier="id-c0e2cbf0c39041958f37b1bd2a47fee6" source="id-aaf0583fdf6a4bb5be6e2f2869fdd2a4" target="id-30966f8647ca4a76876a928272644c73" xsi:type="Association" />
    <relationship identifier="id-dce0f257602f4eaa8d10a01120bf148d" source="id-4458db07e6f640369b4dfab03b672d5d" target="id-dc6d70f7397348ec8cd606e8ce0a374d" xsi:type="Association" />
    <relationship identifier="id-cc19b9fa547243d582c359496bfd1211" source="id-dc6d70f7397348ec8cd606e8ce0a374d" target="id-8779269d947848f0bd7a5e1c0dacf0b3" xsi:type="Assignment" />
    <relationship identifier="id-611ef4f63f5341c89ac7b41273d1420d" source="id-8779269d947848f0bd7a5e1c0dacf0b3" target="id-4458db07e6f640369b4dfab03b672d5d" xsi:type="Realization" />
    <relationship identifier="id-b8c06dd9881a456181ade86a38246515" source="id-cd9f5a3f32124302841f16a30b36721d" target="id-44a9acf5b71f4fcf9be0da6022d7e6f1" xsi:type="Association" />
    <relationship identifier="id-13b51d0652cd4a18a32486a023e7b9c1" source="id-aaf0583fdf6a4bb5be6e2f2869fdd2a4" target="id-44a9acf5b71f4fcf9be0da6022d7e6f1" xsi:type="Association" />
    <relationship identifier="id-3535c6b6554b4862b91b01caf2a25d37" source="id-44a9acf5b71f4fcf9be0da6022d7e6f1" target="id-dc6d70f7397348ec8cd606e8ce0a374d" xsi:type="Association" />
    <relationship identifier="id-2d7bffbae5b04e02a5b0a05e75b437cf" source="id-a9b7e3d685194071b70f08ca20736933" target="id-1ed0b6680a954e9196691162796cea8c" xsi:type="Composition" />
    <relationship identifier="id-1c234b44528a476980cd370ca3d4d317" source="id-a9b7e3d685194071b70f08ca20736933" target="id-9a438febac894ec1ae6c43ff080fbbec" xsi:type="Composition" />
    <relationship identifier="id-83d088ab0f7248368185b101da4e44c3" source="id-a9b7e3d685194071b70f08ca20736933" target="id-5448b50b6a3e413294c52a46d1671dc3" xsi:type="Composition" />
    <relationship identifier="id-6e2553f3d53f459885c3c84f15d8cf4f" source="id-a9b7e3d685194071b70f08ca20736933" target="id-72f90fbcbde249d1b7d9cb629e28ba96" xsi:type="Composition" />
    <relationship identifier="id-90773c308faa46dda30d7c6444b39b3d" source="id-a9b7e3d685194071b70f08ca20736933" target="id-8eb5880c7679453f8d6b7b93414a7fd7" xsi:type="Composition" />
    <relationship identifier="id-d41b435582c348ceb4e98c90fd86da22" source="id-a9b7e3d685194071b70f08ca20736933" target="id-f203326e4119417cb9fb495a9bf26e2c" xsi:type="Composition" />
    <relationship identifier="id-7e41aa8ad5054cf2a90e067707070d97" source="id-a9b7e3d685194071b70f08ca20736933" target="id-aaf0583fdf6a4bb5be6e2f2869fdd2a4" xsi:type="Composition" />
    <relationship identifier="id-87785093c82d4e1f977cd191c13ee9a4" source="id-a9b7e3d685194071b70f08ca20736933" target="id-0d2bcec545154a5e8c7163d94a7028cc" xsi:type="Composition" />
    <relationship identifier="id-e5478849792d4dfcbf8cbe7edaa8e2b9" source="id-a9b7e3d685194071b70f08ca20736933" target="id-db2b88e2589a442fab3bca7fa6f44ce5" xsi:type="Composition" />
    <relationship identifier="id-e0ee2035d63a462eb572694ae0df518f" source="id-a9b7e3d685194071b70f08ca20736933" target="id-dc6d70f7397348ec8cd606e8ce0a374d" xsi:type="Composition" />
    <relationship identifier="id-4ba09b5d0954432fbdeac2da32b7c772" source="id-a9b7e3d685194071b70f08ca20736933" target="id-4458db07e6f640369b4dfab03b672d5d" xsi:type="Composition" />
    <relationship identifier="id-30fbd343500c42679a0152d29a17a39a" source="id-a9b7e3d685194071b70f08ca20736933" target="id-65fb95b4944f4c21814e7033a53c2ce5" xsi:type="Composition" />
    <relationship identifier="id-1897e6120d2d4931a3765adc597f92bf" source="id-4f87a140b4a44ee9bde7eb8d808fdc1e" target="id-a9b7e3d685194071b70f08ca20736933" xsi:type="Association" />
    <relationship identifier="id-508e70fc30c843c290978dafcd507e6f" source="id-a9b7e3d685194071b70f08ca20736933" target="id-8779269d947848f0bd7a5e1c0dacf0b3" xsi:type="Association" />
    <relationship identifier="id-41474e853a634a00b5ca15179549a105" source="id-8db2e104c8274bd69ace60e25e6bab68" target="id-0587c21ebdb94b308a326a435c143214" xsi:type="Association" />
    <relationship identifier="id-80ca56d355504cf5b12daa1c4566b513" source="id-8dc4a1723df74d67bc914b77b2ff159c" target="id-8db2e104c8274bd69ace60e25e6bab68" xsi:type="Realization" />
    <relationship identifier="id-42ae63266805411eba0decb9995df822" source="id-c4eb396033474ce8bd2a05a4d0cde67b" target="id-8dc4a1723df74d67bc914b77b2ff159c" xsi:type="Composition" />
    <relationship identifier="id-378dd1b4f0b04d57bf6f0462243f978d" source="id-ce1a9420d2ff493e83a06af94a8de497" target="id-5f5ee5c36d384ce281bbce484364abb7" xsi:type="Association" />
    <relationship identifier="id-3b7e610dcbc3449aacabbb43e5a59eaa" source="id-ce1a9420d2ff493e83a06af94a8de497" target="id-cdbb414a60b246b3a399fcac8d377dff" xsi:type="Association" />
    <relationship identifier="id-bfb34071fb364ad8ab280cfb4c2b60b4" source="id-137f794b34ff45c0b3365865a74b7697" target="id-925b9cfd6e4843a393a18ba344e845d1" xsi:type="Association" />
    <relationship identifier="id-5123d8dfcde34f969c5d3f56b7ca10b7" source="id-8db2e104c8274bd69ace60e25e6bab68" target="id-925b9cfd6e4843a393a18ba344e845d1" xsi:type="Association" />
    <relationship identifier="id-495510a1796b410ca83a3748d7cc391c" source="id-c4eb396033474ce8bd2a05a4d0cde67b" target="id-5f5ee5c36d384ce281bbce484364abb7" xsi:type="Composition" />
    <relationship identifier="id-6951aaf2f6c14a81a1a7dcdbb39daefd" source="id-ce1a9420d2ff493e83a06af94a8de497" target="id-8abfc6fc96b94ec987298cb4e70f9534" xsi:type="Assignment" />
    <relationship identifier="id-7046e346548843fbb6a357cc4f9f4442" source="id-c4eb396033474ce8bd2a05a4d0cde67b" target="id-b361a52bf17d4200bda0489abc710423" xsi:type="Composition" />
    <relationship identifier="id-3b1eaee9520645dab39e1bcb133c7293" source="id-c4eb396033474ce8bd2a05a4d0cde67b" target="id-cdbb414a60b246b3a399fcac8d377dff" xsi:type="Composition" />
    <relationship identifier="id-3ab9a726e7cf4b63b5901242881acd02" source="id-5f5ee5c36d384ce281bbce484364abb7" target="id-cdbb414a60b246b3a399fcac8d377dff" xsi:type="Association" />
    <relationship identifier="id-b3feb2c96fc94fa1b2c4db19aebdf190" source="id-c6dbbd23314e4cb4af45423bceab84a3" target="id-b361a52bf17d4200bda0489abc710423" xsi:type="Association" />
    <relationship identifier="id-19afbef9a2314df19ee973a308adddcf" source="id-8dc4a1723df74d67bc914b77b2ff159c" target="id-b2a86896d88f43b48a6879cfa827f00c" xsi:type="Association" />
    <relationship identifier="id-0a83d98f42234e5d8675b1a614cc46ab" source="id-c4eb396033474ce8bd2a05a4d0cde67b" target="id-ce1a9420d2ff493e83a06af94a8de497" xsi:type="Composition" />
    <relationship identifier="id-963061f4c02040999ca6e69c40dac619" source="id-8abfc6fc96b94ec987298cb4e70f9534" target="id-c6dbbd23314e4cb4af45423bceab84a3" xsi:type="Triggering" />
    <relationship identifier="id-be1e0412c6b7427c903e4a0810be66ae" source="id-c4eb396033474ce8bd2a05a4d0cde67b" target="id-8abfc6fc96b94ec987298cb4e70f9534" xsi:type="Composition" />
    <relationship identifier="id-3d10c1c861534d93b4ac310a978da9ac" source="id-c4eb396033474ce8bd2a05a4d0cde67b" target="id-9861aa39153f46779719dc9a4219c557" xsi:type="Composition" />
    <relationship identifier="id-5bc26121bd6341f3bfb263b067c7a5c5" source="id-925b9cfd6e4843a393a18ba344e845d1" target="id-b2a86896d88f43b48a6879cfa827f00c" xsi:type="Association" />
    <relationship identifier="id-ecc785b6611047aaab5c19014506b28e" source="id-9861aa39153f46779719dc9a4219c557" target="id-0587c21ebdb94b308a326a435c143214" xsi:type="Association" />
    <relationship identifier="id-155a55ddf05444c28b2c4fc9e43ee00e" source="id-c4eb396033474ce8bd2a05a4d0cde67b" target="id-c6dbbd23314e4cb4af45423bceab84a3" xsi:type="Composition" />
    <relationship identifier="id-3eec8a4e78d34a4c9ee65e854bd84d20" source="id-c4eb396033474ce8bd2a05a4d0cde67b" target="id-8db2e104c8274bd69ace60e25e6bab68" xsi:type="Composition" />
    <relationship identifier="id-53c07e8819ce4b72ab2af917441b9e96" source="id-c6dbbd23314e4cb4af45423bceab84a3" target="id-9861aa39153f46779719dc9a4219c557" xsi:type="Influence" />
    <relationship identifier="id-94a74412e18f493093970c36fedf976a" source="id-c4eb396033474ce8bd2a05a4d0cde67b" target="id-94a5a202efbf4c8c872c1cd66131fd97" xsi:type="Composition" />
    <relationship identifier="id-ccebdddae62848f39b4fd582de7d9a81" source="id-ae0ad30a07c74aab9cb454cd53e490c9" target="id-d8cdf489f06441139b027b8d062326bf" xsi:type="Association" />
    <relationship identifier="id-0ed52ceaf7ba4c26bfcef5ac4106a7ec" source="id-c4eb396033474ce8bd2a05a4d0cde67b" target="id-b2a86896d88f43b48a6879cfa827f00c" xsi:type="Composition" />
    <relationship identifier="id-d8cdf489f06441139b027b8d062326bf" source="id-fadbd167f34b46cb9a3b8f9c56874e35" target="id-8abfc6fc96b94ec987298cb4e70f9534" xsi:type="Association" />
    <relationship identifier="id-8315a88afe5d4941bdafc64ca6a6a009" source="id-1d7a475888e74b40aeb9155845cbf97f" target="id-238287d9d98b452f8efb4ab654006ca9" xsi:type="Association" />
    <relationship identifier="id-71bb0c27349c4cacb253a9105d56c210" source="id-1d7a475888e74b40aeb9155845cbf97f" target="id-7a8da4358ecd4a9d8364a1a1163a99dd" xsi:type="Association" />
    <relationship identifier="id-853b9b30f4784f4193e37ce78ce66cd1" source="id-7a8da4358ecd4a9d8364a1a1163a99dd" target="id-ae0ad30a07c74aab9cb454cd53e490c9" xsi:type="Influence" />
    <relationship identifier="id-425924e7b38b4912b6750adff1d02d1e" source="id-c4eb396033474ce8bd2a05a4d0cde67b" target="id-7a8da4358ecd4a9d8364a1a1163a99dd" xsi:type="Composition" />
    <relationship identifier="id-ac76b84bb2d2413c80c3b4efc621004d" source="id-c4eb396033474ce8bd2a05a4d0cde67b" target="id-1d7a475888e74b40aeb9155845cbf97f" xsi:type="Composition" />
    <relationship identifier="id-5a4b106346994456bdb3ec4039fc5080" source="id-c4eb396033474ce8bd2a05a4d0cde67b" target="id-238287d9d98b452f8efb4ab654006ca9" xsi:type="Composition" />
    <relationship identifier="id-1fda490ab4954e828b6d667aaaa3e553" source="id-7a8da4358ecd4a9d8364a1a1163a99dd" target="id-8db2e104c8274bd69ace60e25e6bab68" xsi:type="Realization" />
    <relationship identifier="id-a0e0790a95aa4ff0b422fe368dee73fc" source="id-4f87a140b4a44ee9bde7eb8d808fdc1e" target="id-c4eb396033474ce8bd2a05a4d0cde67b" xsi:type="Association" />
    <relationship identifier="id-c50d398e75e345a89199e16703ccf17b" source="id-8779269d947848f0bd7a5e1c0dacf0b3" target="id-c4eb396033474ce8bd2a05a4d0cde67b" xsi:type="Realization" />
    <relationship identifier="id-92d984edd9bc40438ff67d5a141aa341" source="id-a9b7e3d685194071b70f08ca20736933" target="id-c4eb396033474ce8bd2a05a4d0cde67b" xsi:type="Triggering" />
    <relationship identifier="id-4a754e7aa8594401b23b2bd2b5b084ba" source="id-0d2bcec545154a5e8c7163d94a7028cc" target="id-9a438febac894ec1ae6c43ff080fbbec" xsi:type="Association" />
    <relationship identifier="id-0169ec37fd3f4c0dbfae5b091fee447a" source="id-8abfc6fc96b94ec987298cb4e70f9534" target="id-94a5a202efbf4c8c872c1cd66131fd97" xsi:type="Association" />
  </relationships>
  <views>
    <diagrams>
      <view identifier="id-a56b1a5e9598475596fca7d8f677f8e5" xsi:type="Diagram">
        <name>removing vulnerability</name>
        <node identifier="id-7400e73151ee4d7bba9be9e1427c0812" elementRef="id-4f87a140b4a44ee9bde7eb8d808fdc1e" xsi:type="Element" x="1080" y="216" w="146" h="67">
          <style>
            <fillColor r="255" g="224" b="224" a="100" />
            <lineColor r="92" g="92" b="92" a="100" />
            <font name="Lucida Grande" size="12">
              <color r="0" g="0" b="0" />
            </font>
          </style>
        </node>
        <node identifier="id-76367f584613469ba5d366fe6276e39f" elementRef="id-8779269d947848f0bd7a5e1c0dacf0b3" xsi:type="Element" x="1044" y="372" w="217" h="121">
          <style>
            <fillColor r="255" g="224" b="224" a="100" />
            <lineColor r="92" g="92" b="92" a="100" />
            <font name="Lucida Grande" size="12">
              <color r="0" g="0" b="0" />
            </font>
          </style>
          <node identifier="id-203fc61f6fa54f26a79fd6ff19d0d69c" elementRef="id-cdc80a27cc9f426c95564ea7df035ee9" xsi:type="Element" x="1068" y="408" w="141" h="69">
            <style>
              <fillColor r="255" g="224" b="224" a="100" />
              <lineColor r="92" g="92" b="92" a="100" />
              <font name="Lucida Grande" size="12">
                <color r="0" g="0" b="0" />
              </font>
            </style>
          </node>
        </node>
        <node identifier="id-fee254b6fe9d4ca788d501821ce22745" elementRef="id-a9b7e3d685194071b70f08ca20736933" xsi:type="Element" x="36" y="24" w="949" h="481">
          <style>
            <fillColor r="255" g="224" b="224" a="100" />
            <lineColor r="92" g="92" b="92" a="100" />
            <font name="Lucida Grande" size="12">
              <color r="0" g="0" b="0" />
            </font>
          </style>
          <node identifier="id-95486ed016f545aa8ba91f0fe37c653d" elementRef="id-066062762cb040ac9ee67b6de7637daf" xsi:type="Element" x="202" y="54" w="192" h="61">
            <style>
              <fillColor r="204" g="204" b="255" a="100" />
              <lineColor r="92" g="92" b="92" a="100" />
              <font name="Lucida Grande" size="12">
                <color r="0" g="0" b="0" />
              </font>
            </style>
          </node>
          <node identifier="id-bc00a0e4774649b49ed1fbae998b1d5b" elementRef="id-cd9f5a3f32124302841f16a30b36721d" xsi:type="Element" x="480" y="342" w="113" h="55">
            <style>
              <fillColor r="204" g="204" b="255" a="100" />
              <lineColor r="92" g="92" b="92" a="100" />
              <font name="Lucida Grande" size="12">
                <color r="0" g="0" b="0" />
              </font>
            </style>
          </node>
          <node identifier="id-1e5fc83e2eac465d9397159d8826a285" elementRef="id-1ed0b6680a954e9196691162796cea8c" xsi:type="Element" x="220" y="354" w="120" h="55">
            <style>
              <fillColor r="245" g="222" b="170" a="100" />
              <lineColor r="92" g="92" b="92" a="100" />
              <font name="Lucida Grande" size="12">
                <color r="0" g="0" b="0" />
              </font>
            </style>
          </node>
          <node identifier="id-29bd7ebdf9874a6c89f41014a41e6e64" elementRef="id-9a438febac894ec1ae6c43ff080fbbec" xsi:type="Element" x="220" y="432" w="120" h="55">
            <style>
              <fillColor r="245" g="222" b="170" a="100" />
              <lineColor r="92" g="92" b="92" a="100" />
              <font name="Lucida Grande" size="12">
                <color r="0" g="0" b="0" />
              </font>
            </style>
          </node>
          <node identifier="id-996055dab97044fd8f2234741ac35ff2" elementRef="id-5448b50b6a3e413294c52a46d1671dc3" xsi:type="Element" x="636" y="157" w="120" h="55">
            <style>
              <fillColor r="204" g="204" b="255" a="100" />
              <lineColor r="92" g="92" b="92" a="100" />
              <font name="Lucida Grande" size="12">
                <color r="0" g="0" b="0" />
              </font>
            </style>
          </node>
          <node identifier="id-75f0fd7b97684be9b09bfeeee2802d72" elementRef="id-72f90fbcbde249d1b7d9cb629e28ba96" xsi:type="Element" x="120" y="258" w="120" h="55">
            <style>
              <fillColor r="204" g="204" b="255" a="100" />
              <lineColor r="92" g="92" b="92" a="100" />
              <font name="Lucida Grande" size="12">
                <color r="0" g="0" b="0" />
              </font>
            </style>
          </node>
          <node identifier="id-6b779be5b88b4e5b9eeb235808987a19" elementRef="id-30966f8647ca4a76876a928272644c73" xsi:type="Element" x="636" y="258" w="120" h="55">
            <style>
              <fillColor r="204" g="204" b="255" a="100" />
              <lineColor r="92" g="92" b="92" a="100" />
              <font name="Lucida Grande" size="12">
                <color r="0" g="0" b="0" />
              </font>
            </style>
          </node>
          <node identifier="id-5290ae3df3a64f97a6d97509170a2d0e" elementRef="id-8eb5880c7679453f8d6b7b93414a7fd7" xsi:type="Element" x="264" y="258" w="120" h="55">
            <style>
              <fillColor r="255" g="255" b="181" a="100" />
              <lineColor r="92" g="92" b="92" a="100" />
              <font name="Lucida Grande" size="12">
                <color r="0" g="0" b="0" />
              </font>
            </style>
          </node>
          <node identifier="id-edc4b2fc10fc4e79b65acb3fd68b8697" elementRef="id-f203326e4119417cb9fb495a9bf26e2c" xsi:type="Element" x="420" y="157" w="120" h="55">
            <style>
              <fillColor r="255" g="255" b="181" a="100" />
              <lineColor r="92" g="92" b="92" a="100" />
              <font name="Lucida Grande" size="12">
                <color r="0" g="0" b="0" />
              </font>
            </style>
          </node>
          <node identifier="id-0ab078d7a5c14bbda88598126e9f398c" elementRef="id-aaf0583fdf6a4bb5be6e2f2869fdd2a4" xsi:type="Element" x="804" y="253" w="157" h="65">
            <style>
              <fillColor r="204" g="204" b="255" a="100" />
              <lineColor r="92" g="92" b="92" a="100" />
              <font name="Lucida Grande" size="12">
                <color r="0" g="0" b="0" />
              </font>
            </style>
          </node>
          <node identifier="id-3c6e1dbd6c934e42a403e08afe56fe65" elementRef="id-0d2bcec545154a5e8c7163d94a7028cc" xsi:type="Element" x="228" y="158" w="139" h="53">
            <style>
              <fillColor r="255" g="255" b="181" a="100" />
              <lineColor r="92" g="92" b="92" a="100" />
              <font name="Lucida Grande" size="12">
                <color r="0" g="0" b="0" />
              </font>
            </style>
          </node>
          <node identifier="id-76755f27c7f14c568b1b59200458ba4a" elementRef="id-db2b88e2589a442fab3bca7fa6f44ce5" xsi:type="Element" x="48" y="354" w="128" h="55">
            <style>
              <fillColor r="245" g="222" b="170" a="100" />
              <lineColor r="92" g="92" b="92" a="100" />
              <font name="Lucida Grande" size="12">
                <color r="0" g="0" b="0" />
              </font>
            </style>
          </node>
          <node identifier="id-ddd81e6c5ec44257876ab0a306096866" elementRef="id-44a9acf5b71f4fcf9be0da6022d7e6f1" xsi:type="Element" x="636" y="342" w="120" h="55">
            <style>
              <fillColor r="204" g="204" b="255" a="100" />
              <lineColor r="92" g="92" b="92" a="100" />
              <font name="Lucida Grande" size="12">
                <color r="0" g="0" b="0" />
              </font>
            </style>
          </node>
          <node identifier="id-a01f7c2cb1e74a299e4dd2eb5e2efbca" elementRef="id-dc6d70f7397348ec8cd606e8ce0a374d" xsi:type="Element" x="618" y="432" w="155" h="55">
            <style>
              <fillColor r="255" g="255" b="181" a="100" />
              <lineColor r="92" g="92" b="92" a="100" />
              <font name="Lucida Grande" size="12">
                <color r="0" g="0" b="0" />
              </font>
            </style>
          </node>
          <node identifier="id-9d562326388248d4928405b11936950a" elementRef="id-4639cd91bdf144f69f0553a0ffdd8449" xsi:type="Element" x="408" y="102" w="120" h="50">
            <style>
              <fillColor r="204" g="204" b="255" a="100" />
              <lineColor r="92" g="92" b="92" a="100" />
              <font name="Lucida Grande" size="12">
                <color r="0" g="0" b="0" />
              </font>
            </style>
          </node>
          <node identifier="id-3903b9461d064ce09c8682046d1bb4ae" elementRef="id-4458db07e6f640369b4dfab03b672d5d" xsi:type="Element" x="802" y="408" w="155" h="55">
            <style>
              <fillColor r="204" g="204" b="255" a="100" />
              <lineColor r="92" g="92" b="92" a="100" />
              <font name="Lucida Grande" size="12">
                <color r="0" g="0" b="0" />
              </font>
            </style>
          </node>
          <node identifier="id-f42c85c015644e9ab05278b7b6f76bde" elementRef="id-65fb95b4944f4c21814e7033a53c2ce5" xsi:type="Element" x="420" y="258" w="132" h="55">
            <style>
              <fillColor r="245" g="222" b="170" a="100" />
              <lineColor r="92" g="92" b="92" a="100" />
              <font name="Lucida Grande" size="12">
                <color r="0" g="0" b="0" />
              </font>
            </style>
          </node>
        </node>
        <node identifier="id-f646f2327e6c4239a62110af808dc40a" elementRef="id-c4eb396033474ce8bd2a05a4d0cde67b" xsi:type="Element" x="36" y="528" w="949" h="457">
          <style>
            <fillColor r="255" g="224" b="224" a="100" />
            <lineColor r="92" g="92" b="92" a="100" />
            <font name="Lucida Grande" size="12">
              <color r="0" g="0" b="0" />
            </font>
          </style>
          <node identifier="id-74b70767f3cc4fd6b206d1d1990c9834" elementRef="id-fadbd167f34b46cb9a3b8f9c56874e35" xsi:type="Element" x="202" y="558" w="192" h="61">
            <style>
              <fillColor r="204" g="204" b="255" a="100" />
              <lineColor r="92" g="92" b="92" a="100" />
              <font name="Lucida Grande" size="12">
                <color r="0" g="0" b="0" />
              </font>
            </style>
          </node>
          <node identifier="id-a0f4ed46dbd946e8bcccbd2662f58187" elementRef="id-137f794b34ff45c0b3365865a74b7697" xsi:type="Element" x="480" y="846" w="113" h="55">
            <style>
              <fillColor r="204" g="204" b="255" a="100" />
              <lineColor r="92" g="92" b="92" a="100" />
              <font name="Lucida Grande" size="12">
                <color r="0" g="0" b="0" />
              </font>
            </style>
          </node>
          <node identifier="id-e9f4856859aa48bc887ed1103202bede" elementRef="id-cdbb414a60b246b3a399fcac8d377dff" xsi:type="Element" x="144" y="846" w="120" h="55">
            <style>
              <fillColor r="245" g="222" b="170" a="100" />
              <lineColor r="92" g="92" b="92" a="100" />
              <font name="Lucida Grande" size="12">
                <color r="0" g="0" b="0" />
              </font>
            </style>
          </node>
          <node identifier="id-1321391405b54dc8a4362e57a9398eb9" elementRef="id-94a5a202efbf4c8c872c1cd66131fd97" xsi:type="Element" x="83" y="662" w="120" h="55">
            <style>
              <fillColor r="245" g="222" b="170" a="100" />
              <lineColor r="92" g="92" b="92" a="100" />
              <font name="Lucida Grande" size="12">
                <color r="0" g="0" b="0" />
              </font>
            </style>
          </node>
          <node identifier="id-de4ece456015485088a6ab4a3c5552f0" elementRef="id-9861aa39153f46779719dc9a4219c557" xsi:type="Element" x="618" y="661" w="120" h="55">
            <style>
              <fillColor r="204" g="204" b="255" a="100" />
              <lineColor r="92" g="92" b="92" a="100" />
              <font name="Lucida Grande" size="12">
                <color r="0" g="0" b="0" />
              </font>
            </style>
          </node>
          <node identifier="id-6ebbcff432d14e1fb7f5cf8444a4669d" elementRef="id-5f5ee5c36d384ce281bbce484364abb7" xsi:type="Element" x="83" y="762" w="120" h="55">
            <style>
              <fillColor r="204" g="204" b="255" a="100" />
              <lineColor r="92" g="92" b="92" a="100" />
              <font name="Lucida Grande" size="12">
                <color r="0" g="0" b="0" />
              </font>
            </style>
          </node>
          <node identifier="id-b7f4e2eff58d481cb3ce1a5bb0098275" elementRef="id-0587c21ebdb94b308a326a435c143214" xsi:type="Element" x="624" y="762" w="120" h="55">
            <style>
              <fillColor r="204" g="204" b="255" a="100" />
              <lineColor r="92" g="92" b="92" a="100" />
              <font name="Lucida Grande" size="12">
                <color r="0" g="0" b="0" />
              </font>
            </style>
          </node>
          <node identifier="id-73457ec8e6ea4e1783b2dff46c721c04" elementRef="id-ce1a9420d2ff493e83a06af94a8de497" xsi:type="Element" x="238" y="762" w="120" h="55">
            <style>
              <fillColor r="255" g="255" b="181" a="100" />
              <lineColor r="92" g="92" b="92" a="100" />
              <font name="Lucida Grande" size="12">
                <color r="0" g="0" b="0" />
              </font>
            </style>
          </node>
          <node identifier="id-1c0963c0352a4dc4973857f2a191462f" elementRef="id-c6dbbd23314e4cb4af45423bceab84a3" xsi:type="Element" x="420" y="661" w="120" h="55">
            <style>
              <fillColor r="255" g="255" b="181" a="100" />
              <lineColor r="92" g="92" b="92" a="100" />
              <font name="Lucida Grande" size="12">
                <color r="0" g="0" b="0" />
              </font>
            </style>
          </node>
          <node identifier="id-f6d33fec734c468d97fbdeb5417ce627" elementRef="id-8db2e104c8274bd69ace60e25e6bab68" xsi:type="Element" x="804" y="732" w="151" h="65">
            <style>
              <fillColor r="204" g="204" b="255" a="100" />
              <lineColor r="92" g="92" b="92" a="100" />
              <font name="Lucida Grande" size="12">
                <color r="0" g="0" b="0" />
              </font>
            </style>
          </node>
          <node identifier="id-abe2feb347d5488596e4a2f41d241377" elementRef="id-8abfc6fc96b94ec987298cb4e70f9534" xsi:type="Element" x="228" y="662" w="139" h="53">
            <style>
              <fillColor r="255" g="255" b="181" a="100" />
              <lineColor r="92" g="92" b="92" a="100" />
              <font name="Lucida Grande" size="12">
                <color r="0" g="0" b="0" />
              </font>
            </style>
          </node>
          <node identifier="id-f5bfc0f0d1fa4af3955e16d131750eea" elementRef="id-925b9cfd6e4843a393a18ba344e845d1" xsi:type="Element" x="636" y="846" w="120" h="55">
            <style>
              <fillColor r="204" g="204" b="255" a="100" />
              <lineColor r="92" g="92" b="92" a="100" />
              <font name="Lucida Grande" size="12">
                <color r="0" g="0" b="0" />
              </font>
            </style>
          </node>
          <node identifier="id-8cd7791c46ec4e70b975363323bc2b8f" elementRef="id-b2a86896d88f43b48a6879cfa827f00c" xsi:type="Element" x="618" y="924" w="155" h="55">
            <style>
              <fillColor r="255" g="255" b="181" a="100" />
              <lineColor r="92" g="92" b="92" a="100" />
              <font name="Lucida Grande" size="12">
                <color r="0" g="0" b="0" />
              </font>
            </style>
          </node>
          <node identifier="id-1cc4f7af13bd4756b7dca2ced12a0cf2" elementRef="id-ae0ad30a07c74aab9cb454cd53e490c9" xsi:type="Element" x="408" y="579" w="120" h="50">
            <style>
              <fillColor r="204" g="204" b="255" a="100" />
              <lineColor r="92" g="92" b="92" a="100" />
              <font name="Lucida Grande" size="12">
                <color r="0" g="0" b="0" />
              </font>
            </style>
          </node>
          <node identifier="id-1908355699b44f7190e3028bf4ca51c9" elementRef="id-8dc4a1723df74d67bc914b77b2ff159c" xsi:type="Element" x="802" y="912" w="155" h="67">
            <style>
              <fillColor r="204" g="204" b="255" a="100" />
              <lineColor r="92" g="92" b="92" a="100" />
              <font name="Lucida Grande" size="12">
                <color r="0" g="0" b="0" />
              </font>
            </style>
          </node>
          <node identifier="id-13378f6fb7d9449995bbc4c49ac749c2" elementRef="id-b361a52bf17d4200bda0489abc710423" xsi:type="Element" x="420" y="762" w="132" h="55">
            <style>
              <fillColor r="245" g="222" b="170" a="100" />
              <lineColor r="92" g="92" b="92" a="100" />
              <font name="Lucida Grande" size="12">
                <color r="0" g="0" b="0" />
              </font>
            </style>
          </node>
          <node identifier="id-0dfcca2a332c4e46990ac664858324e5" elementRef="id-7a8da4358ecd4a9d8364a1a1163a99dd" xsi:type="Element" x="618" y="576" w="120" h="55">
            <style>
              <fillColor r="255" g="255" b="181" a="100" />
              <lineColor r="92" g="92" b="92" a="100" />
              <font name="Lucida Grande" size="12">
                <color r="0" g="0" b="0" />
              </font>
            </style>
          </node>
          <node identifier="id-2f4257d1f9814181b8bf9d80783b4d77" elementRef="id-1d7a475888e74b40aeb9155845cbf97f" xsi:type="Element" x="820" y="561" w="120" h="55">
            <style>
              <fillColor r="245" g="222" b="170" a="100" />
              <lineColor r="92" g="92" b="92" a="100" />
              <font name="Lucida Grande" size="12">
                <color r="0" g="0" b="0" />
              </font>
            </style>
          </node>
          <node identifier="id-e59e7ac8a50948e2a30ca6302274aeb9" elementRef="id-238287d9d98b452f8efb4ab654006ca9" xsi:type="Element" x="795" y="636" w="169" h="55">
            <style>
              <fillColor r="245" g="222" b="170" a="100" />
              <lineColor r="92" g="92" b="92" a="100" />
              <font name="Lucida Grande" size="12">
                <color r="0" g="0" b="0" />
              </font>
            </style>
          </node>
        </node>
        <connection identifier="id-0ac98cc049284779b42d82898d54662d" relationshipRef="id-1897e6120d2d4931a3765adc597f92bf" xsi:type="Relationship" source="id-7400e73151ee4d7bba9be9e1427c0812" target="id-fee254b6fe9d4ca788d501821ce22745">
          <style>
            <lineColor r="0" g="0" b="0" />
            <font name="Lucida Grande" size="12">
              <color r="0" g="0" b="0" />
            </font>
          </style>
        </connection>
        <connection identifier="id-f5fae60214d042bc9df0e775d68be83b" relationshipRef="id-a0e0790a95aa4ff0b422fe368dee73fc" xsi:type="Relationship" source="id-7400e73151ee4d7bba9be9e1427c0812" target="id-f646f2327e6c4239a62110af808dc40a">
          <style>
            <lineColor r="0" g="0" b="0" />
            <font name="Lucida Grande" size="12">
              <color r="0" g="0" b="0" />
            </font>
          </style>
          <bendpoint x="1332" y="236" />
          <bendpoint x="1332" y="628" />
        </connection>
        <connection identifier="id-f84cd58f80114178b60d155b0e8d9534" relationshipRef="id-611ef4f63f5341c89ac7b41273d1420d" xsi:type="Relationship" source="id-76367f584613469ba5d366fe6276e39f" target="id-3903b9461d064ce09c8682046d1bb4ae">
          <style>
            <lineColor r="0" g="0" b="0" />
            <font name="Lucida Grande" size="12">
              <color r="0" g="0" b="0" />
            </font>
          </style>
        </connection>
        <connection identifier="id-f862ef5e5ea34e8d842a1e66a387a882" relationshipRef="id-c50d398e75e345a89199e16703ccf17b" xsi:type="Relationship" source="id-76367f584613469ba5d366fe6276e39f" target="id-f646f2327e6c4239a62110af808dc40a">
          <style>
            <lineColor r="0" g="0" b="0" />
            <font name="Lucida Grande" size="12">
              <color r="0" g="0" b="0" />
            </font>
          </style>
          <bendpoint x="1152" y="582" />
        </connection>
        <connection identifier="id-09000c94591840dbb784ec2821f8a79f" relationshipRef="id-508e70fc30c843c290978dafcd507e6f" xsi:type="Relationship" source="id-fee254b6fe9d4ca788d501821ce22745" target="id-76367f584613469ba5d366fe6276e39f">
          <style>
            <lineColor r="0" g="0" b="0" />
            <font name="Lucida Grande" size="12">
              <color r="0" g="0" b="0" />
            </font>
          </style>
          <bendpoint x="1020" y="420" />
        </connection>
        <connection identifier="id-962691e43bb04d99928065ae8a37892a" relationshipRef="id-92d984edd9bc40438ff67d5a141aa341" xsi:type="Relationship" source="id-fee254b6fe9d4ca788d501821ce22745" target="id-f646f2327e6c4239a62110af808dc40a">
          <style>
            <lineColor r="0" g="0" b="0" />
            <font name="Lucida Grande" size="12">
              <color r="0" g="0" b="0" />
            </font>
          </style>
        </connection>
        <connection identifier="id-0973b2d150cc4cc5a88a52d3e379f980" relationshipRef="id-9018cf164cf44c7e86635cfa05817822" xsi:type="Relationship" source="id-95486ed016f545aa8ba91f0fe37c653d" target="id-3c6e1dbd6c934e42a403e08afe56fe65">
          <style>
            <lineColor r="0" g="0" b="0" />
            <font name="Lucida Grande" size="12">
              <color r="0" g="0" b="0" />
            </font>
          </style>
        </connection>
        <connection identifier="id-893f6871b93642a59b962fe02342319d" relationshipRef="id-b8c06dd9881a456181ade86a38246515" xsi:type="Relationship" source="id-bc00a0e4774649b49ed1fbae998b1d5b" target="id-ddd81e6c5ec44257876ab0a306096866">
          <style>
            <lineColor r="0" g="0" b="0" />
            <font name="Lucida Grande" size="12">
              <color r="0" g="0" b="0" />
            </font>
          </style>
        </connection>
        <connection identifier="id-b36d65505fc6407e8ec8f1e711c6697d" relationshipRef="id-a0cb8839341c4c37a3aed6d81bfc1d2e" xsi:type="Relationship" source="id-29bd7ebdf9874a6c89f41014a41e6e64" target="id-76755f27c7f14c568b1b59200458ba4a">
          <style>
            <lineColor r="0" g="0" b="0" />
            <font name="Lucida Grande" size="12">
              <color r="0" g="0" b="0" />
            </font>
          </style>
          <bendpoint x="108" y="462" />
        </connection>
        <connection identifier="id-33efeabf5257479c9ce3427e2e2baf00" relationshipRef="id-0c0916161df24ce08bf63290d9eadc79" xsi:type="Relationship" source="id-996055dab97044fd8f2234741ac35ff2" target="id-6b779be5b88b4e5b9eeb235808987a19">
          <style>
            <lineColor r="0" g="0" b="0" />
            <font name="Lucida Grande" size="12">
              <color r="0" g="0" b="0" />
            </font>
          </style>
        </connection>
        <connection identifier="id-efd998d6778d46f08f98f78806e4a048" relationshipRef="id-fe9d61c86d864d7993f1541258d205af" xsi:type="Relationship" source="id-75f0fd7b97684be9b09bfeeee2802d72" target="id-76755f27c7f14c568b1b59200458ba4a">
          <style>
            <lineColor r="0" g="0" b="0" />
            <font name="Lucida Grande" size="12">
              <color r="0" g="0" b="0" />
            </font>
          </style>
        </connection>
        <connection identifier="id-75c37a7905e748f5a9759896846f4d85" relationshipRef="id-4afb5763897b47f0a3cafad3a6458fc0" xsi:type="Relationship" source="id-75f0fd7b97684be9b09bfeeee2802d72" target="id-1e5fc83e2eac465d9397159d8826a285">
          <style>
            <lineColor r="0" g="0" b="0" />
            <font name="Lucida Grande" size="12">
              <color r="0" g="0" b="0" />
            </font>
          </style>
        </connection>
        <connection identifier="id-eb06979b33364f9da22af041529087d3" relationshipRef="id-8c665d1c707146a1b7a2e4d935049ceb" xsi:type="Relationship" source="id-5290ae3df3a64f97a6d97509170a2d0e" target="id-3c6e1dbd6c934e42a403e08afe56fe65">
          <style>
            <lineColor r="0" g="0" b="0" />
            <font name="Lucida Grande" size="12">
              <color r="0" g="0" b="0" />
            </font>
          </style>
        </connection>
        <connection identifier="id-e0a26db88de44df2a53efaf9215024ee" relationshipRef="id-75db1a1a34b34bf4b3ac0bda16b19866" xsi:type="Relationship" source="id-5290ae3df3a64f97a6d97509170a2d0e" target="id-75f0fd7b97684be9b09bfeeee2802d72">
          <style>
            <lineColor r="0" g="0" b="0" />
            <font name="Lucida Grande" size="12">
              <color r="0" g="0" b="0" />
            </font>
          </style>
        </connection>
        <connection identifier="id-1023d5f4d34942a4b53df0894ac18c4c" relationshipRef="id-00762873943a4e71a8b386f6e6e7a235" xsi:type="Relationship" source="id-5290ae3df3a64f97a6d97509170a2d0e" target="id-1e5fc83e2eac465d9397159d8826a285">
          <style>
            <lineColor r="0" g="0" b="0" />
            <font name="Lucida Grande" size="12">
              <color r="0" g="0" b="0" />
            </font>
          </style>
        </connection>
        <connection identifier="id-47b5b9298b164cf3a2e9f3f814cb3564" relationshipRef="id-4c8260c3eb9f44d5b897ed413873d606" xsi:type="Relationship" source="id-edc4b2fc10fc4e79b65acb3fd68b8697" target="id-f42c85c015644e9ab05278b7b6f76bde">
          <style>
            <lineColor r="0" g="0" b="0" />
            <font name="Lucida Grande" size="12">
              <color r="0" g="0" b="0" />
            </font>
          </style>
        </connection>
        <connection identifier="id-d5ec6e36129d4e3bab9e9a97fec9580f" relationshipRef="id-9508b116a7e9403fa829aea08e195bf2" xsi:type="Relationship" source="id-edc4b2fc10fc4e79b65acb3fd68b8697" target="id-996055dab97044fd8f2234741ac35ff2">
          <style>
            <lineColor r="0" g="0" b="0" />
            <font name="Lucida Grande" size="12">
              <color r="0" g="0" b="0" />
            </font>
          </style>
        </connection>
        <connection identifier="id-4dd31f1b6bb54fd09ab4eff9887699ba" relationshipRef="id-c0e2cbf0c39041958f37b1bd2a47fee6" xsi:type="Relationship" source="id-0ab078d7a5c14bbda88598126e9f398c" target="id-6b779be5b88b4e5b9eeb235808987a19">
          <style>
            <lineColor r="0" g="0" b="0" />
            <font name="Lucida Grande" size="12">
              <color r="0" g="0" b="0" />
            </font>
          </style>
        </connection>
        <connection identifier="id-2eb5d2195e4643bb9739e0ba3883183a" relationshipRef="id-13b51d0652cd4a18a32486a023e7b9c1" xsi:type="Relationship" source="id-0ab078d7a5c14bbda88598126e9f398c" target="id-ddd81e6c5ec44257876ab0a306096866">
          <style>
            <lineColor r="0" g="0" b="0" />
            <font name="Lucida Grande" size="12">
              <color r="0" g="0" b="0" />
            </font>
          </style>
          <bendpoint x="841" y="372" />
        </connection>
        <connection identifier="id-75a692c622654b0ea01dbf6053bd21e0" relationshipRef="id-51a163be51604b4d8915a4bdb987eba1" xsi:type="Relationship" source="id-3c6e1dbd6c934e42a403e08afe56fe65" target="id-edc4b2fc10fc4e79b65acb3fd68b8697">
          <style>
            <lineColor r="0" g="0" b="0" />
            <font name="Lucida Grande" size="12">
              <color r="0" g="0" b="0" />
            </font>
          </style>
        </connection>
        <connection identifier="id-f42a13fde0864b66a92d07629748e3dc" relationshipRef="id-41a483a81dbd4d96afeabdd570bf62e1" xsi:type="Relationship" source="id-3c6e1dbd6c934e42a403e08afe56fe65" target="id-76755f27c7f14c568b1b59200458ba4a">
          <style>
            <lineColor r="0" g="0" b="0" />
            <font name="Lucida Grande" size="12">
              <color r="0" g="0" b="0" />
            </font>
          </style>
          <bendpoint x="108" y="186" />
        </connection>
        <connection identifier="id-ea8e9e3ab8e6470fa10483abe0ea0f7c" relationshipRef="id-4a754e7aa8594401b23b2bd2b5b084ba" xsi:type="Relationship" source="id-3c6e1dbd6c934e42a403e08afe56fe65" target="id-29bd7ebdf9874a6c89f41014a41e6e64">
          <style>
            <lineColor r="0" g="0" b="0" />
            <font name="Lucida Grande" size="12">
              <color r="0" g="0" b="0" />
            </font>
          </style>
          <bendpoint x="396" y="192" />
          <bendpoint x="396" y="456" />
        </connection>
        <connection identifier="id-f1747d104cce49dbb86eb49b07de3a36" relationshipRef="id-feab20f73b824c3981362ec28d1f265a" xsi:type="Relationship" source="id-76755f27c7f14c568b1b59200458ba4a" target="id-1e5fc83e2eac465d9397159d8826a285">
          <style>
            <lineColor r="0" g="0" b="0" />
            <font name="Lucida Grande" size="12">
              <color r="0" g="0" b="0" />
            </font>
          </style>
        </connection>
        <connection identifier="id-0d76ba028e604b79ba7438b20718f545" relationshipRef="id-3535c6b6554b4862b91b01caf2a25d37" xsi:type="Relationship" source="id-ddd81e6c5ec44257876ab0a306096866" target="id-a01f7c2cb1e74a299e4dd2eb5e2efbca">
          <style>
            <lineColor r="0" g="0" b="0" />
            <font name="Lucida Grande" size="12">
              <color r="0" g="0" b="0" />
            </font>
          </style>
        </connection>
        <connection identifier="id-93c082bcf84c4d84bfb793039843543a" relationshipRef="id-cc19b9fa547243d582c359496bfd1211" xsi:type="Relationship" source="id-a01f7c2cb1e74a299e4dd2eb5e2efbca" target="id-76367f584613469ba5d366fe6276e39f">
          <style>
            <lineColor r="0" g="0" b="0" />
            <font name="Lucida Grande" size="12">
              <color r="0" g="0" b="0" />
            </font>
          </style>
          <bendpoint x="903" y="474" />
        </connection>
        <connection identifier="id-609cdb99a39e4e62bba87d201bd7bc86" relationshipRef="id-d428cba899b74983abe9e038b99c566b" xsi:type="Relationship" source="id-9d562326388248d4928405b11936950a" target="id-0973b2d150cc4cc5a88a52d3e379f980">
          <style>
            <lineColor r="0" g="0" b="0" />
            <font name="Lucida Grande" size="12">
              <color r="0" g="0" b="0" />
            </font>
          </style>
        </connection>
        <connection identifier="id-972d9faa526c456ca678f50dc6546584" relationshipRef="id-4c24075255034d328340f97aa6f18f63" xsi:type="Relationship" source="id-3903b9461d064ce09c8682046d1bb4ae" target="id-0ab078d7a5c14bbda88598126e9f398c">
          <style>
            <lineColor r="0" g="0" b="0" />
            <font name="Lucida Grande" size="12">
              <color r="0" g="0" b="0" />
            </font>
          </style>
        </connection>
        <connection identifier="id-c2d1452876184356a13e90fc1bc8e010" relationshipRef="id-dce0f257602f4eaa8d10a01120bf148d" xsi:type="Relationship" source="id-3903b9461d064ce09c8682046d1bb4ae" target="id-a01f7c2cb1e74a299e4dd2eb5e2efbca">
          <style>
            <lineColor r="0" g="0" b="0" />
            <font name="Lucida Grande" size="12">
              <color r="0" g="0" b="0" />
            </font>
          </style>
        </connection>
        <connection identifier="id-3ffdd000153d4e1c912eb63ba60c5cd4" relationshipRef="id-d8cdf489f06441139b027b8d062326bf" xsi:type="Relationship" source="id-74b70767f3cc4fd6b206d1d1990c9834" target="id-abe2feb347d5488596e4a2f41d241377">
          <style>
            <lineColor r="0" g="0" b="0" />
            <font name="Lucida Grande" size="12">
              <color r="0" g="0" b="0" />
            </font>
          </style>
        </connection>
        <connection identifier="id-a873492d210f46e5b91636a69e1a45bb" relationshipRef="id-bfb34071fb364ad8ab280cfb4c2b60b4" xsi:type="Relationship" source="id-a0f4ed46dbd946e8bcccbd2662f58187" target="id-f5bfc0f0d1fa4af3955e16d131750eea">
          <style>
            <lineColor r="0" g="0" b="0" />
            <font name="Lucida Grande" size="12">
              <color r="0" g="0" b="0" />
            </font>
          </style>
        </connection>
        <connection identifier="id-3216436246944dc99a07fdefeda0d16e" relationshipRef="id-ecc785b6611047aaab5c19014506b28e" xsi:type="Relationship" source="id-de4ece456015485088a6ab4a3c5552f0" target="id-b7f4e2eff58d481cb3ce1a5bb0098275">
          <style>
            <lineColor r="0" g="0" b="0" />
            <font name="Lucida Grande" size="12">
              <color r="0" g="0" b="0" />
            </font>
          </style>
        </connection>
        <connection identifier="id-5eaad984e71f4de3bc5434c37df0f492" relationshipRef="id-3ab9a726e7cf4b63b5901242881acd02" xsi:type="Relationship" source="id-6ebbcff432d14e1fb7f5cf8444a4669d" target="id-e9f4856859aa48bc887ed1103202bede">
          <style>
            <lineColor r="0" g="0" b="0" />
            <font name="Lucida Grande" size="12">
              <color r="0" g="0" b="0" />
            </font>
          </style>
          <bendpoint x="108" y="876" />
        </connection>
        <connection identifier="id-5d96b9e8afb14d569b00469a42ff0eba" relationshipRef="id-3b7e610dcbc3449aacabbb43e5a59eaa" xsi:type="Relationship" source="id-73457ec8e6ea4e1783b2dff46c721c04" target="id-e9f4856859aa48bc887ed1103202bede">
          <style>
            <lineColor r="0" g="0" b="0" />
            <font name="Lucida Grande" size="12">
              <color r="0" g="0" b="0" />
            </font>
          </style>
          <bendpoint x="300" y="876" />
        </connection>
        <connection identifier="id-9ad9d5307d294558836ff9e3b7d1a482" relationshipRef="id-6951aaf2f6c14a81a1a7dcdbb39daefd" xsi:type="Relationship" source="id-73457ec8e6ea4e1783b2dff46c721c04" target="id-abe2feb347d5488596e4a2f41d241377">
          <style>
            <lineColor r="0" g="0" b="0" />
            <font name="Lucida Grande" size="12">
              <color r="0" g="0" b="0" />
            </font>
          </style>
        </connection>
        <connection identifier="id-bd0c5e9666f3408b84f923f3609b009c" relationshipRef="id-378dd1b4f0b04d57bf6f0462243f978d" xsi:type="Relationship" source="id-73457ec8e6ea4e1783b2dff46c721c04" target="id-6ebbcff432d14e1fb7f5cf8444a4669d">
          <style>
            <lineColor r="0" g="0" b="0" />
            <font name="Lucida Grande" size="12">
              <color r="0" g="0" b="0" />
            </font>
          </style>
        </connection>
        <connection identifier="id-a4667a5359874ddd9b0939010a5a506a" relationshipRef="id-b3feb2c96fc94fa1b2c4db19aebdf190" xsi:type="Relationship" source="id-1c0963c0352a4dc4973857f2a191462f" target="id-13378f6fb7d9449995bbc4c49ac749c2">
          <style>
            <lineColor r="0" g="0" b="0" />
            <font name="Lucida Grande" size="12">
              <color r="0" g="0" b="0" />
            </font>
          </style>
        </connection>
        <connection identifier="id-3079ac5a1f4f494e9af700252cb529c9" relationshipRef="id-53c07e8819ce4b72ab2af917441b9e96" xsi:type="Relationship" source="id-1c0963c0352a4dc4973857f2a191462f" target="id-de4ece456015485088a6ab4a3c5552f0">
          <style>
            <lineColor r="0" g="0" b="0" />
            <font name="Lucida Grande" size="12">
              <color r="0" g="0" b="0" />
            </font>
          </style>
        </connection>
        <connection identifier="id-4fc0d52e0c9642d8ace6e3acae33e4f8" relationshipRef="id-41474e853a634a00b5ca15179549a105" xsi:type="Relationship" source="id-f6d33fec734c468d97fbdeb5417ce627" target="id-b7f4e2eff58d481cb3ce1a5bb0098275">
          <style>
            <lineColor r="0" g="0" b="0" />
            <font name="Lucida Grande" size="12">
              <color r="0" g="0" b="0" />
            </font>
          </style>
        </connection>
        <connection identifier="id-769c9226d29d4fb9b92650cfe3a19e5f" relationshipRef="id-5123d8dfcde34f969c5d3f56b7ca10b7" xsi:type="Relationship" source="id-f6d33fec734c468d97fbdeb5417ce627" target="id-f5bfc0f0d1fa4af3955e16d131750eea">
          <style>
            <lineColor r="0" g="0" b="0" />
            <font name="Lucida Grande" size="12">
              <color r="0" g="0" b="0" />
            </font>
          </style>
          <bendpoint x="935" y="893" />
        </connection>
        <connection identifier="id-9ff7aff45dc845f9843e512881be9562" relationshipRef="id-963061f4c02040999ca6e69c40dac619" xsi:type="Relationship" source="id-abe2feb347d5488596e4a2f41d241377" target="id-1c0963c0352a4dc4973857f2a191462f">
          <style>
            <lineColor r="0" g="0" b="0" />
            <font name="Lucida Grande" size="12">
              <color r="0" g="0" b="0" />
            </font>
          </style>
        </connection>
        <connection identifier="id-b75db82fcd4c4ce29c3431b98cbd0883" relationshipRef="id-0169ec37fd3f4c0dbfae5b091fee447a" xsi:type="Relationship" source="id-abe2feb347d5488596e4a2f41d241377" target="id-1321391405b54dc8a4362e57a9398eb9">
          <style>
            <lineColor r="0" g="0" b="0" />
            <font name="Lucida Grande" size="12">
              <color r="0" g="0" b="0" />
            </font>
          </style>
        </connection>
        <connection identifier="id-d90ec3d7ec354ca2a60321c6d9fccaa5" relationshipRef="id-5bc26121bd6341f3bfb263b067c7a5c5" xsi:type="Relationship" source="id-f5bfc0f0d1fa4af3955e16d131750eea" target="id-8cd7791c46ec4e70b975363323bc2b8f">
          <style>
            <lineColor r="0" g="0" b="0" />
            <font name="Lucida Grande" size="12">
              <color r="0" g="0" b="0" />
            </font>
          </style>
        </connection>
        <connection identifier="id-b9a3817113134503ab83c9b81b5b25fb" relationshipRef="id-ccebdddae62848f39b4fd582de7d9a81" xsi:type="Relationship" source="id-1cc4f7af13bd4756b7dca2ced12a0cf2" target="id-3ffdd000153d4e1c912eb63ba60c5cd4">
          <style>
            <lineColor r="0" g="0" b="0" />
            <font name="Lucida Grande" size="12">
              <color r="0" g="0" b="0" />
            </font>
          </style>
        </connection>
        <connection identifier="id-1a899f2294e74bed97e0124825831dd1" relationshipRef="id-19afbef9a2314df19ee973a308adddcf" xsi:type="Relationship" source="id-1908355699b44f7190e3028bf4ca51c9" target="id-8cd7791c46ec4e70b975363323bc2b8f">
          <style>
            <lineColor r="0" g="0" b="0" />
            <font name="Lucida Grande" size="12">
              <color r="0" g="0" b="0" />
            </font>
          </style>
        </connection>
        <connection identifier="id-24bdaf85b37648d9bf277e7da5c81efd" relationshipRef="id-80ca56d355504cf5b12daa1c4566b513" xsi:type="Relationship" source="id-1908355699b44f7190e3028bf4ca51c9" target="id-f6d33fec734c468d97fbdeb5417ce627">
          <style>
            <lineColor r="0" g="0" b="0" />
            <font name="Lucida Grande" size="12">
              <color r="0" g="0" b="0" />
            </font>
          </style>
        </connection>
        <connection identifier="id-d4106465d4c74c959d0c867ac2f41b84" relationshipRef="id-853b9b30f4784f4193e37ce78ce66cd1" xsi:type="Relationship" source="id-0dfcca2a332c4e46990ac664858324e5" target="id-1cc4f7af13bd4756b7dca2ced12a0cf2">
          <style>
            <lineColor r="0" g="0" b="0" />
            <font name="Lucida Grande" size="12">
              <color r="0" g="0" b="0" />
            </font>
          </style>
        </connection>
        <connection identifier="id-accfe59413cc4f768afe629f7676af10" relationshipRef="id-1fda490ab4954e828b6d667aaaa3e553" xsi:type="Relationship" source="id-0dfcca2a332c4e46990ac664858324e5" target="id-f6d33fec734c468d97fbdeb5417ce627">
          <style>
            <lineColor r="0" g="0" b="0" />
            <font name="Lucida Grande" size="12">
              <color r="0" g="0" b="0" />
            </font>
          </style>
        </connection>
        <connection identifier="id-b96db5189675481f88a2b55706d7c3fd" relationshipRef="id-8315a88afe5d4941bdafc64ca6a6a009" xsi:type="Relationship" source="id-2f4257d1f9814181b8bf9d80783b4d77" target="id-e59e7ac8a50948e2a30ca6302274aeb9">
          <style>
            <lineColor r="0" g="0" b="0" />
            <font name="Lucida Grande" size="12">
              <color r="0" g="0" b="0" />
            </font>
          </style>
        </connection>
        <connection identifier="id-1dc3220d8a2945bebcd702dfd38d3323" relationshipRef="id-71bb0c27349c4cacb253a9105d56c210" xsi:type="Relationship" source="id-2f4257d1f9814181b8bf9d80783b4d77" target="id-0dfcca2a332c4e46990ac664858324e5">
          <style>
            <lineColor r="0" g="0" b="0" />
            <font name="Lucida Grande" size="12">
              <color r="0" g="0" b="0" />
            </font>
          </style>
        </connection>
      </view>
    </diagrams>
  </views>
</model>
