{"identifier":"https://me.big.tuwien.ac.at/EAModelSet/076abb71-28da-42ee-b1e8-edeca1a7e431","archimateId":"076abb71-28da-42ee-b1e8-edeca1a7e431","name":"IAAM","description":"","formats":["XML","CSV","JSON","ARCHIMATE"],"source":"GitHub","repository":"","license":"","sourceFile":"raw-data/github/archimate/iaam.archimate","sourceFormat":"ARCHIMATE","timestamp":"2023-07-06T09:29:17","tags":[],"duplicates":[],"language":"en","elements":[{"id":"5550db4c-4a1a-4442-897e-a3f632bf20e2","name":"User","type":"BusinessActor","layer":"business"},{"id":"cfada6b3-384f-43f4-9140-6de9f758ec68","name":"Business Actor","type":"BusinessActor","layer":"business"},{"id":"f2e70629-ca6b-4833-8f94-e17f9f819343","name":"User","type":"BusinessRole","layer":"business"},{"id":"5dfa85f0-c147-4a4c-8514-37e104e3f7cd","name":"System administrator","type":"BusinessRole","layer":"business"},{"id":"718b1442-6c85-48f9-a17e-4d6605073424","name":"Domain administrator","type":"BusinessRole","layer":"business"},{"id":"1e0fa4b7-525f-45ad-b3a4-a5a5e9ac4c5e","name":"User","type":"BusinessRole","layer":"business"},{"id":"93e90e66-ffcf-44bf-baef-c57d72d02d1a","name":"Domain manager","type":"BusinessRole","layer":"business"},{"id":"8d9e4ae3-d117-4b46-8cf9-68ba25df05f9","name":"Client","type":"BusinessActor","layer":"business"},{"id":"e0c0489b-c126-4f66-9f0e-6fbfcb69df9c","name":"Authentication","type":"BusinessProcess","layer":"business"},{"id":"d145db9c-7457-4af2-a2ac-46b48eb9eaa7","name":"Request resource","type":"BusinessEvent","layer":"business"},{"id":"5674cda6-b52e-46be-9790-68e679ed691f","name":"Prompt credentials","type":"BusinessEvent","layer":"business"},{"id":"67b2884e-5d05-40df-9a55-4bc802b810d9","name":"User","type":"BusinessActor","layer":"business"},{"id":"a4b1eac7-173e-4279-b0b0-9a589d93788f","name":"Request resource","type":"BusinessEvent","layer":"business"},{"id":"070945dc-0640-4a5e-9ca5-1db0f5ae556f","name":"Request authorisation","type":"BusinessEvent","layer":"business"},{"id":"f8c901b9-b294-4d27-9800-bed5c39eb339","name":"Request credentials","type":"BusinessEvent","layer":"business"},{"id":"619f5847-182e-4f3e-bbac-a5b7ee50b6d8","name":"Submit credentials","type":"BusinessEvent","layer":"business"},{"id":"6019d36c-f2e6-4b23-bd02-c6973785c3a4","name":"Serve resource","type":"BusinessEvent","layer":"business"},{"id":"6ed688e5-77f5-4a1b-8e02-3d5706b69a69","name":"Query authorisation","type":"BusinessEvent","layer":"business"},{"id":"2799c8d1-bf48-4a85-9e22-9a1768174671","name":"Domain manager","type":"BusinessRole","layer":"business"},{"id":"b03787b2-29b4-4809-a5fd-bb55dcf11e24","name":"Domain management","type":"BusinessInterface","layer":"business"},{"id":"1845c80e-ae85-42bc-bf83-5a2178c8309c","name":"Resource owner","type":"BusinessRole","layer":"business"},{"id":"2253e2ab-566e-4dc6-a601-d6235c95e800","name":"Authentication & Authorisation","type":"BusinessFunction","layer":"business"},{"id":"d37a948a-68d8-4fc3-a115-c4148742411f","name":"Access control","type":"ApplicationInterface","layer":"application"},{"id":"e17441b6-0b34-4564-8c28-e423a3302995","name":"HTTP access filter","type":"ApplicationComponent","layer":"application"},{"id":"2d196b06-f564-41aa-871d-b9420b8c4d63","name":"Service broker","type":"ApplicationComponent","layer":"application"},{"id":"2f51ced6-69a0-41f9-baf8-199d2e174cb6","name":"Identity providers","type":"ApplicationComponent","layer":"application"},{"id":"e01634d6-b45f-4e78-9940-33d18bae7db9","name":"Revocation list","type":"ApplicationComponent","layer":"application"},{"id":"fc39a254-f49f-406a-81aa-e5b1795abcc1","name":"Domain management","type":"ApplicationInterface","layer":"application"},{"id":"f42f25af-ab95-494b-98f2-2d0046577348","name":"Authentication","type":"ApplicationInterface","layer":"application"},{"id":"72888d0d-499c-4a65-b8a8-ac2cd70f8b2f","name":"Domain manager","type":"ApplicationComponent","layer":"application"},{"id":"5db4ba15-7ebd-42ea-a75e-177d54eacc0c","name":"Service discovery","type":"ApplicationInterface","layer":"application"},{"id":"b0cbfb5f-f536-478b-aafb-02e2f090cce8","name":"Resource","type":"ApplicationComponent","layer":"application"},{"id":"40f4d602-5781-4f68-8080-0a32a75e02db","name":"Resource","type":"ApplicationComponent","layer":"application"},{"id":"1ce8e1bd-2b56-4c1a-9821-eb18372af7fd","name":"Issue token","type":"ApplicationEvent","layer":"application"},{"id":"34160d1d-a800-4094-ad84-fbe55a2275f1","name":"Auth Server","type":"ApplicationComponent","layer":"application"},{"id":"8c9abf28-df80-4c44-b29a-8386ff5182fb","name":"Auth Server","type":"ApplicationComponent","layer":"application"},{"id":"54fbe83d-1287-4a2f-a630-0abdf9289038","name":"Request authorisation","type":"ApplicationEvent","layer":"application"},{"id":"82938c04-4569-4a9e-874b-c9d659a26d8c","name":"Request authorisation challenge","type":"ApplicationEvent","layer":"application"},{"id":"aea379bb-b506-43c7-a168-19bd38778eb7","name":"Submit token","type":"ApplicationEvent","layer":"application"},{"id":"780bffa8-ce3a-4f96-bc3b-9488b33fd16e","name":"Validate token","type":"ApplicationEvent","layer":"application"},{"id":"1d8cac69-c86e-4496-bf87-2280a7c2f2ea","name":"Validate token","type":"ApplicationEvent","layer":"application"},{"id":"91b4e34d-e14a-4dc6-b228-91dde4abebb3","name":"Validation result","type":"ApplicationEvent","layer":"application"},{"id":"f5eec8ed-6054-4345-bcc6-fe4d9bcededc","name":"Domain management","type":"ApplicationInterface","layer":"application"},{"id":"d7cad2e5-c376-4199-90f7-caab88745394","name":"Domain manager","type":"ApplicationComponent","layer":"application"},{"id":"64374b03-1816-4765-997d-f8df9941fe32","name":"Workflow editor","type":"ApplicationComponent","layer":"application"},{"id":"5cbf4332-390f-433c-822c-e1a4877812d6","name":"Identity repository manager","type":"ApplicationComponent","layer":"application"},{"id":"717fdbab-64d2-4e0a-ba45-93711c1093a6","name":"Authentication provider manager","type":"ApplicationComponent","layer":"application"},{"id":"7ac4da2b-f5ae-4dfe-bffe-3ebb9fe072f7","name":"Domain","type":"DataObject","layer":"application"},{"id":"e27a4009-6801-497b-84ea-072d988e10eb","name":"Authentication workflow","type":"DataObject","layer":"application"},{"id":"3f994e7a-335c-4d70-9a5b-19c09040852e","name":"Authentication provider configuration","type":"DataObject","layer":"application"},{"id":"0a79fed5-0b5d-4ca3-b2b8-6079f5b46256","name":"Authentication task","type":"DataObject","layer":"application"},{"id":"e00f71db-86bc-469e-baef-fee6d4263aa1","name":"Condition","type":"DataObject","layer":"application"},{"id":"78110dc2-68b6-4536-aa24-e4256d4fb4b3","name":"Identity repository","type":"DataObject","layer":"application"},{"id":"647a61b0-7ac0-4f5f-8961-b9141de81dca","name":"Client","type":"DataObject","layer":"application"},{"id":"f1a2246f-4f83-4c0c-8777-88f72552fc35","name":"Worfklow manager","type":"ApplicationComponent","layer":"application"},{"id":"1eec2fcb-cee5-4fe4-a8c9-8123f8068f35","name":"Authentication provider","type":"DataObject","layer":"application"},{"id":"fbfa9aab-c3ef-48f7-a7e6-dcce699ec81a","name":"Service broker","type":"ApplicationComponent","layer":"application"},{"id":"17dfe88c-82ea-4e1a-b52c-f00e53791b97","name":"Service discovery","type":"ApplicationInterface","layer":"application"},{"id":"2d110999-aa0a-4dcb-ace8-7c280331973b","name":"Service registration","type":"ApplicationInterface","layer":"application"},{"id":"22faabb5-ce46-41d4-abce-93270746f0a5","name":"Resources","type":"ApplicationComponent","layer":"application"},{"id":"2d0035e4-a197-441e-9a4e-17dc1de5a8fa","name":"Domain manager","type":"ApplicationComponent","layer":"application"},{"id":"9ee3dd28-0eaa-4fd7-b8f9-f677aa699cdb","name":"Resources","type":"ApplicationComponent","layer":"application"},{"id":"199a3c00-f416-4c9b-a056-17c4e1a1fb13","name":"Internet gateway","type":"Node","layer":"technology"},{"id":"e6d88220-c7be-42e9-86fe-cc7976e4a3a1","name":"Internet","type":"CommunicationNetwork","layer":"technology"},{"id":"63ec9603-69bf-42b2-9249-ae723dac179b","name":"Network domains","type":"CommunicationNetwork","layer":"technology"},{"id":"60a4cc88-f66b-4e95-9081-44619f466d96","name":"Other networks","type":"CommunicationNetwork","layer":"technology"},{"id":"4fe9439a-d383-402c-aef8-63702fe9ac0c","name":"Domain gateways","type":"Node","layer":"technology"},{"id":"2613f0ac-b14e-43dd-90a8-86247a6920e8","name":"Other network gateway","type":"Node","layer":"technology"},{"id":"2c283e2f-0688-4529-badc-a03a16f4b171","name":"Load balancer","type":"Node","layer":"technology"},{"id":"d9aa5077-29d5-4cf9-93f2-bf2d4d415868","name":"Technology Interface","type":"TechnologyInterface","layer":"technology"},{"id":"e34c6cbf-d671-4c36-9683-d5244494aa72","name":"DC network","type":"CommunicationNetwork","layer":"technology"},{"id":"796958cd-5057-4f35-81b0-c135cd494c84","name":"WAF","type":"Node","layer":"technology"},{"id":"f0205cb4-d46d-429c-8ff1-ceaf75c2a01a","name":"Node","type":"Node","layer":"technology"},{"id":"9847bdca-9bc6-4d85-a56b-fb926ddbb56b","name":"Router","type":"TechnologyFunction","layer":"technology"},{"id":"803060e1-3533-4334-aa97-0fbdbb4922de","name":"Monitoring","type":"TechnologyFunction","layer":"technology"},{"id":"ac694d7a-29f3-45a3-9c18-125d88a37131","name":"Identity providers","type":"Node","layer":"technology"},{"id":"68a2fbbe-49bf-4d2f-b81d-fe93b15f73b0","name":"Oauth 2","type":"TechnologyInterface","layer":"technology"},{"id":"79412227-99f3-4c9a-93b3-f119ba023ad0","name":"Management","type":"TechnologyInterface","layer":"technology"},{"id":"353d74ab-7f06-4f18-97b0-86a8c477c47c","name":"Cloud runtime","type":"SystemSoftware","layer":"technology"},{"id":"66841a88-b32d-41c7-a61c-5aef963c52bd","name":"Identity repositories","type":"Node","layer":"technology"},{"id":"3dbf6a8c-a9d1-4581-aac5-bba0ca0313c1","name":"DC network","type":"CommunicationNetwork","layer":"technology"},{"id":"03352d55-06e3-47aa-8848-93bcc0075286","name":"PKI","type":"Node","layer":"technology"},{"id":"5a618c9b-525e-4321-a169-6a339b96a893","name":"Identity repositories","type":"SystemSoftware","layer":"technology"},{"id":"67ae4cfa-461e-4d2b-bad1-fe9579e39fe3","name":"Configuration repostitory","type":"SystemSoftware","layer":"technology"},{"id":"08e24868-51f9-4720-9cac-50c19ed13910","name":"Authentication providers","type":"Node","layer":"technology"},{"id":"3e2156a3-4ef7-4055-b974-95c2096e9ae1","name":"Client","type":"Device","layer":"technology"},{"id":"a490358d-36a5-4650-84ee-bb9d6580026c","name":"Resource","type":"TechnologyFunction","layer":"technology"},{"id":"fc54a59f-e666-4e91-93f5-3f4c62249d25","name":"Domain configuration","type":"SystemSoftware","layer":"technology"},{"id":"6849071f-e0b9-4a57-9131-f64df600d45e","name":"Identity repositories","type":"SystemSoftware","layer":"technology"},{"id":"7c9b34a8-d382-4ec0-88e6-c66f5bc84551","name":"Authentication providers","type":"SystemSoftware","layer":"technology"},{"id":"fbee98e8-88eb-4a10-a247-a673e926764f","name":"Revocation list repository","type":"SystemSoftware","layer":"technology"},{"id":"41cf247a-2e84-4901-8080-50e1ac5afa54","name":"Revocation list repostiory","type":"Artifact","layer":"technology"},{"id":"c63a29ff-2e46-4859-9b21-4508740bb0ac","name":"Client","type":"Device","layer":"technology"},{"id":"4662df66-a1d6-4f9a-9039-3813d1cd982b","name":"Resources","type":"Node","layer":"technology"},{"id":"7aac4923-ff67-4658-937e-cb78fa698557","name":"Session storage","type":"Artifact","layer":"technology"},{"id":"856c28ca-b250-4780-b781-28af9da376a7","name":"Service storage","type":"SystemSoftware","layer":"technology"},{"id":"99f2dfc4-2845-4071-af90-ac4752b1046a","name":"DNS","type":"Device","layer":"technology"},{"id":"89ce96cb-ec00-45d2-aeef-ca56c5e576bf","name":"DC 1","type":"Facility","layer":"technology"},{"id":"9cb59153-1c42-485b-800d-6813d1b6840c","name":"DC n","type":"Facility","layer":"technology"},{"id":"4a71dfd2-f5c1-47d8-8597-37faa4b8137a","name":"...","type":"Facility","layer":"technology"},{"id":"53327b6b-35c9-4a28-89d7-c885128d8620","name":"WAN","type":"CommunicationNetwork","layer":"technology"},{"id":"fc57436e-6235-4506-95ea-e67296c20742","name":"DC interconnect","type":"Path","layer":"technology"},{"id":"f5d9a04a-7a0c-4293-9afa-e6bcd534af34","name":"Cloud platform","type":"Grouping","layer":"other"},{"id":"0e8bbe31-be07-4103-a5bc-52c688ddf467","name":"Junction","type":"Junction","layer":"other"},{"id":"3abb47f7-5ea6-4b17-8339-9ead9df1c277","name":"Outside","type":"Grouping","layer":"other"},{"id":"1983b85f-291c-44ce-b61f-ebe21e977e2c","name":"DC","type":"Grouping","layer":"other"},{"id":"02c3344e-32de-4dbc-82c2-12b72b19b5da","name":"Data centre","type":"Grouping","layer":"other"},{"id":"a8624004-bceb-4d50-9af3-a1cb633c0ebc","name":"Domain model","type":"Grouping","layer":"other"},{"id":"e289910f-7978-4b18-912c-bf003a8505f1","name":"Service domain","type":"Grouping","layer":"other"}],"relationships":[{"id":"7748b359-5907-4916-b42f-f29459241d25","sourceId":"63ec9603-69bf-42b2-9249-ae723dac179b","targetId":"4fe9439a-d383-402c-aef8-63702fe9ac0c","type":"Association"},{"id":"b425f8d4-2252-485b-91fe-f1fbe35a3ec4","sourceId":"e6d88220-c7be-42e9-86fe-cc7976e4a3a1","targetId":"199a3c00-f416-4c9b-a056-17c4e1a1fb13","type":"Association"},{"id":"756edeeb-d948-44ad-a2a2-0115b8cea8d6","sourceId":"60a4cc88-f66b-4e95-9081-44619f466d96","targetId":"2613f0ac-b14e-43dd-90a8-86247a6920e8","type":"Association"},{"id":"f7fcc49e-1d2f-4070-abbe-b15572c3f264","sourceId":"4fe9439a-d383-402c-aef8-63702fe9ac0c","targetId":"e34c6cbf-d671-4c36-9683-d5244494aa72","type":"Association"},{"id":"be3264a5-450f-4732-a32d-5502f8772a20","sourceId":"199a3c00-f416-4c9b-a056-17c4e1a1fb13","targetId":"e34c6cbf-d671-4c36-9683-d5244494aa72","type":"Association"},{"id":"564ccef4-d855-4f69-ab0e-fcac0c366370","sourceId":"2613f0ac-b14e-43dd-90a8-86247a6920e8","targetId":"e34c6cbf-d671-4c36-9683-d5244494aa72","type":"Association"},{"id":"bbd10d7d-0d40-4c96-b403-93d0539213da","sourceId":"e34c6cbf-d671-4c36-9683-d5244494aa72","targetId":"2c283e2f-0688-4529-badc-a03a16f4b171","type":"Association"},{"id":"3ee7134b-3f88-4917-8f74-61cbed7f44e0","sourceId":"2c283e2f-0688-4529-badc-a03a16f4b171","targetId":"796958cd-5057-4f35-81b0-c135cd494c84","type":"Association"},{"id":"07ef1d23-f233-4fc3-aee6-f85d8366a255","sourceId":"e34c6cbf-d671-4c36-9683-d5244494aa72","targetId":"796958cd-5057-4f35-81b0-c135cd494c84","type":"Association"},{"id":"5cebb491-a1cb-4cd6-95a0-d2ee018c1473","sourceId":"796958cd-5057-4f35-81b0-c135cd494c84","targetId":"9847bdca-9bc6-4d85-a56b-fb926ddbb56b","type":"Association"},{"id":"1c48b4aa-2f40-4d47-a682-fc5b12c046a7","sourceId":"796958cd-5057-4f35-81b0-c135cd494c84","targetId":"803060e1-3533-4334-aa97-0fbdbb4922de","type":"Association"},{"id":"ba7b94a4-e162-4afb-9f90-055f15ca000f","sourceId":"9847bdca-9bc6-4d85-a56b-fb926ddbb56b","targetId":"803060e1-3533-4334-aa97-0fbdbb4922de","type":"Association"},{"id":"324ef333-eb29-4552-ba2a-d07276c7c8ae","sourceId":"9847bdca-9bc6-4d85-a56b-fb926ddbb56b","targetId":"ac694d7a-29f3-45a3-9c18-125d88a37131","type":"Association"},{"id":"884a24ef-4e73-4494-86e9-1e93a0ce6e2f","sourceId":"803060e1-3533-4334-aa97-0fbdbb4922de","targetId":"ac694d7a-29f3-45a3-9c18-125d88a37131","type":"Association"},{"id":"bac8b5c1-9601-4546-873a-963b08af7fa0","sourceId":"9847bdca-9bc6-4d85-a56b-fb926ddbb56b","targetId":"68a2fbbe-49bf-4d2f-b81d-fe93b15f73b0","type":"Association"},{"id":"c2fc81a8-7b26-4e28-b551-e53a34f37917","sourceId":"ac694d7a-29f3-45a3-9c18-125d88a37131","targetId":"68a2fbbe-49bf-4d2f-b81d-fe93b15f73b0","type":"Realization"},{"id":"fcdf6891-0b13-48f3-b131-ab0614a105d9","sourceId":"9847bdca-9bc6-4d85-a56b-fb926ddbb56b","targetId":"79412227-99f3-4c9a-93b3-f119ba023ad0","type":"Association"},{"id":"1f9ccbf5-b274-4f3e-a3a3-ed5ab66dbd8b","sourceId":"79412227-99f3-4c9a-93b3-f119ba023ad0","targetId":"ac694d7a-29f3-45a3-9c18-125d88a37131","type":"Association"},{"id":"6337bf96-30af-4d3f-88e0-f536017c1579","sourceId":"f5d9a04a-7a0c-4293-9afa-e6bcd534af34","targetId":"353d74ab-7f06-4f18-97b0-86a8c477c47c","type":"Realization"},{"id":"b05aa4e3-7a68-4845-b670-e5fe04c65961","sourceId":"3dbf6a8c-a9d1-4581-aac5-bba0ca0313c1","targetId":"ac694d7a-29f3-45a3-9c18-125d88a37131","type":"Serving"},{"id":"679dff85-833a-4a2e-b66b-7744215e530e","sourceId":"66841a88-b32d-41c7-a61c-5aef963c52bd","targetId":"3dbf6a8c-a9d1-4581-aac5-bba0ca0313c1","type":"Association"},{"id":"cbbd6605-6d04-43f3-8aca-22543adc6dc8","sourceId":"63ec9603-69bf-42b2-9249-ae723dac179b","targetId":"5550db4c-4a1a-4442-897e-a3f632bf20e2","type":"Serving"},{"id":"a112d200-6769-4f87-a160-1b6c5fb75570","sourceId":"e6d88220-c7be-42e9-86fe-cc7976e4a3a1","targetId":"5550db4c-4a1a-4442-897e-a3f632bf20e2","type":"Triggering"},{"id":"f0e29c6e-2458-4b4a-af26-f3b3f7d31125","sourceId":"60a4cc88-f66b-4e95-9081-44619f466d96","targetId":"5550db4c-4a1a-4442-897e-a3f632bf20e2","type":"Triggering"},{"id":"141c60b5-0264-4825-b361-eebf48063434","sourceId":"63ec9603-69bf-42b2-9249-ae723dac179b","targetId":"f2e70629-ca6b-4833-8f94-e17f9f819343","type":"Serving"},{"id":"a6c78d68-690d-4ae0-a797-387b98fbd0c1","sourceId":"e6d88220-c7be-42e9-86fe-cc7976e4a3a1","targetId":"f2e70629-ca6b-4833-8f94-e17f9f819343","type":"Serving"},{"id":"2884d76d-384c-465e-8e43-197d68cf269d","sourceId":"60a4cc88-f66b-4e95-9081-44619f466d96","targetId":"f2e70629-ca6b-4833-8f94-e17f9f819343","type":"Serving"},{"id":"64eb8779-784b-4bf1-96d0-e34051e54e40","sourceId":"803060e1-3533-4334-aa97-0fbdbb4922de","targetId":"5dfa85f0-c147-4a4c-8514-37e104e3f7cd","type":"Serving"},{"id":"70e28d2f-89b5-4756-9553-e88f245d5efe","sourceId":"79412227-99f3-4c9a-93b3-f119ba023ad0","targetId":"5dfa85f0-c147-4a4c-8514-37e104e3f7cd","type":"Serving"},{"id":"380e525d-6c2a-43ed-8e23-4a051330f921","sourceId":"79412227-99f3-4c9a-93b3-f119ba023ad0","targetId":"718b1442-6c85-48f9-a17e-4d6605073424","type":"Serving"},{"id":"446a1f3b-b552-4c16-a70d-84a584943fde","sourceId":"4fe9439a-d383-402c-aef8-63702fe9ac0c","targetId":"03352d55-06e3-47aa-8848-93bcc0075286","type":"Serving"},{"id":"65360ebe-3587-49b4-a112-42968770e3dd","sourceId":"03352d55-06e3-47aa-8848-93bcc0075286","targetId":"796958cd-5057-4f35-81b0-c135cd494c84","type":"Serving"},{"id":"30ffca05-938b-4b0d-8cd8-c26fae69610d","sourceId":"e34c6cbf-d671-4c36-9683-d5244494aa72","targetId":"03352d55-06e3-47aa-8848-93bcc0075286","type":"Association"},{"id":"a8bf6f37-8047-4a38-9154-e0df8578b450","sourceId":"5a618c9b-525e-4321-a169-6a339b96a893","targetId":"3dbf6a8c-a9d1-4581-aac5-bba0ca0313c1","type":"Association"},{"id":"bba18d42-0a0c-4057-9f2a-cba804c6a9fc","sourceId":"5a618c9b-525e-4321-a169-6a339b96a893","targetId":"ac694d7a-29f3-45a3-9c18-125d88a37131","type":"Serving"},{"id":"229a1f3e-63e4-4d78-95ff-d1dad7c2056c","sourceId":"67ae4cfa-461e-4d2b-bad1-fe9579e39fe3","targetId":"ac694d7a-29f3-45a3-9c18-125d88a37131","type":"Serving"},{"id":"ac0d205d-e89e-4f0d-8a10-eea7593bef16","sourceId":"08e24868-51f9-4720-9cac-50c19ed13910","targetId":"ac694d7a-29f3-45a3-9c18-125d88a37131","type":"Serving"},{"id":"4d511b36-08c8-42d9-babf-21d4c21245c9","sourceId":"3e2156a3-4ef7-4055-b974-95c2096e9ae1","targetId":"1e0fa4b7-525f-45ad-b3a4-a5a5e9ac4c5e","type":"Serving"},{"id":"24aabba7-4b2d-4f07-97bc-6fcb79aecbc4","sourceId":"d37a948a-68d8-4fc3-a115-c4148742411f","targetId":"3e2156a3-4ef7-4055-b974-95c2096e9ae1","type":"Serving"},{"id":"2ac3264b-484b-421d-8429-e69a301f2016","sourceId":"0e8bbe31-be07-4103-a5bc-52c688ddf467","targetId":"d37a948a-68d8-4fc3-a115-c4148742411f","type":"Realization"},{"id":"9d54ee49-289f-4dfa-a81a-8dbe0adc94a4","sourceId":"a490358d-36a5-4650-84ee-bb9d6580026c","targetId":"d37a948a-68d8-4fc3-a115-c4148742411f","type":"Serving"},{"id":"9c2f0592-6c35-4f22-a68d-4aaf8d9c6610","sourceId":"d37a948a-68d8-4fc3-a115-c4148742411f","targetId":"a490358d-36a5-4650-84ee-bb9d6580026c","type":"Serving"},{"id":"45a37986-ea03-412a-8d4e-f4db44cf5244","sourceId":"0e8bbe31-be07-4103-a5bc-52c688ddf467","targetId":"e17441b6-0b34-4564-8c28-e423a3302995","type":"Association"},{"id":"3a949e32-1bb5-4352-aa2a-c37956b87e6d","sourceId":"2d196b06-f564-41aa-871d-b9420b8c4d63","targetId":"0e8bbe31-be07-4103-a5bc-52c688ddf467","type":"Association"},{"id":"01cbf45e-ad92-407e-b8f6-bbcb72c39aa2","sourceId":"2f51ced6-69a0-41f9-baf8-199d2e174cb6","targetId":"e17441b6-0b34-4564-8c28-e423a3302995","type":"Realization"},{"id":"97bf91c7-caf3-4a93-a850-22e657a7c640","sourceId":"2f51ced6-69a0-41f9-baf8-199d2e174cb6","targetId":"e17441b6-0b34-4564-8c28-e423a3302995","type":"Serving"},{"id":"de66b090-2337-42aa-8620-100c02c1dc6b","sourceId":"2d196b06-f564-41aa-871d-b9420b8c4d63","targetId":"e17441b6-0b34-4564-8c28-e423a3302995","type":"Serving"},{"id":"67ef4d5d-5231-4315-ac09-c42284f1f885","sourceId":"2f51ced6-69a0-41f9-baf8-199d2e174cb6","targetId":"2d196b06-f564-41aa-871d-b9420b8c4d63","type":"Serving"},{"id":"6bcbbc96-91c7-43dd-83bf-788dd05466ee","sourceId":"fc54a59f-e666-4e91-93f5-3f4c62249d25","targetId":"2f51ced6-69a0-41f9-baf8-199d2e174cb6","type":"Flow"},{"id":"f92c271e-aa31-4e3b-b2f5-be4d1c0cea95","sourceId":"6849071f-e0b9-4a57-9131-f64df600d45e","targetId":"2f51ced6-69a0-41f9-baf8-199d2e174cb6","type":"Serving"},{"id":"a91d0b57-e4a8-4279-b351-b71fdf83b1ea","sourceId":"fc54a59f-e666-4e91-93f5-3f4c62249d25","targetId":"2f51ced6-69a0-41f9-baf8-199d2e174cb6","type":"Triggering"},{"id":"03ec388b-8421-43ea-ba6b-d1ba205dd219","sourceId":"e01634d6-b45f-4e78-9940-33d18bae7db9","targetId":"e17441b6-0b34-4564-8c28-e423a3302995","type":"Serving"},{"id":"f304cc0d-0b55-4f13-bb00-05b3ececf2e4","sourceId":"fc54a59f-e666-4e91-93f5-3f4c62249d25","targetId":"2d196b06-f564-41aa-871d-b9420b8c4d63","type":"Serving"},{"id":"551ab190-a751-4080-8123-7b45987323cd","sourceId":"72888d0d-499c-4a65-b8a8-ac2cd70f8b2f","targetId":"fc39a254-f49f-406a-81aa-e5b1795abcc1","type":"Realization"},{"id":"6fc35df3-0923-45c9-83c0-882d832db780","sourceId":"fc39a254-f49f-406a-81aa-e5b1795abcc1","targetId":"93e90e66-ffcf-44bf-baef-c57d72d02d1a","type":"Serving"},{"id":"f4286c24-1def-4ad0-b964-df2639bea320","sourceId":"e17441b6-0b34-4564-8c28-e423a3302995","targetId":"0e8bbe31-be07-4103-a5bc-52c688ddf467","type":"Association"},{"id":"5df75ce9-8949-4139-8404-274084ab6903","sourceId":"e17441b6-0b34-4564-8c28-e423a3302995","targetId":"d37a948a-68d8-4fc3-a115-c4148742411f","type":"Realization"},{"id":"e0862dbe-1f96-4080-bd85-4f85045fc134","sourceId":"2d196b06-f564-41aa-871d-b9420b8c4d63","targetId":"f42f25af-ab95-494b-98f2-2d0046577348","type":"Realization"},{"id":"1fca673e-9b18-4424-a718-4f78e3069837","sourceId":"f42f25af-ab95-494b-98f2-2d0046577348","targetId":"3e2156a3-4ef7-4055-b974-95c2096e9ae1","type":"Serving"},{"id":"8b097050-3317-45ed-a1cd-066690917957","sourceId":"2f51ced6-69a0-41f9-baf8-199d2e174cb6","targetId":"fc39a254-f49f-406a-81aa-e5b1795abcc1","type":"Realization"},{"id":"5694fd64-5651-48b9-a979-903cc3f2e6a3","sourceId":"2d196b06-f564-41aa-871d-b9420b8c4d63","targetId":"72888d0d-499c-4a65-b8a8-ac2cd70f8b2f","type":"Triggering"},{"id":"cb29a0d9-d564-4bae-ad58-4b2a85fbe582","sourceId":"2d196b06-f564-41aa-871d-b9420b8c4d63","targetId":"72888d0d-499c-4a65-b8a8-ac2cd70f8b2f","type":"Serving"},{"id":"90b8d5b9-256b-4820-aa29-7165d352d095","sourceId":"fc54a59f-e666-4e91-93f5-3f4c62249d25","targetId":"72888d0d-499c-4a65-b8a8-ac2cd70f8b2f","type":"Serving"},{"id":"89cec51b-b04c-4cfa-b50e-e4bff0134044","sourceId":"7c9b34a8-d382-4ec0-88e6-c66f5bc84551","targetId":"2f51ced6-69a0-41f9-baf8-199d2e174cb6","type":"Serving"},{"id":"565016d6-7cda-4352-8e83-6c09d69efc42","sourceId":"fbee98e8-88eb-4a10-a247-a673e926764f","targetId":"e01634d6-b45f-4e78-9940-33d18bae7db9","type":"Serving"},{"id":"54518b29-96d0-4c65-99a6-8a0e8f71f63d","sourceId":"5db4ba15-7ebd-42ea-a75e-177d54eacc0c","targetId":"a490358d-36a5-4650-84ee-bb9d6580026c","type":"Serving"},{"id":"7326e6f4-c1ac-4e2b-8c4e-bbda16dd93dd","sourceId":"2d196b06-f564-41aa-871d-b9420b8c4d63","targetId":"5db4ba15-7ebd-42ea-a75e-177d54eacc0c","type":"Realization"},{"id":"e57ea546-4e29-468b-9ce3-2eb66debf216","sourceId":"8d9e4ae3-d117-4b46-8cf9-68ba25df05f9","targetId":"d145db9c-7457-4af2-a2ac-46b48eb9eaa7","type":"Triggering"},{"id":"427fd91e-0395-415b-aa4b-267d116fd32d","sourceId":"d145db9c-7457-4af2-a2ac-46b48eb9eaa7","targetId":"b0cbfb5f-f536-478b-aafb-02e2f090cce8","type":"Flow"},{"id":"d9a715fc-7033-40e7-8f72-0aef20321a94","sourceId":"b0cbfb5f-f536-478b-aafb-02e2f090cce8","targetId":"5674cda6-b52e-46be-9790-68e679ed691f","type":"Triggering"},{"id":"e6ba0b7d-930f-4ecc-9ebb-28d3f6bb0f84","sourceId":"5674cda6-b52e-46be-9790-68e679ed691f","targetId":"67b2884e-5d05-40df-9a55-4bc802b810d9","type":"Flow"},{"id":"4a9a716e-beb5-4818-be30-da60a9c361f5","sourceId":"8d9e4ae3-d117-4b46-8cf9-68ba25df05f9","targetId":"a4b1eac7-173e-4279-b0b0-9a589d93788f","type":"Triggering"},{"id":"327ce767-dee0-46fd-92ee-97f679644627","sourceId":"a4b1eac7-173e-4279-b0b0-9a589d93788f","targetId":"40f4d602-5781-4f68-8080-0a32a75e02db","type":"Flow"},{"id":"c3620b1a-4423-458a-b5a4-469eb222c08d","sourceId":"40f4d602-5781-4f68-8080-0a32a75e02db","targetId":"40f4d602-5781-4f68-8080-0a32a75e02db","type":"Triggering"},{"id":"32a75ec6-b256-48d6-a2a1-c3d86567b31f","sourceId":"40f4d602-5781-4f68-8080-0a32a75e02db","targetId":"070945dc-0640-4a5e-9ca5-1db0f5ae556f","type":"Triggering"},{"id":"804d8159-96ad-4b48-a5ed-50c4b8c8596f","sourceId":"070945dc-0640-4a5e-9ca5-1db0f5ae556f","targetId":"8d9e4ae3-d117-4b46-8cf9-68ba25df05f9","type":"Flow"},{"id":"e3ad9af9-e820-40b3-a875-c732fc3ca3dd","sourceId":"34160d1d-a800-4094-ad84-fbe55a2275f1","targetId":"f8c901b9-b294-4d27-9800-bed5c39eb339","type":"Triggering"},{"id":"f13e7f23-7883-4f97-a9e0-7c468f29296b","sourceId":"8d9e4ae3-d117-4b46-8cf9-68ba25df05f9","targetId":"a4b1eac7-173e-4279-b0b0-9a589d93788f","type":"Triggering"},{"id":"e0dc3b4b-2271-4902-b8a8-5c115243d113","sourceId":"f8c901b9-b294-4d27-9800-bed5c39eb339","targetId":"8d9e4ae3-d117-4b46-8cf9-68ba25df05f9","type":"Flow"},{"id":"fba8643f-f7bf-4311-ac1e-1a54668610cf","sourceId":"8d9e4ae3-d117-4b46-8cf9-68ba25df05f9","targetId":"619f5847-182e-4f3e-bbac-a5b7ee50b6d8","type":"Triggering"},{"id":"60b80d31-3d52-486f-93a2-adfeb512e213","sourceId":"619f5847-182e-4f3e-bbac-a5b7ee50b6d8","targetId":"34160d1d-a800-4094-ad84-fbe55a2275f1","type":"Flow"},{"id":"622d7883-3d27-44c3-88f1-a0523e11c0c4","sourceId":"34160d1d-a800-4094-ad84-fbe55a2275f1","targetId":"1ce8e1bd-2b56-4c1a-9821-eb18372af7fd","type":"Triggering"},{"id":"1d2b430e-b639-4f43-a910-0140014ca7f4","sourceId":"1ce8e1bd-2b56-4c1a-9821-eb18372af7fd","targetId":"40f4d602-5781-4f68-8080-0a32a75e02db","type":"Flow"},{"id":"7d8521c7-1340-48fb-8599-bc01a5b21257","sourceId":"40f4d602-5781-4f68-8080-0a32a75e02db","targetId":"6019d36c-f2e6-4b23-bd02-c6973785c3a4","type":"Triggering"},{"id":"3e048009-2c49-477e-9562-aa58353d19e5","sourceId":"6019d36c-f2e6-4b23-bd02-c6973785c3a4","targetId":"8d9e4ae3-d117-4b46-8cf9-68ba25df05f9","type":"Flow"},{"id":"a9f5cd52-eb28-4aff-9e0f-34ae74f8e4b8","sourceId":"40f4d602-5781-4f68-8080-0a32a75e02db","targetId":"070945dc-0640-4a5e-9ca5-1db0f5ae556f","type":"Triggering"},{"id":"b9d38233-f4df-4472-b8bb-9967052b9961","sourceId":"8d9e4ae3-d117-4b46-8cf9-68ba25df05f9","targetId":"a4b1eac7-173e-4279-b0b0-9a589d93788f","type":"Triggering"},{"id":"33120ba9-3d3f-41cd-b08e-cde23053eed9","sourceId":"8d9e4ae3-d117-4b46-8cf9-68ba25df05f9","targetId":"6ed688e5-77f5-4a1b-8e02-3d5706b69a69","type":"Triggering"},{"id":"b2cbfab3-1d39-429b-8ea4-fc0dcdfe45a1","sourceId":"6ed688e5-77f5-4a1b-8e02-3d5706b69a69","targetId":"34160d1d-a800-4094-ad84-fbe55a2275f1","type":"Flow"},{"id":"022957d9-18ea-4874-92d3-055c830f8c72","sourceId":"40f4d602-5781-4f68-8080-0a32a75e02db","targetId":"54fbe83d-1287-4a2f-a630-0abdf9289038","type":"Triggering"},{"id":"203d788e-bc17-4b50-937b-101704d28eb4","sourceId":"54fbe83d-1287-4a2f-a630-0abdf9289038","targetId":"8d9e4ae3-d117-4b46-8cf9-68ba25df05f9","type":"Triggering"},{"id":"8c533580-13b1-47ee-b9bb-c50ef6edc844","sourceId":"8d9e4ae3-d117-4b46-8cf9-68ba25df05f9","targetId":"82938c04-4569-4a9e-874b-c9d659a26d8c","type":"Triggering"},{"id":"9500fe02-c479-43a4-badc-68d54d96c040","sourceId":"82938c04-4569-4a9e-874b-c9d659a26d8c","targetId":"34160d1d-a800-4094-ad84-fbe55a2275f1","type":"Triggering"},{"id":"73f9a2d5-d944-4213-a8ef-5085fed7b60b","sourceId":"1ce8e1bd-2b56-4c1a-9821-eb18372af7fd","targetId":"8d9e4ae3-d117-4b46-8cf9-68ba25df05f9","type":"Triggering"},{"id":"368dc33b-817e-4a22-ad4d-ef7f95989d02","sourceId":"8d9e4ae3-d117-4b46-8cf9-68ba25df05f9","targetId":"aea379bb-b506-43c7-a168-19bd38778eb7","type":"Triggering"},{"id":"69397c65-5a66-4af1-be62-b872470a3b0b","sourceId":"aea379bb-b506-43c7-a168-19bd38778eb7","targetId":"40f4d602-5781-4f68-8080-0a32a75e02db","type":"Triggering"},{"id":"c1f1c40c-adbf-410e-a498-ed2641bc7aae","sourceId":"8d9e4ae3-d117-4b46-8cf9-68ba25df05f9","targetId":"aea379bb-b506-43c7-a168-19bd38778eb7","type":"Triggering"},{"id":"82380675-bb07-4b7b-b1a2-5a79bb8e1b92","sourceId":"40f4d602-5781-4f68-8080-0a32a75e02db","targetId":"1d8cac69-c86e-4496-bf87-2280a7c2f2ea","type":"Triggering"},{"id":"815a97c1-6c08-4bfd-930a-835b10570b57","sourceId":"1d8cac69-c86e-4496-bf87-2280a7c2f2ea","targetId":"34160d1d-a800-4094-ad84-fbe55a2275f1","type":"Triggering"},{"id":"55f355b8-28e9-45bd-9c44-92abcd099441","sourceId":"34160d1d-a800-4094-ad84-fbe55a2275f1","targetId":"1ce8e1bd-2b56-4c1a-9821-eb18372af7fd","type":"Triggering"},{"id":"a945f307-b6e0-4bf9-b473-b3713ad272d8","sourceId":"34160d1d-a800-4094-ad84-fbe55a2275f1","targetId":"f8c901b9-b294-4d27-9800-bed5c39eb339","type":"Triggering"},{"id":"607c14c8-11e7-4102-b175-886cfdc9a7a2","sourceId":"40f4d602-5781-4f68-8080-0a32a75e02db","targetId":"1d8cac69-c86e-4496-bf87-2280a7c2f2ea","type":"Triggering"},{"id":"d6aa4eed-d14e-45df-adc3-0c80beb61623","sourceId":"40f4d602-5781-4f68-8080-0a32a75e02db","targetId":"6019d36c-f2e6-4b23-bd02-c6973785c3a4","type":"Triggering"},{"id":"27242bf0-2457-49a4-a92b-dbdb8d9fe114","sourceId":"40f4d602-5781-4f68-8080-0a32a75e02db","targetId":"1d8cac69-c86e-4496-bf87-2280a7c2f2ea","type":"Triggering"},{"id":"57f6cfe6-33e8-47aa-ab12-0b603d54ac01","sourceId":"34160d1d-a800-4094-ad84-fbe55a2275f1","targetId":"91b4e34d-e14a-4dc6-b228-91dde4abebb3","type":"Triggering"},{"id":"daef1fab-cf1e-4816-8b5c-0534834527c7","sourceId":"91b4e34d-e14a-4dc6-b228-91dde4abebb3","targetId":"40f4d602-5781-4f68-8080-0a32a75e02db","type":"Triggering"},{"id":"08b379a0-7530-4f7d-8deb-d7f0d0eda0cc","sourceId":"40f4d602-5781-4f68-8080-0a32a75e02db","targetId":"54fbe83d-1287-4a2f-a630-0abdf9289038","type":"Triggering"},{"id":"93863fc2-b528-4151-8fa7-b6aa0f9ff462","sourceId":"ac694d7a-29f3-45a3-9c18-125d88a37131","targetId":"4662df66-a1d6-4f9a-9039-3813d1cd982b","type":"Serving"},{"id":"7707d33d-20f5-416b-900a-7c975dcab6fb","sourceId":"803060e1-3533-4334-aa97-0fbdbb4922de","targetId":"ac694d7a-29f3-45a3-9c18-125d88a37131","type":"Serving"},{"id":"cf0ff4ee-e1d8-4391-8efc-7c9ad81748fb","sourceId":"4662df66-a1d6-4f9a-9039-3813d1cd982b","targetId":"f2e70629-ca6b-4833-8f94-e17f9f819343","type":"Serving"},{"id":"d4441f08-4550-4e12-8123-920978ff7462","sourceId":"63ec9603-69bf-42b2-9249-ae723dac179b","targetId":"4662df66-a1d6-4f9a-9039-3813d1cd982b","type":"Serving"},{"id":"44e376f6-983a-46fc-9e39-fe64d3606f1b","sourceId":"e34c6cbf-d671-4c36-9683-d5244494aa72","targetId":"03352d55-06e3-47aa-8848-93bcc0075286","type":"Association"},{"id":"df276738-abb5-4f5d-9d0c-5d55cfb85b48","sourceId":"ac694d7a-29f3-45a3-9c18-125d88a37131","targetId":"7aac4923-ff67-4658-937e-cb78fa698557","type":"Access"},{"id":"6cec2ed7-0cbe-4352-b628-ee80a72c95ac","sourceId":"63ec9603-69bf-42b2-9249-ae723dac179b","targetId":"4662df66-a1d6-4f9a-9039-3813d1cd982b","type":"Serving"},{"id":"e2792b55-cfe6-433e-9fc4-9508710564a7","sourceId":"68a2fbbe-49bf-4d2f-b81d-fe93b15f73b0","targetId":"4662df66-a1d6-4f9a-9039-3813d1cd982b","type":"Serving"},{"id":"c1e5d145-bad1-447f-807e-861321d4c9a7","sourceId":"b03787b2-29b4-4809-a5fd-bb55dcf11e24","targetId":"2799c8d1-bf48-4a85-9e22-9a1768174671","type":"Serving"},{"id":"d664adcd-24a7-483c-ab34-dfd9a5943608","sourceId":"f5eec8ed-6054-4345-bcc6-fe4d9bcededc","targetId":"b03787b2-29b4-4809-a5fd-bb55dcf11e24","type":"Realization"},{"id":"5604aa81-9735-4818-8ef7-949767425aa5","sourceId":"d7cad2e5-c376-4199-90f7-caab88745394","targetId":"f5eec8ed-6054-4345-bcc6-fe4d9bcededc","type":"Realization"},{"id":"a68054a9-1f29-4e79-ab7a-8949ae84a095","sourceId":"64374b03-1816-4765-997d-f8df9941fe32","targetId":"d7cad2e5-c376-4199-90f7-caab88745394","type":"Serving"},{"id":"cdf07c3a-11cb-4545-90df-7049f5756048","sourceId":"64374b03-1816-4765-997d-f8df9941fe32","targetId":"f5eec8ed-6054-4345-bcc6-fe4d9bcededc","type":"Realization"},{"id":"b8e2e783-5ff4-4d64-a212-038ff306566e","sourceId":"5cbf4332-390f-433c-822c-e1a4877812d6","targetId":"d7cad2e5-c376-4199-90f7-caab88745394","type":"Serving"},{"id":"50bbf198-e4e8-4841-b5aa-84d2419ecc6d","sourceId":"717fdbab-64d2-4e0a-ba45-93711c1093a6","targetId":"d7cad2e5-c376-4199-90f7-caab88745394","type":"Triggering"},{"id":"61018a48-3def-4465-809c-effd181342a3","sourceId":"717fdbab-64d2-4e0a-ba45-93711c1093a6","targetId":"d7cad2e5-c376-4199-90f7-caab88745394","type":"Serving"},{"id":"3cbc52d1-d4a8-498e-96f5-401433817012","sourceId":"7ac4da2b-f5ae-4dfe-bffe-3ebb9fe072f7","targetId":"e27a4009-6801-497b-84ea-072d988e10eb","type":"Composition"},{"id":"54a7ebe4-436f-49f0-99a4-51c7dc715e6a","sourceId":"e27a4009-6801-497b-84ea-072d988e10eb","targetId":"3f994e7a-335c-4d70-9a5b-19c09040852e","type":"Aggregation"},{"id":"a087fa68-11b2-4626-b9ce-229f7e3942c7","sourceId":"e27a4009-6801-497b-84ea-072d988e10eb","targetId":"0a79fed5-0b5d-4ca3-b2b8-6079f5b46256","type":"Aggregation"},{"id":"3b49917b-6f12-407d-bad8-4b6182c39970","sourceId":"0a79fed5-0b5d-4ca3-b2b8-6079f5b46256","targetId":"3f994e7a-335c-4d70-9a5b-19c09040852e","type":"Association"},{"id":"94d30974-c0e7-4cc0-9cc9-60ae6f74f39c","sourceId":"e27a4009-6801-497b-84ea-072d988e10eb","targetId":"0a79fed5-0b5d-4ca3-b2b8-6079f5b46256","type":"Composition"},{"id":"de3b40e5-991b-40a9-91d8-7ed405f6dac2","sourceId":"0a79fed5-0b5d-4ca3-b2b8-6079f5b46256","targetId":"e00f71db-86bc-469e-baef-fee6d4263aa1","type":"Composition"},{"id":"7035ca2c-77de-434e-9a8d-a0eebf58a149","sourceId":"0a79fed5-0b5d-4ca3-b2b8-6079f5b46256","targetId":"78110dc2-68b6-4536-aa24-e4256d4fb4b3","type":"Composition"},{"id":"98a0149d-85f3-483e-b696-8bcbc44fb408","sourceId":"7ac4da2b-f5ae-4dfe-bffe-3ebb9fe072f7","targetId":"647a61b0-7ac0-4f5f-8961-b9141de81dca","type":"Composition"},{"id":"5e121176-a3d1-4510-b133-b83d58c5ba09","sourceId":"647a61b0-7ac0-4f5f-8961-b9141de81dca","targetId":"e27a4009-6801-497b-84ea-072d988e10eb","type":"Composition"},{"id":"697595d9-6b81-4f3f-b17c-bb96e1f676ca","sourceId":"f1a2246f-4f83-4c0c-8777-88f72552fc35","targetId":"64374b03-1816-4765-997d-f8df9941fe32","type":"Serving"},{"id":"921a7c43-7c95-49f6-b834-b97541114012","sourceId":"f1a2246f-4f83-4c0c-8777-88f72552fc35","targetId":"d7cad2e5-c376-4199-90f7-caab88745394","type":"Serving"},{"id":"185f03a1-d5ca-4ab0-9f6c-2b032f37bfae","sourceId":"3f994e7a-335c-4d70-9a5b-19c09040852e","targetId":"1eec2fcb-cee5-4fe4-a8c9-8123f8068f35","type":"Aggregation"},{"id":"5e0b28b2-c113-4415-93f1-e6a8b9fcfe78","sourceId":"0a79fed5-0b5d-4ca3-b2b8-6079f5b46256","targetId":"78110dc2-68b6-4536-aa24-e4256d4fb4b3","type":"Aggregation"},{"id":"27a410de-5022-407f-bac6-1b9bcfe8d855","sourceId":"0a79fed5-0b5d-4ca3-b2b8-6079f5b46256","targetId":"3f994e7a-335c-4d70-9a5b-19c09040852e","type":"Aggregation"},{"id":"de1ea4f0-1db1-448d-b830-9d286b59a7bd","sourceId":"fbfa9aab-c3ef-48f7-a7e6-dcce699ec81a","targetId":"17dfe88c-82ea-4e1a-b52c-f00e53791b97","type":"Realization"},{"id":"7a29a6ae-3652-4b9a-a2dd-15aecd4c6266","sourceId":"fbfa9aab-c3ef-48f7-a7e6-dcce699ec81a","targetId":"2d110999-aa0a-4dcb-ace8-7c280331973b","type":"Realization"},{"id":"f22e839a-8d26-4d80-a387-c7be8f9aab52","sourceId":"17dfe88c-82ea-4e1a-b52c-f00e53791b97","targetId":"22faabb5-ce46-41d4-abce-93270746f0a5","type":"Serving"},{"id":"40bbc27f-1bb0-4721-bc28-0af94603c474","sourceId":"2d110999-aa0a-4dcb-ace8-7c280331973b","targetId":"22faabb5-ce46-41d4-abce-93270746f0a5","type":"Serving"},{"id":"90dfaa43-65ad-43fc-8146-48c76eb8e958","sourceId":"2d0035e4-a197-441e-9a4e-17dc1de5a8fa","targetId":"fbfa9aab-c3ef-48f7-a7e6-dcce699ec81a","type":"Serving"},{"id":"cbecafcd-66d3-4d13-8cc5-08267d08b67d","sourceId":"856c28ca-b250-4780-b781-28af9da376a7","targetId":"fbfa9aab-c3ef-48f7-a7e6-dcce699ec81a","type":"Serving"},{"id":"ee745443-b2ca-4928-9404-04842dcef3b8","sourceId":"99f2dfc4-2845-4071-af90-ac4752b1046a","targetId":"1845c80e-ae85-42bc-bf83-5a2178c8309c","type":"Serving"},{"id":"3e98c883-7ac6-422a-9087-1337b065dd42","sourceId":"99f2dfc4-2845-4071-af90-ac4752b1046a","targetId":"89ce96cb-ec00-45d2-aeef-ca56c5e576bf","type":"Association"},{"id":"d3b28578-8eb2-4f66-8b42-33fb27b902c4","sourceId":"99f2dfc4-2845-4071-af90-ac4752b1046a","targetId":"4a71dfd2-f5c1-47d8-8597-37faa4b8137a","type":"Association"},{"id":"380dd328-1377-4e1f-8289-1f65f39e4130","sourceId":"1845c80e-ae85-42bc-bf83-5a2178c8309c","targetId":"53327b6b-35c9-4a28-89d7-c885128d8620","type":"Association"},{"id":"fd2f9e47-8b7b-450f-9746-96174f6343b8","sourceId":"2253e2ab-566e-4dc6-a601-d6235c95e800","targetId":"1845c80e-ae85-42bc-bf83-5a2178c8309c","type":"Serving"},{"id":"7c47ba38-5422-4b89-a40f-bac6a7ec3cdb","sourceId":"53327b6b-35c9-4a28-89d7-c885128d8620","targetId":"2253e2ab-566e-4dc6-a601-d6235c95e800","type":"Realization"},{"id":"82ccc19b-de1e-4278-9f4d-f5061088b6a9","sourceId":"99f2dfc4-2845-4071-af90-ac4752b1046a","targetId":"2253e2ab-566e-4dc6-a601-d6235c95e800","type":"Realization"},{"id":"bf5c5e36-fcbd-4f23-aa93-4c01868a31c3","sourceId":"89ce96cb-ec00-45d2-aeef-ca56c5e576bf","targetId":"53327b6b-35c9-4a28-89d7-c885128d8620","type":"Association"},{"id":"cb7ba447-aebe-44b0-aeb0-9307ef391f4c","sourceId":"4a71dfd2-f5c1-47d8-8597-37faa4b8137a","targetId":"53327b6b-35c9-4a28-89d7-c885128d8620","type":"Association"},{"id":"d32dcfff-cbdd-452f-ac3b-14d8eab436c7","sourceId":"9cb59153-1c42-485b-800d-6813d1b6840c","targetId":"53327b6b-35c9-4a28-89d7-c885128d8620","type":"Association"},{"id":"2ce676ac-6067-4b6e-af2d-c93952e22859","sourceId":"fc57436e-6235-4506-95ea-e67296c20742","targetId":"89ce96cb-ec00-45d2-aeef-ca56c5e576bf","type":"Triggering"},{"id":"e3606db4-6855-40ad-9ba1-4cefdd679ad8","sourceId":"fc57436e-6235-4506-95ea-e67296c20742","targetId":"4a71dfd2-f5c1-47d8-8597-37faa4b8137a","type":"Triggering"},{"id":"4b98c551-7f80-4bf8-a239-e6979cdcb01d","sourceId":"fc57436e-6235-4506-95ea-e67296c20742","targetId":"9cb59153-1c42-485b-800d-6813d1b6840c","type":"Triggering"},{"id":"4fe5948d-5926-410e-a5f8-fdaa658c79b0","sourceId":"9ee3dd28-0eaa-4fd7-b8f9-f677aa699cdb","targetId":"53327b6b-35c9-4a28-89d7-c885128d8620","type":"Association"}],"views":[{"id":"35fb544f-ec82-448c-9ec5-6c9e3289e751","name":"System view","viewpoint":""},{"id":"4e6592a8-0cd3-4393-8e67-b558b2e3c911","name":"Application view","viewpoint":""},{"id":"7387b660-9391-4550-bbc5-2ec268e08d25","name":"Authentication flow","viewpoint":""},{"id":"60e19e89-a4e4-43a2-bc82-20e6445a9af2","name":"Domain management","viewpoint":""},{"id":"c8504390-1a3b-40d9-8047-a94f2bba2a66","name":"Service discovery","viewpoint":""},{"id":"47c39686-e996-4550-b432-aa5786de2020","name":"Composite scalability strategy","viewpoint":""}]}