<?xml version="1.0" encoding="UTF-8"?><model xmlns="http://www.opengroup.org/xsd/archimate/3.0/" xmlns:xsi="http://www.w3.org/2001/XMLSchema-instance" identifier="_8x22YKoUEeqEM7mFKilpXw">  <name xml:lang="en">UASSISTER1920GENAPKLSANIM1810511053</name>  <elements>    <element xsi:type="SystemSoftware" identifier="_8yCdrKoUEeqEM7mFKilpXw">      <name xml:lang="en">Software</name>      <documentation/>    </element>    <element xsi:type="ApplicationService" identifier="_8yCdrqoUEeqEM7mFKilpXw">      <name xml:lang="en">SI Digital Library</name>      <documentation/>    </element>    <element xsi:type="ApplicationService" identifier="_8yCdsKoUEeqEM7mFKilpXw">      <name xml:lang="en">E – Learning</name>      <documentation/>    </element>    <element xsi:type="ApplicationService" identifier="_8yCdsqoUEeqEM7mFKilpXw">      <name xml:lang="en">SI Mahasiswa</name>      <documentation/>    </element>    <element xsi:type="ApplicationService" identifier="_8yCdtKoUEeqEM7mFKilpXw">      <name xml:lang="en">SI Alumni</name>      <documentation/>    </element>    <element xsi:type="ApplicationService" identifier="_8yCdtqoUEeqEM7mFKilpXw">      <name xml:lang="en">SI PPM</name>      <documentation/>    </element>    <element xsi:type="ApplicationService" identifier="_8yCduKoUEeqEM7mFKilpXw">      <name xml:lang="en">SI Akuntansi Keuangan</name>      <documentation/>    </element>    <element xsi:type="ApplicationService" identifier="_8yCduqoUEeqEM7mFKilpXw">      <name xml:lang="en">SI Kepegawaian</name>      <documentation/>    </element>    <element xsi:type="ApplicationService" identifier="_8yCdvKoUEeqEM7mFKilpXw">      <name xml:lang="en">SI Inventori</name>      <documentation/>    </element>    <element xsi:type="ApplicationService" identifier="_8yCdvqoUEeqEM7mFKilpXw">      <name xml:lang="en">SI Administrasi Umum</name>      <documentation/>    </element>    <element xsi:type="ApplicationService" identifier="_8yCdwKoUEeqEM7mFKilpXw">      <name xml:lang="en">SI Unit Bisnis</name>      <documentation/>    </element>    <element xsi:type="ApplicationService" identifier="_8yCdwqoUEeqEM7mFKilpXw">      <name xml:lang="en">SI Kerjasama</name>      <documentation/>    </element>    <element xsi:type="ApplicationService" identifier="_8yCdxKoUEeqEM7mFKilpXw">      <name xml:lang="en">SI Monitoring Data</name>      <documentation/>    </element>    <element xsi:type="ApplicationService" identifier="_8yCdxqoUEeqEM7mFKilpXw">      <name xml:lang="en">SI SATKER</name>      <documentation/>    </element>    <element xsi:type="ApplicationService" identifier="_8yCdyKoUEeqEM7mFKilpXw">      <name xml:lang="en">SI Akademik</name>      <documentation/>    </element>    <element xsi:type="ApplicationService" identifier="_8yCdyqoUEeqEM7mFKilpXw">      <name xml:lang="en">SI Penmaru</name>      <documentation/>    </element>    <element xsi:type="ApplicationComponent" identifier="_8yCdzKoUEeqEM7mFKilpXw">      <name xml:lang="en">Webapp Penmaru - penmaru</name>      <documentation/>    </element>    <element xsi:type="ApplicationComponent" identifier="_8yCdzqoUEeqEM7mFKilpXw">      <name xml:lang="en">DesktopApp Unissys</name>      <documentation/>    </element>    <element xsi:type="ApplicationComponent" identifier="_8yCd0KoUEeqEM7mFKilpXw">      <name xml:lang="en">WebApp Mahasiswa - Simawa</name>      <documentation/>    </element>    <element xsi:type="ApplicationComponent" identifier="_8yCd0qoUEeqEM7mFKilpXw">      <name xml:lang="en">WebApp Alumni - Tracer</name>      <documentation/>    </element>    <element xsi:type="ApplicationComponent" identifier="_8yCd1KoUEeqEM7mFKilpXw">      <name xml:lang="en">Web Moodle 3.0 - Elearning40</name>      <documentation/>    </element>    <element xsi:type="ApplicationComponent" identifier="_8yCd1qoUEeqEM7mFKilpXw">      <name xml:lang="en">Web SLIMS - Library</name>      <documentation/>    </element>    <element xsi:type="ApplicationComponent" identifier="_8yCd2KoUEeqEM7mFKilpXw">      <name xml:lang="en">WebKepegawaian</name>      <documentation/>    </element>    <element xsi:type="ApplicationComponent" identifier="_8yCd2qoUEeqEM7mFKilpXw">      <name xml:lang="en">DesktopApp Akuntansi - Siska</name>      <documentation/>    </element>    <element xsi:type="ApplicationComponent" identifier="_8yCd3KoUEeqEM7mFKilpXw">      <name xml:lang="en">WebApp Litabmas Simlitabmas</name>      <documentation/>    </element>    <element xsi:type="Node" identifier="_8yCd3qoUEeqEM7mFKilpXw">      <name xml:lang="en">Websvr Penmaru</name>      <documentation/>    </element>    <element xsi:type="TechnologyService" identifier="_8yCd4KoUEeqEM7mFKilpXw">      <name xml:lang="en">WebBrowser Penmaru</name>      <documentation/>    </element>    <element xsi:type="ApplicationComponent" identifier="_8yCd4qoUEeqEM7mFKilpXw">      <name xml:lang="en">DesktopApp  Penmaru</name>      <documentation/>    </element>    <element xsi:type="ApplicationComponent" identifier="_8yCd5KoUEeqEM7mFKilpXw">      <name xml:lang="en">Webapp Eprints.org - Repository</name>      <documentation/>    </element>    <element xsi:type="TechnologyService" identifier="_8yCd5qoUEeqEM7mFKilpXw">      <name xml:lang="en">PC Client Unissys</name>      <documentation/>    </element>    <element xsi:type="ApplicationComponent" identifier="_8yCd6KoUEeqEM7mFKilpXw">      <name xml:lang="en">Webapp Dosen - Dosen</name>      <documentation/>    </element>    <element xsi:type="ApplicationComponent" identifier="_8yCd6qoUEeqEM7mFKilpXw">      <name xml:lang="en">Webapp Akademik - Akademik</name>      <documentation/>    </element>    <element xsi:type="ApplicationComponent" identifier="_8yCd7KoUEeqEM7mFKilpXw">      <name xml:lang="en">Webapp Mahasiswa - Presma</name>      <documentation/>    </element>    <element xsi:type="ApplicationComponent" identifier="_8yCd7qoUEeqEM7mFKilpXw">      <name xml:lang="en">Webapp Persuratan - Etakah</name>      <documentation/>    </element>    <element xsi:type="ApplicationComponent" identifier="_8yCd8KoUEeqEM7mFKilpXw">      <name xml:lang="en">Webapp OJS - Ejournal</name>      <documentation/>    </element>    <element xsi:type="ApplicationComponent" identifier="_8yCd8qoUEeqEM7mFKilpXw">      <name xml:lang="en">Webapp OJS - Conference</name>      <documentation/>    </element>    <element xsi:type="ApplicationComponent" identifier="_8yCd9KoUEeqEM7mFKilpXw">      <name xml:lang="en">Webapp OCS - OCS</name>      <documentation/>    </element>    <element xsi:type="TechnologyService" identifier="_8yCd9qoUEeqEM7mFKilpXw">      <name xml:lang="en">WebBrowser Akademik</name>      <documentation/>    </element>    <element xsi:type="TechnologyService" identifier="_8yCd-KoUEeqEM7mFKilpXw">      <name xml:lang="en">PC Client Penmaru</name>      <documentation/>    </element>    <element xsi:type="TechnologyService" identifier="_8yCd-qoUEeqEM7mFKilpXw">      <name xml:lang="en">WebBrowser Presma</name>      <documentation/>    </element>    <element xsi:type="TechnologyService" identifier="_8yCd_KoUEeqEM7mFKilpXw">      <name xml:lang="en">WebBrowser Simawa</name>      <documentation/>    </element>    <element xsi:type="TechnologyService" identifier="_8yCd_qoUEeqEM7mFKilpXw">      <name xml:lang="en">WebBrowser Tracer</name>      <documentation/>    </element>    <element xsi:type="TechnologyService" identifier="_8yCeAKoUEeqEM7mFKilpXw">      <name xml:lang="en">WebBrowser Elearning40</name>      <documentation/>    </element>    <element xsi:type="TechnologyService" identifier="_8yCeAqoUEeqEM7mFKilpXw">      <name xml:lang="en">WebBrowser Library</name>      <documentation/>    </element>    <element xsi:type="TechnologyService" identifier="_8yCeBKoUEeqEM7mFKilpXw">      <name xml:lang="en">WebBrowser Repository</name>      <documentation/>    </element>    <element xsi:type="TechnologyService" identifier="_8yCeBqoUEeqEM7mFKilpXw">      <name xml:lang="en">WebBrowser Sevima</name>      <documentation/>    </element>    <element xsi:type="TechnologyService" identifier="_8yCeCKoUEeqEM7mFKilpXw">      <name xml:lang="en">WebBrowser Ejournal</name>      <documentation/>    </element>    <element xsi:type="TechnologyService" identifier="_8yCeCqoUEeqEM7mFKilpXw">      <name xml:lang="en">WebBrowser OCS</name>      <documentation/>    </element>    <element xsi:type="TechnologyService" identifier="_8yCeDKoUEeqEM7mFKilpXw">      <name xml:lang="en">WebBrowser Conference</name>      <documentation/>    </element>    <element xsi:type="TechnologyService" identifier="_8yCeDqoUEeqEM7mFKilpXw">      <name xml:lang="en">PC Siska</name>      <documentation/>    </element>    <element xsi:type="TechnologyService" identifier="_8yCeEKoUEeqEM7mFKilpXw">      <name xml:lang="en">WebBrowser Etakah</name>      <documentation/>    </element>    <element xsi:type="SystemSoftware" identifier="_8yCeEqoUEeqEM7mFKilpXw">      <name xml:lang="en">PHP 6.x</name>      <documentation/>    </element>    <element xsi:type="SystemSoftware" identifier="_8yCeFKoUEeqEM7mFKilpXw">      <name xml:lang="en">PHP 7.x</name>      <documentation/>    </element>    <element xsi:type="SystemSoftware" identifier="_8yCeFqoUEeqEM7mFKilpXw">      <name xml:lang="en">Postgresql 8.x</name>      <documentation/>    </element>    <element xsi:type="SystemSoftware" identifier="_8yCeGKoUEeqEM7mFKilpXw">      <name xml:lang="en">Postgresql 6.x</name>      <documentation/>    </element>    <element xsi:type="Node" identifier="_8yCeGqoUEeqEM7mFKilpXw">      <name xml:lang="en">DBsvr Unisys</name>      <documentation/>    </element>    <element xsi:type="Node" identifier="_8yCeHKoUEeqEM7mFKilpXw">      <name xml:lang="en">Websvr Kemahasiswaan</name>      <documentation/>    </element>    <element xsi:type="Node" identifier="_8yCeHqoUEeqEM7mFKilpXw">      <name xml:lang="en">Websvr Akademik</name>      <documentation/>    </element>    <element xsi:type="SystemSoftware" identifier="_8yCeIKoUEeqEM7mFKilpXw">      <name xml:lang="en">PHP 7.x</name>      <documentation/>    </element>    <element xsi:type="SystemSoftware" identifier="_8yCeIqoUEeqEM7mFKilpXw">      <name xml:lang="en">Postgresql 6.x</name>      <documentation/>    </element>    <element xsi:type="Node" identifier="_8yCeJKoUEeqEM7mFKilpXw">      <name xml:lang="en">Websvr Tracer</name>      <documentation/>    </element>    <element xsi:type="SystemSoftware" identifier="_8yCeJqoUEeqEM7mFKilpXw">      <name xml:lang="en">Python 3.x</name>      <documentation/>    </element>    <element xsi:type="SystemSoftware" identifier="_8yCeKKoUEeqEM7mFKilpXw">      <name xml:lang="en">Postgresql 6.x</name>      <documentation/>    </element>    <element xsi:type="Node" identifier="_8yCeKqoUEeqEM7mFKilpXw">      <name xml:lang="en">Websvr Tracer</name>      <documentation/>    </element>    <element xsi:type="Node" identifier="_8yCeLKoUEeqEM7mFKilpXw">      <name xml:lang="en">DBsvr Tracer</name>      <documentation/>    </element>    <element xsi:type="SystemSoftware" identifier="_8yCeLqoUEeqEM7mFKilpXw">      <name xml:lang="en">PHP 7.x</name>      <documentation/>    </element>    <element xsi:type="SystemSoftware" identifier="_8yCeMKoUEeqEM7mFKilpXw">      <name xml:lang="en">Postgresql 9.x</name>      <documentation/>    </element>    <element xsi:type="Node" identifier="_8yCeMqoUEeqEM7mFKilpXw">      <name xml:lang="en">Websvr Tracer</name>      <documentation/>    </element>    <element xsi:type="SystemSoftware" identifier="_8yCeNKoUEeqEM7mFKilpXw">      <name xml:lang="en">Postgresql 9.x</name>      <documentation/>    </element>    <element xsi:type="SystemSoftware" identifier="_8yCeNqoUEeqEM7mFKilpXw">      <name xml:lang="en">PHP 7.x</name>      <documentation/>    </element>    <element xsi:type="Node" identifier="_8yCeOKoUEeqEM7mFKilpXw">      <name xml:lang="en">Websvr Repository</name>      <documentation/>    </element>    <element xsi:type="SystemSoftware" identifier="_8yCeOqoUEeqEM7mFKilpXw">      <name xml:lang="en">PHP 7.x</name>      <documentation/>    </element>    <element xsi:type="SystemSoftware" identifier="_8yCePKoUEeqEM7mFKilpXw">      <name xml:lang="en">Postgresql 9.x</name>      <documentation/>    </element>    <element xsi:type="Node" identifier="_8yCePqoUEeqEM7mFKilpXw">      <name xml:lang="en">Websvr Repository</name>      <documentation/>    </element>    <element xsi:type="SystemSoftware" identifier="_8yCeQKoUEeqEM7mFKilpXw">      <name xml:lang="en">PHP 7.x</name>      <documentation/>    </element>    <element xsi:type="SystemSoftware" identifier="_8yCeQqoUEeqEM7mFKilpXw">      <name xml:lang="en">Postgresql 9.x</name>      <documentation/>    </element>    <element xsi:type="Node" identifier="_8yCeRKoUEeqEM7mFKilpXw">      <name xml:lang="en">Websvr Ejournal</name>      <documentation/>    </element>    <element xsi:type="SystemSoftware" identifier="_8yCeRqoUEeqEM7mFKilpXw">      <name xml:lang="en">PHP 6.x</name>      <documentation/>    </element>    <element xsi:type="SystemSoftware" identifier="_8yCeSKoUEeqEM7mFKilpXw">      <name xml:lang="en">MySQL 8.x</name>      <documentation/>    </element>    <element xsi:type="Node" identifier="_8yCeSqoUEeqEM7mFKilpXw">      <name xml:lang="en">Websvr OCS</name>      <documentation/>    </element>    <element xsi:type="SystemSoftware" identifier="_8yCeTKoUEeqEM7mFKilpXw">      <name xml:lang="en">PHP 6.x</name>      <documentation/>    </element>    <element xsi:type="SystemSoftware" identifier="_8yCeTqoUEeqEM7mFKilpXw">      <name xml:lang="en">MySQL 8.x</name>      <documentation/>    </element>    <element xsi:type="Node" identifier="_8yCeUKoUEeqEM7mFKilpXw">      <name xml:lang="en">Websvr Conference</name>      <documentation/>    </element>    <element xsi:type="SystemSoftware" identifier="_8yCeUqoUEeqEM7mFKilpXw">      <name xml:lang="en">MySQL 8.x</name>      <documentation/>    </element>    <element xsi:type="SystemSoftware" identifier="_8yCeVKoUEeqEM7mFKilpXw">      <name xml:lang="en">PHP 6.x</name>      <documentation/>    </element>    <element xsi:type="Node" identifier="_8yCeVqoUEeqEM7mFKilpXw">      <name xml:lang="en">DBsvr Siska</name>      <documentation/>    </element>    <element xsi:type="SystemSoftware" identifier="_8yCeWKoUEeqEM7mFKilpXw">      <name xml:lang="en">Oracle 9.x</name>      <documentation/>    </element>    <element xsi:type="Node" identifier="_8yCeWqoUEeqEM7mFKilpXw">      <name xml:lang="en">Websvr Etakah</name>      <documentation/>    </element>    <element xsi:type="SystemSoftware" identifier="_8yCeXKoUEeqEM7mFKilpXw">      <name xml:lang="en">MySQL 8.x</name>      <documentation/>    </element>    <element xsi:type="SystemSoftware" identifier="_8yCeXqoUEeqEM7mFKilpXw">      <name xml:lang="en">PHP 6.x</name>      <documentation/>    </element>    <element xsi:type="BusinessProcess" identifier="_8yCeYKoUEeqEM7mFKilpXw">      <name xml:lang="en">Pelaporan Kesiapan Akreditasi Semester</name>      <documentation/>    </element>    <element xsi:type="BusinessProcess" identifier="_8yCeYqoUEeqEM7mFKilpXw">      <name xml:lang="en">Pelaporan Ormawa Semester</name>      <documentation/>    </element>    <element xsi:type="BusinessProcess" identifier="_8yCeZKoUEeqEM7mFKilpXw">      <name xml:lang="en">Perencanaan Keuangan Bulanan</name>      <documentation/>    </element>    <element xsi:type="BusinessProcess" identifier="_8yCeZqoUEeqEM7mFKilpXw">      <name xml:lang="en">Pelaporan Keuangan Bulanan</name>      <documentation/>    </element>    <element xsi:type="BusinessProcess" identifier="_8yCeaKoUEeqEM7mFKilpXw">      <name xml:lang="en">Perencanaan Inovasi Semester</name>      <documentation/>    </element>    <element xsi:type="BusinessProcess" identifier="_8yCeaqoUEeqEM7mFKilpXw">      <name xml:lang="en">Perencanaan Kerjasama Bulanan</name>      <documentation/>    </element>    <element xsi:type="BusinessProcess" identifier="_8yCebKoUEeqEM7mFKilpXw">      <name xml:lang="en">Pelaporan Akademik Bulanan</name>      <documentation/>    </element>    <element xsi:type="BusinessProcess" identifier="_8yCebqoUEeqEM7mFKilpXw">      <name xml:lang="en">Perencanaan  Ormawa Semester</name>      <documentation/>    </element>    <element xsi:type="BusinessProcess" identifier="_8yCecKoUEeqEM7mFKilpXw">      <name xml:lang="en">Perencanaan Akademik Bulanan</name>      <documentation/>    </element>    <element xsi:type="BusinessProcess" identifier="_8yCecqoUEeqEM7mFKilpXw">      <name xml:lang="en">Perencanaan Kesiapan Akreditasi Semester</name>      <documentation/>    </element>    <element xsi:type="BusinessProcess" identifier="_8yCedKoUEeqEM7mFKilpXw">      <name xml:lang="en">Pelaporan Inovasi Semester</name>      <documentation/>    </element>    <element xsi:type="BusinessProcess" identifier="_8yCedqoUEeqEM7mFKilpXw">      <name xml:lang="en">Pelaporan Kerjasama Bulanan</name>      <documentation/>    </element>    <element xsi:type="ApplicationService" identifier="_8yCeeKoUEeqEM7mFKilpXw">      <name xml:lang="en">Central Authentication 1234567890</name>      <documentation/>    </element>    <element xsi:type="ApplicationComponent" identifier="_8yCeeqoUEeqEM7mFKilpXw">      <name xml:lang="en">OAuth Server 1234567890</name>      <documentation/>    </element>    <element xsi:type="TechnologyFunction" identifier="_8yCefKoUEeqEM7mFKilpXw">      <name xml:lang="en">Function</name>      <documentation/>    </element>  </elements>  <relationships>    <relationship xsi:type="Realization" identifier="_8yCefqoUEeqEM7mFKilpXw" source="_8yCd2qoUEeqEM7mFKilpXw" target="_8yCduKoUEeqEM7mFKilpXw">      <name xml:lang="en"/>      <documentation/>    </relationship>    <relationship xsi:type="Realization" identifier="_8yCegKoUEeqEM7mFKilpXw" source="_8yCd1qoUEeqEM7mFKilpXw" target="_8yCdrqoUEeqEM7mFKilpXw">      <name xml:lang="en"/>      <documentation/>    </relationship>    <relationship xsi:type="Realization" identifier="_8yCegqoUEeqEM7mFKilpXw" source="_8yCd1KoUEeqEM7mFKilpXw" target="_8yCdsKoUEeqEM7mFKilpXw">      <name xml:lang="en"/>      <documentation/>    </relationship>    <relationship xsi:type="Realization" identifier="_8yCehKoUEeqEM7mFKilpXw" source="_8yCd0qoUEeqEM7mFKilpXw" target="_8yCdtKoUEeqEM7mFKilpXw">      <name xml:lang="en"/>      <documentation/>    </relationship>    <relationship xsi:type="Realization" identifier="_8yDDoaoUEeqEM7mFKilpXw" source="_8yCd0KoUEeqEM7mFKilpXw" target="_8yCdsqoUEeqEM7mFKilpXw">      <name xml:lang="en"/>      <documentation/>    </relationship>    <relationship xsi:type="Realization" identifier="_8yDDo6oUEeqEM7mFKilpXw" source="_8yCdzKoUEeqEM7mFKilpXw" target="_8yCdyqoUEeqEM7mFKilpXw">      <name xml:lang="en"/>      <documentation/>    </relationship>    <relationship xsi:type="Realization" identifier="_8yDDpaoUEeqEM7mFKilpXw" source="_8yCd4qoUEeqEM7mFKilpXw" target="_8yCdyqoUEeqEM7mFKilpXw">      <name xml:lang="en"/>      <documentation/>    </relationship>    <relationship xsi:type="Realization" identifier="_8yDDp6oUEeqEM7mFKilpXw" source="_8yCd3KoUEeqEM7mFKilpXw" target="_8yCdtqoUEeqEM7mFKilpXw">      <name xml:lang="en"/>      <documentation/>    </relationship>    <relationship xsi:type="Realization" identifier="_8yDDqaoUEeqEM7mFKilpXw" source="_8yCd2KoUEeqEM7mFKilpXw" target="_8yCduqoUEeqEM7mFKilpXw">      <name xml:lang="en"/>      <documentation/>    </relationship>    <relationship xsi:type="Realization" identifier="_8yDDq6oUEeqEM7mFKilpXw" source="_8yCd5KoUEeqEM7mFKilpXw" target="_8yCdrqoUEeqEM7mFKilpXw">      <name xml:lang="en"/>      <documentation/>    </relationship>    <relationship xsi:type="Realization" identifier="_8yDDraoUEeqEM7mFKilpXw" source="_8yCd7KoUEeqEM7mFKilpXw" target="_8yCdsqoUEeqEM7mFKilpXw">      <name xml:lang="en"/>      <documentation/>    </relationship>    <relationship xsi:type="Realization" identifier="_8yDDr6oUEeqEM7mFKilpXw" source="_8yCd7qoUEeqEM7mFKilpXw" target="_8yCdvqoUEeqEM7mFKilpXw">      <name xml:lang="en"/>      <documentation/>    </relationship>    <relationship xsi:type="Realization" identifier="_8yDDsaoUEeqEM7mFKilpXw" source="_8yCd6qoUEeqEM7mFKilpXw" target="_8yCdyKoUEeqEM7mFKilpXw">      <name xml:lang="en"/>      <documentation/>    </relationship>    <relationship xsi:type="Realization" identifier="_8yDDs6oUEeqEM7mFKilpXw" source="_8yCd6KoUEeqEM7mFKilpXw" target="_8yCdyKoUEeqEM7mFKilpXw">      <name xml:lang="en"/>      <documentation/>    </relationship>    <relationship xsi:type="Serving" identifier="_8yDDtaoUEeqEM7mFKilpXw" source="_8yCd4KoUEeqEM7mFKilpXw" target="_8yCdzKoUEeqEM7mFKilpXw">      <name xml:lang="en"/>      <documentation/>    </relationship>    <relationship xsi:type="Serving" identifier="_8yDDt6oUEeqEM7mFKilpXw" source="_8yCd9qoUEeqEM7mFKilpXw" target="_8yCd6qoUEeqEM7mFKilpXw">      <name xml:lang="en"/>      <documentation/>    </relationship>    <relationship xsi:type="Serving" identifier="_8yDDuaoUEeqEM7mFKilpXw" source="_8yCd9qoUEeqEM7mFKilpXw" target="_8yCd6KoUEeqEM7mFKilpXw">      <name xml:lang="en"/>      <documentation/>    </relationship>    <relationship xsi:type="Serving" identifier="_8yDDu6oUEeqEM7mFKilpXw" source="_8yCd_KoUEeqEM7mFKilpXw" target="_8yCd0KoUEeqEM7mFKilpXw">      <name xml:lang="en"/>      <documentation/>    </relationship>    <relationship xsi:type="Serving" identifier="_8yDDvaoUEeqEM7mFKilpXw" source="_8yCd-qoUEeqEM7mFKilpXw" target="_8yCd7KoUEeqEM7mFKilpXw">      <name xml:lang="en"/>      <documentation/>    </relationship>    <relationship xsi:type="Serving" identifier="_8yDDv6oUEeqEM7mFKilpXw" source="_8yCd5qoUEeqEM7mFKilpXw" target="_8yCdzqoUEeqEM7mFKilpXw">      <name xml:lang="en"/>      <documentation/>    </relationship>    <relationship xsi:type="Serving" identifier="_8yDDwaoUEeqEM7mFKilpXw" source="_8yCd-KoUEeqEM7mFKilpXw" target="_8yCd4qoUEeqEM7mFKilpXw">      <name xml:lang="en"/>      <documentation/>    </relationship>    <relationship xsi:type="Serving" identifier="_8yDDw6oUEeqEM7mFKilpXw" source="_8yCeAKoUEeqEM7mFKilpXw" target="_8yCd1KoUEeqEM7mFKilpXw">      <name xml:lang="en"/>      <documentation/>    </relationship>    <relationship xsi:type="Serving" identifier="_8yDDxaoUEeqEM7mFKilpXw" source="_8yCeAqoUEeqEM7mFKilpXw" target="_8yCd1qoUEeqEM7mFKilpXw">      <name xml:lang="en"/>      <documentation/>    </relationship>    <relationship xsi:type="Serving" identifier="_8yDDx6oUEeqEM7mFKilpXw" source="_8yCeBKoUEeqEM7mFKilpXw" target="_8yCd5KoUEeqEM7mFKilpXw">      <name xml:lang="en"/>      <documentation/>    </relationship>    <relationship xsi:type="Serving" identifier="_8yDDyaoUEeqEM7mFKilpXw" source="_8yCeBqoUEeqEM7mFKilpXw" target="_8yCd2KoUEeqEM7mFKilpXw">      <name xml:lang="en"/>      <documentation/>    </relationship>    <relationship xsi:type="Serving" identifier="_8yDDy6oUEeqEM7mFKilpXw" source="_8yCeBqoUEeqEM7mFKilpXw" target="_8yCd3KoUEeqEM7mFKilpXw">      <name xml:lang="en"/>      <documentation/>    </relationship>    <relationship xsi:type="Serving" identifier="_8yDDzaoUEeqEM7mFKilpXw" source="_8yCeDqoUEeqEM7mFKilpXw" target="_8yCd2qoUEeqEM7mFKilpXw">      <name xml:lang="en"/>      <documentation/>    </relationship>    <relationship xsi:type="Serving" identifier="_8yDDz6oUEeqEM7mFKilpXw" source="_8yCeDKoUEeqEM7mFKilpXw" target="_8yCd8qoUEeqEM7mFKilpXw">      <name xml:lang="en"/>      <documentation/>    </relationship>    <relationship xsi:type="Serving" identifier="_8yDD0aoUEeqEM7mFKilpXw" source="_8yCeCqoUEeqEM7mFKilpXw" target="_8yCd9KoUEeqEM7mFKilpXw">      <name xml:lang="en"/>      <documentation/>    </relationship>    <relationship xsi:type="Serving" identifier="_8yDD06oUEeqEM7mFKilpXw" source="_8yCeCKoUEeqEM7mFKilpXw" target="_8yCd8KoUEeqEM7mFKilpXw">      <name xml:lang="en"/>      <documentation/>    </relationship>    <relationship xsi:type="Serving" identifier="_8yDD1aoUEeqEM7mFKilpXw" source="_8yCeEKoUEeqEM7mFKilpXw" target="_8yCd7qoUEeqEM7mFKilpXw">      <name xml:lang="en"/>      <documentation/>    </relationship>    <relationship xsi:type="Aggregation" identifier="_8yDD16oUEeqEM7mFKilpXw" source="_8yCd3qoUEeqEM7mFKilpXw" target="_8yCeEqoUEeqEM7mFKilpXw">      <name xml:lang="en"/>      <documentation/>    </relationship>    <relationship xsi:type="Realization" identifier="_8yDD2aoUEeqEM7mFKilpXw" source="_8yCd3qoUEeqEM7mFKilpXw" target="_8yCd4KoUEeqEM7mFKilpXw">      <name xml:lang="en"/>      <documentation/>    </relationship>    <relationship xsi:type="Aggregation" identifier="_8yDD26oUEeqEM7mFKilpXw" source="_8yCeGqoUEeqEM7mFKilpXw" target="_8yCeGKoUEeqEM7mFKilpXw">      <name xml:lang="en"/>      <documentation/>    </relationship>    <relationship xsi:type="Realization" identifier="_8yDD3aoUEeqEM7mFKilpXw" source="_8yCeGqoUEeqEM7mFKilpXw" target="_8yCd5qoUEeqEM7mFKilpXw">      <name xml:lang="en"/>      <documentation/>    </relationship>    <relationship xsi:type="Realization" identifier="_8yDD36oUEeqEM7mFKilpXw" source="_8yCeHqoUEeqEM7mFKilpXw" target="_8yCd9qoUEeqEM7mFKilpXw">      <name xml:lang="en"/>      <documentation/>    </relationship>    <relationship xsi:type="Serving" identifier="_8yDD4aoUEeqEM7mFKilpXw" source="_8yCeGqoUEeqEM7mFKilpXw" target="_8yCeHqoUEeqEM7mFKilpXw">      <name xml:lang="en"/>      <documentation/>    </relationship>    <relationship xsi:type="Aggregation" identifier="_8yDD46oUEeqEM7mFKilpXw" source="_8yCeHqoUEeqEM7mFKilpXw" target="_8yCeFKoUEeqEM7mFKilpXw">      <name xml:lang="en"/>      <documentation/>    </relationship>    <relationship xsi:type="Realization" identifier="_8yDD5aoUEeqEM7mFKilpXw" source="_8yCeHKoUEeqEM7mFKilpXw" target="_8yCd-qoUEeqEM7mFKilpXw">      <name xml:lang="en"/>      <documentation/>    </relationship>    <relationship xsi:type="Aggregation" identifier="_8yDD56oUEeqEM7mFKilpXw" source="_8yCeHKoUEeqEM7mFKilpXw" target="_8yCeIKoUEeqEM7mFKilpXw">      <name xml:lang="en"/>      <documentation/>    </relationship>    <relationship xsi:type="Serving" identifier="_8yDD6aoUEeqEM7mFKilpXw" source="_8yCd_qoUEeqEM7mFKilpXw" target="_8yCd0qoUEeqEM7mFKilpXw">      <name xml:lang="en"/>      <documentation/>    </relationship>    <relationship xsi:type="Realization" identifier="_8yDD66oUEeqEM7mFKilpXw" source="_8yCeJKoUEeqEM7mFKilpXw" target="_8yCd_qoUEeqEM7mFKilpXw">      <name xml:lang="en"/>      <documentation/>    </relationship>    <relationship xsi:type="Aggregation" identifier="_8yDD7aoUEeqEM7mFKilpXw" source="_8yCeJKoUEeqEM7mFKilpXw" target="_8yCeJqoUEeqEM7mFKilpXw">      <name xml:lang="en"/>      <documentation/>    </relationship>    <relationship xsi:type="Realization" identifier="_8yDD76oUEeqEM7mFKilpXw" source="_8yCeHKoUEeqEM7mFKilpXw" target="_8yCd_KoUEeqEM7mFKilpXw">      <name xml:lang="en"/>      <documentation/>    </relationship>    <relationship xsi:type="Serving" identifier="_8yDD8aoUEeqEM7mFKilpXw" source="_8yCeLKoUEeqEM7mFKilpXw" target="_8yCeKqoUEeqEM7mFKilpXw">      <name xml:lang="en"/>      <documentation/>    </relationship>    <relationship xsi:type="Aggregation" identifier="_8yDD86oUEeqEM7mFKilpXw" source="_8yCeKqoUEeqEM7mFKilpXw" target="_8yCeLqoUEeqEM7mFKilpXw">      <name xml:lang="en"/>      <documentation/>    </relationship>    <relationship xsi:type="Aggregation" identifier="_8yDD9aoUEeqEM7mFKilpXw" source="_8yCeLKoUEeqEM7mFKilpXw" target="_8yCeMKoUEeqEM7mFKilpXw">      <name xml:lang="en"/>      <documentation/>    </relationship>    <relationship xsi:type="Realization" identifier="_8yDD96oUEeqEM7mFKilpXw" source="_8yCeKqoUEeqEM7mFKilpXw" target="_8yCeAKoUEeqEM7mFKilpXw">      <name xml:lang="en"/>      <documentation/>    </relationship>    <relationship xsi:type="Realization" identifier="_8yDD-aoUEeqEM7mFKilpXw" source="_8yCd3qoUEeqEM7mFKilpXw" target="_8yCd-KoUEeqEM7mFKilpXw">      <name xml:lang="en"/>      <documentation/>    </relationship>    <relationship xsi:type="Aggregation" identifier="_8yDD-6oUEeqEM7mFKilpXw" source="_8yCd3qoUEeqEM7mFKilpXw" target="_8yCeFqoUEeqEM7mFKilpXw">      <name xml:lang="en"/>      <documentation/>    </relationship>    <relationship xsi:type="Aggregation" identifier="_8yDD_aoUEeqEM7mFKilpXw" source="_8yCeHKoUEeqEM7mFKilpXw" target="_8yCeIqoUEeqEM7mFKilpXw">      <name xml:lang="en"/>      <documentation/>    </relationship>    <relationship xsi:type="Aggregation" identifier="_8yDD_6oUEeqEM7mFKilpXw" source="_8yCeJKoUEeqEM7mFKilpXw" target="_8yCeKKoUEeqEM7mFKilpXw">      <name xml:lang="en"/>      <documentation/>    </relationship>    <relationship xsi:type="Realization" identifier="_8yDEAaoUEeqEM7mFKilpXw" source="_8yCeMqoUEeqEM7mFKilpXw" target="_8yCeAqoUEeqEM7mFKilpXw">      <name xml:lang="en"/>      <documentation/>    </relationship>    <relationship xsi:type="Aggregation" identifier="_8yDEA6oUEeqEM7mFKilpXw" source="_8yCeMqoUEeqEM7mFKilpXw" target="_8yCeNqoUEeqEM7mFKilpXw">      <name xml:lang="en"/>      <documentation/>    </relationship>    <relationship xsi:type="Aggregation" identifier="_8yDEBaoUEeqEM7mFKilpXw" source="_8yCeMqoUEeqEM7mFKilpXw" target="_8yCeNKoUEeqEM7mFKilpXw">      <name xml:lang="en"/>      <documentation/>    </relationship>    <relationship xsi:type="Aggregation" identifier="_8yDEB6oUEeqEM7mFKilpXw" source="_8yCeOKoUEeqEM7mFKilpXw" target="_8yCeOqoUEeqEM7mFKilpXw">      <name xml:lang="en"/>      <documentation/>    </relationship>    <relationship xsi:type="Aggregation" identifier="_8yDECaoUEeqEM7mFKilpXw" source="_8yCeOKoUEeqEM7mFKilpXw" target="_8yCePKoUEeqEM7mFKilpXw">      <name xml:lang="en"/>      <documentation/>    </relationship>    <relationship xsi:type="Realization" identifier="_8yDEC6oUEeqEM7mFKilpXw" source="_8yCeOKoUEeqEM7mFKilpXw" target="_8yCeBKoUEeqEM7mFKilpXw">      <name xml:lang="en"/>      <documentation/>    </relationship>    <relationship xsi:type="Aggregation" identifier="_8yDEDaoUEeqEM7mFKilpXw" source="_8yCePqoUEeqEM7mFKilpXw" target="_8yCeQKoUEeqEM7mFKilpXw">      <name xml:lang="en"/>      <documentation/>    </relationship>    <relationship xsi:type="Aggregation" identifier="_8yDED6oUEeqEM7mFKilpXw" source="_8yCePqoUEeqEM7mFKilpXw" target="_8yCeQqoUEeqEM7mFKilpXw">      <name xml:lang="en"/>      <documentation/>    </relationship>    <relationship xsi:type="Realization" identifier="_8yDEEaoUEeqEM7mFKilpXw" source="_8yCePqoUEeqEM7mFKilpXw" target="_8yCeBqoUEeqEM7mFKilpXw">      <name xml:lang="en"/>      <documentation/>    </relationship>    <relationship xsi:type="Aggregation" identifier="_8yDEE6oUEeqEM7mFKilpXw" source="_8yCeRKoUEeqEM7mFKilpXw" target="_8yCeRqoUEeqEM7mFKilpXw">      <name xml:lang="en"/>      <documentation/>    </relationship>    <relationship xsi:type="Aggregation" identifier="_8yDEFaoUEeqEM7mFKilpXw" source="_8yCeRKoUEeqEM7mFKilpXw" target="_8yCeSKoUEeqEM7mFKilpXw">      <name xml:lang="en"/>      <documentation/>    </relationship>    <relationship xsi:type="Aggregation" identifier="_8yDEF6oUEeqEM7mFKilpXw" source="_8yCeSqoUEeqEM7mFKilpXw" target="_8yCeTKoUEeqEM7mFKilpXw">      <name xml:lang="en"/>      <documentation/>    </relationship>    <relationship xsi:type="Aggregation" identifier="_8yDEGaoUEeqEM7mFKilpXw" source="_8yCeSqoUEeqEM7mFKilpXw" target="_8yCeTqoUEeqEM7mFKilpXw">      <name xml:lang="en"/>      <documentation/>    </relationship>    <relationship xsi:type="Aggregation" identifier="_8yDEG6oUEeqEM7mFKilpXw" source="_8yCeUKoUEeqEM7mFKilpXw" target="_8yCeVKoUEeqEM7mFKilpXw">      <name xml:lang="en"/>      <documentation/>    </relationship>    <relationship xsi:type="Aggregation" identifier="_8yDEHaoUEeqEM7mFKilpXw" source="_8yCeUKoUEeqEM7mFKilpXw" target="_8yCeUqoUEeqEM7mFKilpXw">      <name xml:lang="en"/>      <documentation/>    </relationship>    <relationship xsi:type="Realization" identifier="_8yDEH6oUEeqEM7mFKilpXw" source="_8yCeUKoUEeqEM7mFKilpXw" target="_8yCeDKoUEeqEM7mFKilpXw">      <name xml:lang="en"/>      <documentation/>    </relationship>    <relationship xsi:type="Realization" identifier="_8yDEIaoUEeqEM7mFKilpXw" source="_8yCeSqoUEeqEM7mFKilpXw" target="_8yCeCqoUEeqEM7mFKilpXw">      <name xml:lang="en"/>      <documentation/>    </relationship>    <relationship xsi:type="Realization" identifier="_8yDEI6oUEeqEM7mFKilpXw" source="_8yCeRKoUEeqEM7mFKilpXw" target="_8yCeCKoUEeqEM7mFKilpXw">      <name xml:lang="en"/>      <documentation/>    </relationship>    <relationship xsi:type="Aggregation" identifier="_8yDEJaoUEeqEM7mFKilpXw" source="_8yCeVqoUEeqEM7mFKilpXw" target="_8yCeWKoUEeqEM7mFKilpXw">      <name xml:lang="en"/>      <documentation/>    </relationship>    <relationship xsi:type="Realization" identifier="_8yDEJ6oUEeqEM7mFKilpXw" source="_8yCeVqoUEeqEM7mFKilpXw" target="_8yCeDqoUEeqEM7mFKilpXw">      <name xml:lang="en"/>      <documentation/>    </relationship>    <relationship xsi:type="Realization" identifier="_8yDEKaoUEeqEM7mFKilpXw" source="_8yCd8KoUEeqEM7mFKilpXw" target="_8yCdtqoUEeqEM7mFKilpXw">      <name xml:lang="en"/>      <documentation/>    </relationship>    <relationship xsi:type="Aggregation" identifier="_8yDEK6oUEeqEM7mFKilpXw" source="_8yCeWqoUEeqEM7mFKilpXw" target="_8yCeXqoUEeqEM7mFKilpXw">      <name xml:lang="en"/>      <documentation/>    </relationship>    <relationship xsi:type="Aggregation" identifier="_8yDELaoUEeqEM7mFKilpXw" source="_8yCeWqoUEeqEM7mFKilpXw" target="_8yCeXKoUEeqEM7mFKilpXw">      <name xml:lang="en"/>      <documentation/>    </relationship>    <relationship xsi:type="Realization" identifier="_8yDEL6oUEeqEM7mFKilpXw" source="_8yCeWqoUEeqEM7mFKilpXw" target="_8yCeEKoUEeqEM7mFKilpXw">      <name xml:lang="en"/>      <documentation/>    </relationship>    <relationship xsi:type="Serving" identifier="_8yDEMaoUEeqEM7mFKilpXw" source="_8yCdyqoUEeqEM7mFKilpXw" target="_8yCeYKoUEeqEM7mFKilpXw">      <name xml:lang="en"/>      <documentation/>    </relationship>    <relationship xsi:type="Serving" identifier="_8yDEM6oUEeqEM7mFKilpXw" source="_8yCdyKoUEeqEM7mFKilpXw" target="_8yCeYKoUEeqEM7mFKilpXw">      <name xml:lang="en"/>      <documentation/>    </relationship>    <relationship xsi:type="Serving" identifier="_8yDENaoUEeqEM7mFKilpXw" source="_8yCdsqoUEeqEM7mFKilpXw" target="_8yCeYKoUEeqEM7mFKilpXw">      <name xml:lang="en"/>      <documentation/>    </relationship>    <relationship xsi:type="Serving" identifier="_8yDEN6oUEeqEM7mFKilpXw" source="_8yCdtKoUEeqEM7mFKilpXw" target="_8yCeYKoUEeqEM7mFKilpXw">      <name xml:lang="en"/>      <documentation/>    </relationship>    <relationship xsi:type="Serving" identifier="_8yDEOaoUEeqEM7mFKilpXw" source="_8yCdsKoUEeqEM7mFKilpXw" target="_8yCeYKoUEeqEM7mFKilpXw">      <name xml:lang="en"/>      <documentation/>    </relationship>    <relationship xsi:type="Serving" identifier="_8yDEO6oUEeqEM7mFKilpXw" source="_8yCdrqoUEeqEM7mFKilpXw" target="_8yCeYKoUEeqEM7mFKilpXw">      <name xml:lang="en"/>      <documentation/>    </relationship>    <relationship xsi:type="Serving" identifier="_8yDEPaoUEeqEM7mFKilpXw" source="_8yCduqoUEeqEM7mFKilpXw" target="_8yCeYKoUEeqEM7mFKilpXw">      <name xml:lang="en"/>      <documentation/>    </relationship>    <relationship xsi:type="Serving" identifier="_8yDEP6oUEeqEM7mFKilpXw" source="_8yCdtqoUEeqEM7mFKilpXw" target="_8yCeYKoUEeqEM7mFKilpXw">      <name xml:lang="en"/>      <documentation/>    </relationship>    <relationship xsi:type="Serving" identifier="_8yDEQaoUEeqEM7mFKilpXw" source="_8yCduKoUEeqEM7mFKilpXw" target="_8yCeYKoUEeqEM7mFKilpXw">      <name xml:lang="en"/>      <documentation/>    </relationship>    <relationship xsi:type="Serving" identifier="_8yDEQ6oUEeqEM7mFKilpXw" source="_8yCdvqoUEeqEM7mFKilpXw" target="_8yCeYKoUEeqEM7mFKilpXw">      <name xml:lang="en"/>      <documentation/>    </relationship>    <relationship xsi:type="Serving" identifier="_8yDERaoUEeqEM7mFKilpXw" source="_8yCdvKoUEeqEM7mFKilpXw" target="_8yCeYKoUEeqEM7mFKilpXw">      <name xml:lang="en"/>      <documentation/>    </relationship>    <relationship xsi:type="Serving" identifier="_8yDER6oUEeqEM7mFKilpXw" source="_8yCdwqoUEeqEM7mFKilpXw" target="_8yCeYKoUEeqEM7mFKilpXw">      <name xml:lang="en"/>      <documentation/>    </relationship>    <relationship xsi:type="Serving" identifier="_8yDESaoUEeqEM7mFKilpXw" source="_8yCdwKoUEeqEM7mFKilpXw" target="_8yCeYKoUEeqEM7mFKilpXw">      <name xml:lang="en"/>      <documentation/>    </relationship>    <relationship xsi:type="Realization" identifier="_8yDES6oUEeqEM7mFKilpXw" source="_8yCd9KoUEeqEM7mFKilpXw" target="_8yCdtqoUEeqEM7mFKilpXw">      <name xml:lang="en"/>      <documentation/>    </relationship>    <relationship xsi:type="Realization" identifier="_8yDETaoUEeqEM7mFKilpXw" source="_8yCd8qoUEeqEM7mFKilpXw" target="_8yCdtqoUEeqEM7mFKilpXw">      <name xml:lang="en"/>      <documentation/>    </relationship>    <relationship xsi:type="Serving" identifier="_8yDET6oUEeqEM7mFKilpXw" source="_8yCdxKoUEeqEM7mFKilpXw" target="_8yCeYKoUEeqEM7mFKilpXw">      <name xml:lang="en"/>      <documentation/>    </relationship>    <relationship xsi:type="Serving" identifier="_8yDEUaoUEeqEM7mFKilpXw" source="_8yCdxqoUEeqEM7mFKilpXw" target="_8yCeYKoUEeqEM7mFKilpXw">      <name xml:lang="en"/>      <documentation/>    </relationship>    <relationship xsi:type="Realization" identifier="_8yDEU6oUEeqEM7mFKilpXw" source="_8yCeeqoUEeqEM7mFKilpXw" target="_8yCeeKoUEeqEM7mFKilpXw">      <name xml:lang="en"/>      <documentation/>    </relationship>    <relationship xsi:type="Realization" identifier="_8yDEVaoUEeqEM7mFKilpXw" source="_8yCeeqoUEeqEM7mFKilpXw" target="_8yCeeqoUEeqEM7mFKilpXw">      <name xml:lang="en"/>      <documentation/>    </relationship>    <relationship xsi:type="Realization" identifier="_8yDEV6oUEeqEM7mFKilpXw" source="_8yCd6KoUEeqEM7mFKilpXw" target="_8yCeeqoUEeqEM7mFKilpXw">      <name xml:lang="en"/>      <documentation/>    </relationship>    <relationship xsi:type="Realization" identifier="_8yDEWaoUEeqEM7mFKilpXw" source="_8yCdzqoUEeqEM7mFKilpXw" target="_8yCeeqoUEeqEM7mFKilpXw">      <name xml:lang="en"/>      <documentation/>    </relationship>    <relationship xsi:type="Realization" identifier="_8yDEW6oUEeqEM7mFKilpXw" source="_8yCd7KoUEeqEM7mFKilpXw" target="_8yCeeqoUEeqEM7mFKilpXw">      <name xml:lang="en"/>      <documentation/>    </relationship>    <relationship xsi:type="Realization" identifier="_8yDEXaoUEeqEM7mFKilpXw" source="_8yCd0KoUEeqEM7mFKilpXw" target="_8yCeeqoUEeqEM7mFKilpXw">      <name xml:lang="en"/>      <documentation/>    </relationship>    <relationship xsi:type="Realization" identifier="_8yDEX6oUEeqEM7mFKilpXw" source="_8yCd0qoUEeqEM7mFKilpXw" target="_8yCeeqoUEeqEM7mFKilpXw">      <name xml:lang="en"/>      <documentation/>    </relationship>    <relationship xsi:type="Realization" identifier="_8yDEYaoUEeqEM7mFKilpXw" source="_8yCeeqoUEeqEM7mFKilpXw" target="_8yCd6KoUEeqEM7mFKilpXw">      <name xml:lang="en"/>      <documentation/>    </relationship>    <relationship xsi:type="Realization" identifier="_8yDEY6oUEeqEM7mFKilpXw" source="_8yCeeqoUEeqEM7mFKilpXw" target="_8yCdzqoUEeqEM7mFKilpXw">      <name xml:lang="en"/>      <documentation/>    </relationship>    <relationship xsi:type="Realization" identifier="_8yDEZaoUEeqEM7mFKilpXw" source="_8yCeeqoUEeqEM7mFKilpXw" target="_8yCd0qoUEeqEM7mFKilpXw">      <name xml:lang="en"/>      <documentation/>    </relationship>    <relationship xsi:type="Realization" identifier="_8yDEZ6oUEeqEM7mFKilpXw" source="_8yCd1KoUEeqEM7mFKilpXw" target="_8yCeeqoUEeqEM7mFKilpXw">      <name xml:lang="en"/>      <documentation/>    </relationship>    <relationship xsi:type="Realization" identifier="_8yDEaaoUEeqEM7mFKilpXw" source="_8yCeeqoUEeqEM7mFKilpXw" target="_8yCd1KoUEeqEM7mFKilpXw">      <name xml:lang="en"/>      <documentation/>    </relationship>    <relationship xsi:type="Serving" identifier="_8yDEa6oUEeqEM7mFKilpXw" source="_8yCecqoUEeqEM7mFKilpXw" target="_8yCeYKoUEeqEM7mFKilpXw">      <name xml:lang="en"/>      <documentation/>    </relationship>    <relationship xsi:type="Serving" identifier="_8yDEbaoUEeqEM7mFKilpXw" source="_8yCdvqoUEeqEM7mFKilpXw" target="_8yCeZqoUEeqEM7mFKilpXw">      <name xml:lang="en"/>      <documentation/>    </relationship>    <relationship xsi:type="Triggering" identifier="_8yDEb6oUEeqEM7mFKilpXw" source="_8yCeZKoUEeqEM7mFKilpXw" target="_8yCeZqoUEeqEM7mFKilpXw">      <name xml:lang="en"/>      <documentation/>    </relationship>    <relationship xsi:type="Serving" identifier="_8yDEcaoUEeqEM7mFKilpXw" source="_8yCecKoUEeqEM7mFKilpXw" target="_8yCebKoUEeqEM7mFKilpXw">      <name xml:lang="en"/>      <documentation/>    </relationship>    <relationship xsi:type="Serving" identifier="_8yDEc6oUEeqEM7mFKilpXw" source="_8yCebKoUEeqEM7mFKilpXw" target="_8yCeYKoUEeqEM7mFKilpXw">      <name xml:lang="en"/>      <documentation/>    </relationship>    <relationship xsi:type="Serving" identifier="_8yDEdaoUEeqEM7mFKilpXw" source="_8yCebqoUEeqEM7mFKilpXw" target="_8yCeYqoUEeqEM7mFKilpXw">      <name xml:lang="en"/>      <documentation/>    </relationship>    <relationship xsi:type="Serving" identifier="_8yDEd6oUEeqEM7mFKilpXw" source="_8yCeaKoUEeqEM7mFKilpXw" target="_8yCedKoUEeqEM7mFKilpXw">      <name xml:lang="en"/>      <documentation/>    </relationship>    <relationship xsi:type="Serving" identifier="_8yDEeaoUEeqEM7mFKilpXw" source="_8yCdtqoUEeqEM7mFKilpXw" target="_8yCedKoUEeqEM7mFKilpXw">      <name xml:lang="en"/>      <documentation/>    </relationship>    <relationship xsi:type="Serving" identifier="_8yDEe6oUEeqEM7mFKilpXw" source="_8yCdwqoUEeqEM7mFKilpXw" target="_8yCedqoUEeqEM7mFKilpXw">      <name xml:lang="en"/>      <documentation/>    </relationship>    <relationship xsi:type="Serving" identifier="_8yDEfaoUEeqEM7mFKilpXw" source="_8yCdwKoUEeqEM7mFKilpXw" target="_8yCeYqoUEeqEM7mFKilpXw">      <name xml:lang="en"/>      <documentation/>    </relationship>    <relationship xsi:type="Serving" identifier="_8yDEf6oUEeqEM7mFKilpXw" source="_8yCeaqoUEeqEM7mFKilpXw" target="_8yCedqoUEeqEM7mFKilpXw">      <name xml:lang="en"/>      <documentation/>    </relationship>    <relationship xsi:type="Serving" identifier="_8yDEgaoUEeqEM7mFKilpXw" source="_8yCdsKoUEeqEM7mFKilpXw" target="_8yCebKoUEeqEM7mFKilpXw">      <name xml:lang="en"/>      <documentation/>    </relationship>    <relationship xsi:type="Serving" identifier="_8yDEg6oUEeqEM7mFKilpXw" source="_8yCdsqoUEeqEM7mFKilpXw" target="_8yCebKoUEeqEM7mFKilpXw">      <name xml:lang="en"/>      <documentation/>    </relationship>  </relationships>  <views>    <diagrams>      <view identifier="_8yBOcKoUEeqEM7mFKilpXw">        <name xml:lang="en">ApplicationComponents</name>        <node xsi:type="Element" identifier="_8yBOcqoUEeqEM7mFKilpXw" h="40" w="130" x="470" y="868" elementRef="_8yCdrqoUEeqEM7mFKilpXw"/>        <node xsi:type="Element" identifier="_8yBOc6oUEeqEM7mFKilpXw" h="40" w="144" x="456" y="769" elementRef="_8yCdsKoUEeqEM7mFKilpXw"/>        <node xsi:type="Element" identifier="_8yBOdKoUEeqEM7mFKilpXw" h="30" w="134" x="466" y="525" elementRef="_8yCdsqoUEeqEM7mFKilpXw"/>        <node xsi:type="Element" identifier="_8yBOdaoUEeqEM7mFKilpXw" h="30" w="144" x="456" y="688" elementRef="_8yCdtKoUEeqEM7mFKilpXw"/>        <node xsi:type="Element" identifier="_8yBOdqoUEeqEM7mFKilpXw" h="40" w="130" x="470" y="1091" elementRef="_8yCdtqoUEeqEM7mFKilpXw"/>        <node xsi:type="Element" identifier="_8yBOd6oUEeqEM7mFKilpXw" h="40" w="130" x="476" y="1377" elementRef="_8yCduKoUEeqEM7mFKilpXw"/>        <node xsi:type="Element" identifier="_8yBOeKoUEeqEM7mFKilpXw" h="40" w="130" x="470" y="993" elementRef="_8yCduqoUEeqEM7mFKilpXw"/>        <node xsi:type="Element" identifier="_8yBOeaoUEeqEM7mFKilpXw" h="40" w="130" x="489" y="1576" elementRef="_8yCdvKoUEeqEM7mFKilpXw"/>        <node xsi:type="Element" identifier="_8yBOeqoUEeqEM7mFKilpXw" h="40" w="130" x="489" y="1472" elementRef="_8yCdvqoUEeqEM7mFKilpXw"/>        <node xsi:type="Element" identifier="_8yBOe6oUEeqEM7mFKilpXw" h="40" w="130" x="493" y="1889" elementRef="_8yCdwKoUEeqEM7mFKilpXw"/>        <node xsi:type="Element" identifier="_8yBOfKoUEeqEM7mFKilpXw" h="40" w="130" x="493" y="1812" elementRef="_8yCdwqoUEeqEM7mFKilpXw"/>        <node xsi:type="Element" identifier="_8yBOfaoUEeqEM7mFKilpXw" h="40" w="130" x="493" y="1650" elementRef="_8yCdxKoUEeqEM7mFKilpXw"/>        <node xsi:type="Element" identifier="_8yBOfqoUEeqEM7mFKilpXw" h="40" w="130" x="493" y="1731" elementRef="_8yCdxqoUEeqEM7mFKilpXw"/>        <node xsi:type="Element" identifier="_8yBOf6oUEeqEM7mFKilpXw" h="40" w="130" x="470" y="214" elementRef="_8yCdyKoUEeqEM7mFKilpXw"/>        <node xsi:type="Element" identifier="_8yBOgKoUEeqEM7mFKilpXw" h="40" w="130" x="470" y="39" elementRef="_8yCdyqoUEeqEM7mFKilpXw"/>        <node xsi:type="Element" identifier="_8yBOgaoUEeqEM7mFKilpXw" h="40" w="130" x="721" y="29" elementRef="_8yCdzKoUEeqEM7mFKilpXw"/>        <node xsi:type="Element" identifier="_8yBOgqoUEeqEM7mFKilpXw" h="50" w="130" x="721" y="376" elementRef="_8yCdzqoUEeqEM7mFKilpXw"/>        <node xsi:type="Element" identifier="_8yBOg6oUEeqEM7mFKilpXw" h="50" w="130" x="721" y="554" elementRef="_8yCd0KoUEeqEM7mFKilpXw"/>        <node xsi:type="Element" identifier="_8yBOhKoUEeqEM7mFKilpXw" h="50" w="130" x="721" y="640" elementRef="_8yCd0qoUEeqEM7mFKilpXw"/>        <node xsi:type="Element" identifier="_8yBOhaoUEeqEM7mFKilpXw" h="50" w="130" x="721" y="741" elementRef="_8yCd1KoUEeqEM7mFKilpXw"/>        <node xsi:type="Element" identifier="_8yBOhqoUEeqEM7mFKilpXw" h="40" w="130" x="721" y="834" elementRef="_8yCd1qoUEeqEM7mFKilpXw"/>        <node xsi:type="Element" identifier="_8yBOh6oUEeqEM7mFKilpXw" h="40" w="130" x="721" y="993" elementRef="_8yCd2KoUEeqEM7mFKilpXw"/>        <node xsi:type="Element" identifier="_8yBOiKoUEeqEM7mFKilpXw" h="40" w="130" x="714" y="1377" elementRef="_8yCd2qoUEeqEM7mFKilpXw"/>        <node xsi:type="Element" identifier="_8yBOsaoUEeqEM7mFKilpXw" h="50" w="130" x="721" y="1068" elementRef="_8yCd3KoUEeqEM7mFKilpXw"/>        <node xsi:type="Element" identifier="_8yBOsqoUEeqEM7mFKilpXw" h="30" w="130" x="1136" y="30" elementRef="_8yCd3qoUEeqEM7mFKilpXw"/>        <node xsi:type="Element" identifier="_8yBOs6oUEeqEM7mFKilpXw" h="30" w="130" x="926" y="29" elementRef="_8yCd4KoUEeqEM7mFKilpXw"/>        <node xsi:type="Element" identifier="_8yBOvKoUEeqEM7mFKilpXw" h="30" w="130" x="721" y="142" elementRef="_8yCd4qoUEeqEM7mFKilpXw"/>        <node xsi:type="Element" identifier="_8yBO1aoUEeqEM7mFKilpXw" h="40" w="130" x="721" y="905" elementRef="_8yCd5KoUEeqEM7mFKilpXw"/>        <node xsi:type="Element" identifier="_8yBO1qoUEeqEM7mFKilpXw" h="30" w="130" x="926" y="376" elementRef="_8yCd5qoUEeqEM7mFKilpXw"/>        <node xsi:type="Element" identifier="_8yBO16oUEeqEM7mFKilpXw" h="50" w="130" x="721" y="293" elementRef="_8yCd6KoUEeqEM7mFKilpXw"/>        <node xsi:type="Element" identifier="_8yBO2KoUEeqEM7mFKilpXw" h="50" w="130" x="721" y="214" elementRef="_8yCd6qoUEeqEM7mFKilpXw"/>        <node xsi:type="Element" identifier="_8yBO4aoUEeqEM7mFKilpXw" h="50" w="130" x="721" y="466" elementRef="_8yCd7KoUEeqEM7mFKilpXw"/>        <node xsi:type="Element" identifier="_8yBO6qoUEeqEM7mFKilpXw" h="50" w="130" x="727" y="1472" elementRef="_8yCd7qoUEeqEM7mFKilpXw"/>        <node xsi:type="Element" identifier="_8yBO86oUEeqEM7mFKilpXw" h="40" w="130" x="714" y="1140" elementRef="_8yCd8KoUEeqEM7mFKilpXw"/>        <node xsi:type="Element" identifier="_8yBO9KoUEeqEM7mFKilpXw" h="40" w="130" x="716" y="1279" elementRef="_8yCd8qoUEeqEM7mFKilpXw"/>        <node xsi:type="Element" identifier="_8yBO9aoUEeqEM7mFKilpXw" h="40" w="130" x="716" y="1212" elementRef="_8yCd9KoUEeqEM7mFKilpXw"/>        <node xsi:type="Element" identifier="_8yBPBqoUEeqEM7mFKilpXw" h="40" w="130" x="926" y="255" elementRef="_8yCd9qoUEeqEM7mFKilpXw"/>        <node xsi:type="Element" identifier="_8yBPD6oUEeqEM7mFKilpXw" h="30" w="130" x="926" y="142" elementRef="_8yCd-KoUEeqEM7mFKilpXw"/>        <node xsi:type="Element" identifier="_8yBPIKoUEeqEM7mFKilpXw" h="40" w="130" x="926" y="466" elementRef="_8yCd-qoUEeqEM7mFKilpXw"/>        <node xsi:type="Element" identifier="_8yBPIaoUEeqEM7mFKilpXw" h="40" w="130" x="926" y="554" elementRef="_8yCd_KoUEeqEM7mFKilpXw"/>        <node xsi:type="Element" identifier="_8yBPIqoUEeqEM7mFKilpXw" h="40" w="130" x="926" y="640" elementRef="_8yCd_qoUEeqEM7mFKilpXw"/>        <node xsi:type="Element" identifier="_8yBPQ6oUEeqEM7mFKilpXw" h="40" w="130" x="926" y="751" elementRef="_8yCeAKoUEeqEM7mFKilpXw"/>        <node xsi:type="Element" identifier="_8yBPTKoUEeqEM7mFKilpXw" h="40" w="130" x="926" y="824" elementRef="_8yCeAqoUEeqEM7mFKilpXw"/>        <node xsi:type="Element" identifier="_8yBPTaoUEeqEM7mFKilpXw" h="40" w="130" x="926" y="905" elementRef="_8yCeBKoUEeqEM7mFKilpXw"/>        <node xsi:type="Element" identifier="_8yBPXqoUEeqEM7mFKilpXw" h="40" w="130" x="926" y="1019" elementRef="_8yCeBqoUEeqEM7mFKilpXw"/>        <node xsi:type="Element" identifier="_8yB1haoUEeqEM7mFKilpXw" h="40" w="130" x="926" y="1139" elementRef="_8yCeCKoUEeqEM7mFKilpXw"/>        <node xsi:type="Element" identifier="_8yB1hqoUEeqEM7mFKilpXw" h="40" w="130" x="926" y="1211" elementRef="_8yCeCqoUEeqEM7mFKilpXw"/>        <node xsi:type="Element" identifier="_8yB1h6oUEeqEM7mFKilpXw" h="40" w="130" x="926" y="1288" elementRef="_8yCeDKoUEeqEM7mFKilpXw"/>        <node xsi:type="Element" identifier="_8yB1iKoUEeqEM7mFKilpXw" h="30" w="130" x="926" y="1376" elementRef="_8yCeDqoUEeqEM7mFKilpXw"/>        <node xsi:type="Element" identifier="_8yB1qaoUEeqEM7mFKilpXw" h="40" w="130" x="926" y="1460" elementRef="_8yCeEKoUEeqEM7mFKilpXw"/>        <node xsi:type="Element" identifier="_8yB1sqoUEeqEM7mFKilpXw" h="30" w="130" x="1366" y="29" elementRef="_8yCeEqoUEeqEM7mFKilpXw"/>        <node xsi:type="Element" identifier="_8yB1s6oUEeqEM7mFKilpXw" h="30" w="130" x="1366" y="255" elementRef="_8yCeFKoUEeqEM7mFKilpXw"/>        <node xsi:type="Element" identifier="_8yB1tKoUEeqEM7mFKilpXw" h="30" w="130" x="1366" y="82" elementRef="_8yCeFqoUEeqEM7mFKilpXw"/>        <node xsi:type="Element" identifier="_8yB1taoUEeqEM7mFKilpXw" h="40" w="130" x="1366" y="335" elementRef="_8yCeGKoUEeqEM7mFKilpXw"/>        <node xsi:type="Element" identifier="_8yB1tqoUEeqEM7mFKilpXw" h="30" w="130" x="1136" y="362" elementRef="_8yCeGqoUEeqEM7mFKilpXw"/>        <node xsi:type="Element" identifier="_8yB116oUEeqEM7mFKilpXw" h="30" w="130" x="1136" y="477" elementRef="_8yCeHKoUEeqEM7mFKilpXw"/>        <node xsi:type="Element" identifier="_8yB12KoUEeqEM7mFKilpXw" h="30" w="130" x="1136" y="256" elementRef="_8yCeHqoUEeqEM7mFKilpXw"/>        <node xsi:type="Element" identifier="_8yB1-aoUEeqEM7mFKilpXw" h="30" w="130" x="1366" y="466" elementRef="_8yCeIKoUEeqEM7mFKilpXw"/>        <node xsi:type="Element" identifier="_8yB1-qoUEeqEM7mFKilpXw" h="30" w="130" x="1366" y="530" elementRef="_8yCeIqoUEeqEM7mFKilpXw"/>        <node xsi:type="Element" identifier="_8yB2C6oUEeqEM7mFKilpXw" h="30" w="130" x="1136" y="646" elementRef="_8yCeJKoUEeqEM7mFKilpXw"/>        <node xsi:type="Element" identifier="_8yB2FKoUEeqEM7mFKilpXw" h="30" w="130" x="1366" y="625" elementRef="_8yCeJqoUEeqEM7mFKilpXw"/>        <node xsi:type="Element" identifier="_8yB2FaoUEeqEM7mFKilpXw" h="30" w="130" x="1366" y="688" elementRef="_8yCeKKoUEeqEM7mFKilpXw"/>        <node xsi:type="Element" identifier="_8yB2JqoUEeqEM7mFKilpXw" h="30" w="130" x="1136" y="767" elementRef="_8yCeKqoUEeqEM7mFKilpXw"/>        <node xsi:type="Element" identifier="_8yB2J6oUEeqEM7mFKilpXw" h="30" w="130" x="1136" y="814" elementRef="_8yCeLKoUEeqEM7mFKilpXw"/>        <node xsi:type="Element" identifier="_8yB2KKoUEeqEM7mFKilpXw" h="30" w="130" x="1366" y="766" elementRef="_8yCeLqoUEeqEM7mFKilpXw"/>        <node xsi:type="Element" identifier="_8yB2KaoUEeqEM7mFKilpXw" h="30" w="130" x="1366" y="813" elementRef="_8yCeMKoUEeqEM7mFKilpXw"/>        <node xsi:type="Element" identifier="_8yB2aqoUEeqEM7mFKilpXw" h="30" w="130" x="1136" y="869" elementRef="_8yCeMqoUEeqEM7mFKilpXw"/>        <node xsi:type="Element" identifier="_8yB2c6oUEeqEM7mFKilpXw" h="30" w="130" x="1366" y="905" elementRef="_8yCeNKoUEeqEM7mFKilpXw"/>        <node xsi:type="Element" identifier="_8yB2dKoUEeqEM7mFKilpXw" h="30" w="130" x="1366" y="849" elementRef="_8yCeNqoUEeqEM7mFKilpXw"/>        <node xsi:type="Element" identifier="_8yB2haoUEeqEM7mFKilpXw" h="30" w="130" x="1136" y="953" elementRef="_8yCeOKoUEeqEM7mFKilpXw"/>        <node xsi:type="Element" identifier="_8yB2hqoUEeqEM7mFKilpXw" h="30" w="130" x="1366" y="953" elementRef="_8yCeOqoUEeqEM7mFKilpXw"/>        <node xsi:type="Element" identifier="_8yB2h6oUEeqEM7mFKilpXw" h="30" w="130" x="1366" y="998" elementRef="_8yCePKoUEeqEM7mFKilpXw"/>        <node xsi:type="Element" identifier="_8yB2oKoUEeqEM7mFKilpXw" h="30" w="130" x="1136" y="1052" elementRef="_8yCePqoUEeqEM7mFKilpXw"/>        <node xsi:type="Element" identifier="_8yB2oaoUEeqEM7mFKilpXw" h="30" w="130" x="1366" y="1052" elementRef="_8yCeQKoUEeqEM7mFKilpXw"/>        <node xsi:type="Element" identifier="_8yB2oqoUEeqEM7mFKilpXw" h="30" w="130" x="1366" y="1096" elementRef="_8yCeQqoUEeqEM7mFKilpXw"/>        <node xsi:type="Element" identifier="_8yB2u6oUEeqEM7mFKilpXw" h="30" w="130" x="1136" y="1146" elementRef="_8yCeRKoUEeqEM7mFKilpXw"/>        <node xsi:type="Element" identifier="_8yB2vKoUEeqEM7mFKilpXw" h="30" w="130" x="1366" y="1145" elementRef="_8yCeRqoUEeqEM7mFKilpXw"/>        <node xsi:type="Element" identifier="_8yB2vaoUEeqEM7mFKilpXw" h="30" w="130" x="1366" y="1185" elementRef="_8yCeSKoUEeqEM7mFKilpXw"/>        <node xsi:type="Element" identifier="_8yB2zqoUEeqEM7mFKilpXw" h="30" w="130" x="1136" y="1228" elementRef="_8yCeSqoUEeqEM7mFKilpXw"/>        <node xsi:type="Element" identifier="_8yB2z6oUEeqEM7mFKilpXw" h="30" w="130" x="1366" y="1266" elementRef="_8yCeTKoUEeqEM7mFKilpXw"/>        <node xsi:type="Element" identifier="_8yB20KoUEeqEM7mFKilpXw" h="30" w="130" x="1366" y="1227" elementRef="_8yCeTqoUEeqEM7mFKilpXw"/>        <node xsi:type="Element" identifier="_8yB24aoUEeqEM7mFKilpXw" h="30" w="130" x="1136" y="1290" elementRef="_8yCeUKoUEeqEM7mFKilpXw"/>        <node xsi:type="Element" identifier="_8yB24qoUEeqEM7mFKilpXw" h="30" w="130" x="1371" y="1358" elementRef="_8yCeUqoUEeqEM7mFKilpXw"/>        <node xsi:type="Element" identifier="_8yB246oUEeqEM7mFKilpXw" h="30" w="130" x="1371" y="1316" elementRef="_8yCeVKoUEeqEM7mFKilpXw"/>        <node xsi:type="Element" identifier="_8yB3DKoUEeqEM7mFKilpXw" h="30" w="130" x="1136" y="1383" elementRef="_8yCeVqoUEeqEM7mFKilpXw"/>        <node xsi:type="Element" identifier="_8yB3DaoUEeqEM7mFKilpXw" h="30" w="130" x="1371" y="1418" elementRef="_8yCeWKoUEeqEM7mFKilpXw"/>        <node xsi:type="Element" identifier="_8yB3JqoUEeqEM7mFKilpXw" h="30" w="130" x="1136" y="1483" elementRef="_8yCeWqoUEeqEM7mFKilpXw"/>        <node xsi:type="Element" identifier="_8yB3J6oUEeqEM7mFKilpXw" h="30" w="130" x="1371" y="1541" elementRef="_8yCeXKoUEeqEM7mFKilpXw"/>        <node xsi:type="Element" identifier="_8yB3KKoUEeqEM7mFKilpXw" h="30" w="130" x="1371" y="1489" elementRef="_8yCeXqoUEeqEM7mFKilpXw"/>        <node xsi:type="Element" identifier="_8yB3QaoUEeqEM7mFKilpXw" h="60" w="130" x="145" y="890" elementRef="_8yCeYKoUEeqEM7mFKilpXw"/>        <node xsi:type="Element" identifier="_8yCc0KoUEeqEM7mFKilpXw" h="50" w="130" x="145" y="640" elementRef="_8yCeYqoUEeqEM7mFKilpXw"/>        <node xsi:type="Element" identifier="_8yCc0aoUEeqEM7mFKilpXw" h="50" w="130" x="145" y="496" elementRef="_8yCeZKoUEeqEM7mFKilpXw"/>        <node xsi:type="Element" identifier="_8yCc0qoUEeqEM7mFKilpXw" h="50" w="130" x="145" y="433" elementRef="_8yCeZqoUEeqEM7mFKilpXw"/>        <node xsi:type="Element" identifier="_8yCc06oUEeqEM7mFKilpXw" h="50" w="130" x="145" y="293" elementRef="_8yCeaKoUEeqEM7mFKilpXw"/>        <node xsi:type="Element" identifier="_8yCc1KoUEeqEM7mFKilpXw" h="40" w="130" x="145" y="152" elementRef="_8yCeaqoUEeqEM7mFKilpXw"/>        <node xsi:type="Element" identifier="_8yCc1aoUEeqEM7mFKilpXw" h="40" w="130" x="145" y="746" elementRef="_8yCebKoUEeqEM7mFKilpXw"/>        <node xsi:type="Element" identifier="_8yCc1qoUEeqEM7mFKilpXw" h="50" w="130" x="145" y="580" elementRef="_8yCebqoUEeqEM7mFKilpXw"/>        <node xsi:type="Element" identifier="_8yCc16oUEeqEM7mFKilpXw" h="40" w="130" x="145" y="809" elementRef="_8yCecKoUEeqEM7mFKilpXw"/>        <node xsi:type="Element" identifier="_8yCc2KoUEeqEM7mFKilpXw" h="60" w="130" x="145" y="965" elementRef="_8yCecqoUEeqEM7mFKilpXw"/>        <node xsi:type="Element" identifier="_8yCc2aoUEeqEM7mFKilpXw" h="50" w="130" x="145" y="352" elementRef="_8yCedKoUEeqEM7mFKilpXw"/>        <node xsi:type="Element" identifier="_8yCc2qoUEeqEM7mFKilpXw" h="40" w="130" x="145" y="204" elementRef="_8yCedqoUEeqEM7mFKilpXw"/>        <node xsi:type="Element" identifier="_8yCc26oUEeqEM7mFKilpXw" h="60" w="130" x="444" y="325" elementRef="_8yCeeKoUEeqEM7mFKilpXw"/>        <node xsi:type="Element" identifier="_8yCc3KoUEeqEM7mFKilpXw" h="60" w="130" x="578" y="413" elementRef="_8yCeeqoUEeqEM7mFKilpXw"/>        <node xsi:type="Element" identifier="_8yCdj6oUEeqEM7mFKilpXw" h="60" w="130" x="870" y="1920" elementRef="_8yCefKoUEeqEM7mFKilpXw"/>        <connection xsi:type="Relationship" identifier="_8yBOiqoUEeqEM7mFKilpXw" source="_8yBOiKoUEeqEM7mFKilpXw" target="_8yBOd6oUEeqEM7mFKilpXw" relationshipRef="_8yCefqoUEeqEM7mFKilpXw">          <bendpoint x="660" y="1399"/>          <bendpoint x="660" y="1399"/>        </connection>        <connection xsi:type="Relationship" identifier="_8yBOkqoUEeqEM7mFKilpXw" source="_8yBOhqoUEeqEM7mFKilpXw" target="_8yBOcqoUEeqEM7mFKilpXw" relationshipRef="_8yCegKoUEeqEM7mFKilpXw">          <bendpoint x="661" y="871"/>          <bendpoint x="660" y="871"/>        </connection>        <connection xsi:type="Relationship" identifier="_8yBOmqoUEeqEM7mFKilpXw" source="_8yBOhaoUEeqEM7mFKilpXw" target="_8yBOc6oUEeqEM7mFKilpXw" relationshipRef="_8yCegqoUEeqEM7mFKilpXw">          <bendpoint x="661" y="780"/>          <bendpoint x="660" y="780"/>        </connection>        <connection xsi:type="Relationship" identifier="_8yBOoqoUEeqEM7mFKilpXw" source="_8yBOhKoUEeqEM7mFKilpXw" target="_8yBOdaoUEeqEM7mFKilpXw" relationshipRef="_8yCehKoUEeqEM7mFKilpXw">          <bendpoint x="661" y="689"/>          <bendpoint x="660" y="689"/>        </connection>        <connection xsi:type="Relationship" identifier="_8yBOqqoUEeqEM7mFKilpXw" source="_8yBOg6oUEeqEM7mFKilpXw" target="_8yBOdKoUEeqEM7mFKilpXw" relationshipRef="_8yDDoaoUEeqEM7mFKilpXw">          <bendpoint x="701" y="555"/>          <bendpoint x="660" y="554"/>        </connection>        <connection xsi:type="Relationship" identifier="_8yBOtaoUEeqEM7mFKilpXw" source="_8yBOgaoUEeqEM7mFKilpXw" target="_8yBOgKoUEeqEM7mFKilpXw" relationshipRef="_8yDDo6oUEeqEM7mFKilpXw">          <bendpoint x="661" y="54"/>          <bendpoint x="660" y="54"/>        </connection>        <connection xsi:type="Relationship" identifier="_8yBOvqoUEeqEM7mFKilpXw" source="_8yBOvKoUEeqEM7mFKilpXw" target="_8yBOgKoUEeqEM7mFKilpXw" relationshipRef="_8yDDpaoUEeqEM7mFKilpXw">          <bendpoint x="786" y="110"/>          <bendpoint x="535" y="111"/>        </connection>        <connection xsi:type="Relationship" identifier="_8yBOxqoUEeqEM7mFKilpXw" source="_8yBOsaoUEeqEM7mFKilpXw" target="_8yBOdqoUEeqEM7mFKilpXw" relationshipRef="_8yDDp6oUEeqEM7mFKilpXw">          <bendpoint x="661" y="1104"/>          <bendpoint x="660" y="1104"/>        </connection>        <connection xsi:type="Relationship" identifier="_8yBOzqoUEeqEM7mFKilpXw" source="_8yBOh6oUEeqEM7mFKilpXw" target="_8yBOeKoUEeqEM7mFKilpXw" relationshipRef="_8yDDqaoUEeqEM7mFKilpXw">          <bendpoint x="661" y="1013"/>          <bendpoint x="660" y="1013"/>        </connection>        <connection xsi:type="Relationship" identifier="_8yBO2qoUEeqEM7mFKilpXw" source="_8yBO1aoUEeqEM7mFKilpXw" target="_8yBOcqoUEeqEM7mFKilpXw" relationshipRef="_8yDDq6oUEeqEM7mFKilpXw">          <bendpoint x="661" y="906"/>          <bendpoint x="660" y="906"/>        </connection>        <connection xsi:type="Relationship" identifier="_8yBO46oUEeqEM7mFKilpXw" source="_8yBO4aoUEeqEM7mFKilpXw" target="_8yBOdKoUEeqEM7mFKilpXw" relationshipRef="_8yDDraoUEeqEM7mFKilpXw">          <bendpoint x="786" y="521"/>          <bendpoint x="533" y="520"/>        </connection>        <connection xsi:type="Relationship" identifier="_8yBO7KoUEeqEM7mFKilpXw" source="_8yBO6qoUEeqEM7mFKilpXw" target="_8yBOeqoUEeqEM7mFKilpXw" relationshipRef="_8yDDr6oUEeqEM7mFKilpXw">          <bendpoint x="673" y="1492"/>          <bendpoint x="673" y="1492"/>        </connection>        <connection xsi:type="Relationship" identifier="_8yBO96oUEeqEM7mFKilpXw" source="_8yBO2KoUEeqEM7mFKilpXw" target="_8yBOf6oUEeqEM7mFKilpXw" relationshipRef="_8yDDsaoUEeqEM7mFKilpXw">          <bendpoint x="661" y="234"/>          <bendpoint x="660" y="234"/>        </connection>        <connection xsi:type="Relationship" identifier="_8yBO_6oUEeqEM7mFKilpXw" source="_8yBO16oUEeqEM7mFKilpXw" target="_8yBOf6oUEeqEM7mFKilpXw" relationshipRef="_8yDDs6oUEeqEM7mFKilpXw">          <bendpoint x="786" y="273"/>          <bendpoint x="535" y="274"/>        </connection>        <connection xsi:type="Relationship" identifier="_8yBPCKoUEeqEM7mFKilpXw" source="_8yBOs6oUEeqEM7mFKilpXw" target="_8yBOgaoUEeqEM7mFKilpXw" relationshipRef="_8yDDtaoUEeqEM7mFKilpXw">          <bendpoint x="889" y="44"/>          <bendpoint x="888" y="44"/>        </connection>        <connection xsi:type="Relationship" identifier="_8yBPEaoUEeqEM7mFKilpXw" source="_8yBPBqoUEeqEM7mFKilpXw" target="_8yBO2KoUEeqEM7mFKilpXw" relationshipRef="_8yDDt6oUEeqEM7mFKilpXw">          <bendpoint x="889" y="259"/>          <bendpoint x="888" y="259"/>        </connection>        <connection xsi:type="Relationship" identifier="_8yBPGaoUEeqEM7mFKilpXw" source="_8yBPBqoUEeqEM7mFKilpXw" target="_8yBO16oUEeqEM7mFKilpXw" relationshipRef="_8yDDuaoUEeqEM7mFKilpXw">          <bendpoint x="889" y="294"/>          <bendpoint x="888" y="294"/>        </connection>        <connection xsi:type="Relationship" identifier="_8yBPJKoUEeqEM7mFKilpXw" source="_8yBPIaoUEeqEM7mFKilpXw" target="_8yBOg6oUEeqEM7mFKilpXw" relationshipRef="_8yDDu6oUEeqEM7mFKilpXw">          <bendpoint x="889" y="574"/>          <bendpoint x="888" y="574"/>        </connection>        <connection xsi:type="Relationship" identifier="_8yBPLKoUEeqEM7mFKilpXw" source="_8yBPIKoUEeqEM7mFKilpXw" target="_8yBO4aoUEeqEM7mFKilpXw" relationshipRef="_8yDDvaoUEeqEM7mFKilpXw">          <bendpoint x="889" y="486"/>          <bendpoint x="888" y="486"/>        </connection>        <connection xsi:type="Relationship" identifier="_8yBPNKoUEeqEM7mFKilpXw" source="_8yBO1qoUEeqEM7mFKilpXw" target="_8yBOgqoUEeqEM7mFKilpXw" relationshipRef="_8yDDv6oUEeqEM7mFKilpXw">          <bendpoint x="889" y="391"/>          <bendpoint x="888" y="391"/>        </connection>        <connection xsi:type="Relationship" identifier="_8yBPPKoUEeqEM7mFKilpXw" source="_8yBPD6oUEeqEM7mFKilpXw" target="_8yBOvKoUEeqEM7mFKilpXw" relationshipRef="_8yDDwaoUEeqEM7mFKilpXw">          <bendpoint x="889" y="157"/>          <bendpoint x="888" y="157"/>        </connection>        <connection xsi:type="Relationship" identifier="_8yBPRaoUEeqEM7mFKilpXw" source="_8yBPQ6oUEeqEM7mFKilpXw" target="_8yBOhaoUEeqEM7mFKilpXw" relationshipRef="_8yDDw6oUEeqEM7mFKilpXw">          <bendpoint x="889" y="771"/>          <bendpoint x="888" y="771"/>        </connection>        <connection xsi:type="Relationship" identifier="_8yBPT6oUEeqEM7mFKilpXw" source="_8yBPTKoUEeqEM7mFKilpXw" target="_8yBOhqoUEeqEM7mFKilpXw" relationshipRef="_8yDDxaoUEeqEM7mFKilpXw">          <bendpoint x="889" y="849"/>          <bendpoint x="888" y="849"/>        </connection>        <connection xsi:type="Relationship" identifier="_8yBPV6oUEeqEM7mFKilpXw" source="_8yBPTaoUEeqEM7mFKilpXw" target="_8yBO1aoUEeqEM7mFKilpXw" relationshipRef="_8yDDx6oUEeqEM7mFKilpXw">          <bendpoint x="889" y="925"/>          <bendpoint x="888" y="925"/>        </connection>        <connection xsi:type="Relationship" identifier="_8yBPYKoUEeqEM7mFKilpXw" source="_8yBPXqoUEeqEM7mFKilpXw" target="_8yBOh6oUEeqEM7mFKilpXw" relationshipRef="_8yDDyaoUEeqEM7mFKilpXw">          <bendpoint x="889" y="1026"/>          <bendpoint x="888" y="1026"/>        </connection>        <connection xsi:type="Relationship" identifier="_8yBPaKoUEeqEM7mFKilpXw" source="_8yBPXqoUEeqEM7mFKilpXw" target="_8yBOsaoUEeqEM7mFKilpXw" relationshipRef="_8yDDy6oUEeqEM7mFKilpXw">          <bendpoint x="889" y="1045"/>          <bendpoint x="888" y="1093"/>        </connection>        <connection xsi:type="Relationship" identifier="_8yB1iqoUEeqEM7mFKilpXw" source="_8yB1iKoUEeqEM7mFKilpXw" target="_8yBOiKoUEeqEM7mFKilpXw" relationshipRef="_8yDDzaoUEeqEM7mFKilpXw">          <bendpoint x="885" y="1391"/>          <bendpoint x="885" y="1391"/>        </connection>        <connection xsi:type="Relationship" identifier="_8yB1kqoUEeqEM7mFKilpXw" source="_8yB1h6oUEeqEM7mFKilpXw" target="_8yBO9KoUEeqEM7mFKilpXw" relationshipRef="_8yDDz6oUEeqEM7mFKilpXw">          <bendpoint x="886" y="1303"/>          <bendpoint x="886" y="1303"/>        </connection>        <connection xsi:type="Relationship" identifier="_8yB1mqoUEeqEM7mFKilpXw" source="_8yB1hqoUEeqEM7mFKilpXw" target="_8yBO9aoUEeqEM7mFKilpXw" relationshipRef="_8yDD0aoUEeqEM7mFKilpXw">          <bendpoint x="886" y="1231"/>          <bendpoint x="886" y="1231"/>        </connection>        <connection xsi:type="Relationship" identifier="_8yB1oqoUEeqEM7mFKilpXw" source="_8yB1haoUEeqEM7mFKilpXw" target="_8yBO86oUEeqEM7mFKilpXw" relationshipRef="_8yDD06oUEeqEM7mFKilpXw">          <bendpoint x="885" y="1159"/>          <bendpoint x="885" y="1159"/>        </connection>        <connection xsi:type="Relationship" identifier="_8yB1q6oUEeqEM7mFKilpXw" source="_8yB1qaoUEeqEM7mFKilpXw" target="_8yBO6qoUEeqEM7mFKilpXw" relationshipRef="_8yDD1aoUEeqEM7mFKilpXw">          <bendpoint x="892" y="1486"/>          <bendpoint x="891" y="1486"/>        </connection>        <connection xsi:type="Relationship" identifier="_8yB1uKoUEeqEM7mFKilpXw" source="_8yBOsqoUEeqEM7mFKilpXw" target="_8yB1sqoUEeqEM7mFKilpXw" relationshipRef="_8yDD16oUEeqEM7mFKilpXw">          <bendpoint x="1316" y="44"/>          <bendpoint x="1316" y="44"/>        </connection>        <connection xsi:type="Relationship" identifier="_8yB1wKoUEeqEM7mFKilpXw" source="_8yBOsqoUEeqEM7mFKilpXw" target="_8yBOs6oUEeqEM7mFKilpXw" relationshipRef="_8yDD2aoUEeqEM7mFKilpXw">          <bendpoint x="1096" y="44"/>          <bendpoint x="1096" y="44"/>        </connection>        <connection xsi:type="Relationship" identifier="_8yB1yKoUEeqEM7mFKilpXw" source="_8yB1tqoUEeqEM7mFKilpXw" target="_8yB1taoUEeqEM7mFKilpXw" relationshipRef="_8yDD26oUEeqEM7mFKilpXw">          <bendpoint x="1316" y="368"/>          <bendpoint x="1316" y="368"/>        </connection>        <connection xsi:type="Relationship" identifier="_8yB10KoUEeqEM7mFKilpXw" source="_8yB1tqoUEeqEM7mFKilpXw" target="_8yBO1qoUEeqEM7mFKilpXw" relationshipRef="_8yDD3aoUEeqEM7mFKilpXw">          <bendpoint x="1096" y="384"/>          <bendpoint x="1096" y="384"/>        </connection>        <connection xsi:type="Relationship" identifier="_8yB12qoUEeqEM7mFKilpXw" source="_8yB12KoUEeqEM7mFKilpXw" target="_8yBPBqoUEeqEM7mFKilpXw" relationshipRef="_8yDD36oUEeqEM7mFKilpXw">          <bendpoint x="1096" y="271"/>          <bendpoint x="1096" y="271"/>        </connection>        <connection xsi:type="Relationship" identifier="_8yB14qoUEeqEM7mFKilpXw" source="_8yB1tqoUEeqEM7mFKilpXw" target="_8yB12KoUEeqEM7mFKilpXw" relationshipRef="_8yDD4aoUEeqEM7mFKilpXw">          <bendpoint x="1201" y="324"/>          <bendpoint x="1201" y="324"/>        </connection>        <connection xsi:type="Relationship" identifier="_8yB16qoUEeqEM7mFKilpXw" source="_8yB12KoUEeqEM7mFKilpXw" target="_8yB1s6oUEeqEM7mFKilpXw" relationshipRef="_8yDD46oUEeqEM7mFKilpXw">          <bendpoint x="1316" y="270"/>          <bendpoint x="1316" y="270"/>        </connection>        <connection xsi:type="Relationship" identifier="_8yB18qoUEeqEM7mFKilpXw" source="_8yB116oUEeqEM7mFKilpXw" target="_8yBPIKoUEeqEM7mFKilpXw" relationshipRef="_8yDD5aoUEeqEM7mFKilpXw">          <bendpoint x="1096" y="491"/>          <bendpoint x="1096" y="491"/>        </connection>        <connection xsi:type="Relationship" identifier="_8yB1_KoUEeqEM7mFKilpXw" source="_8yB116oUEeqEM7mFKilpXw" target="_8yB1-aoUEeqEM7mFKilpXw" relationshipRef="_8yDD56oUEeqEM7mFKilpXw">          <bendpoint x="1316" y="486"/>          <bendpoint x="1316" y="486"/>        </connection>        <connection xsi:type="Relationship" identifier="_8yB2BKoUEeqEM7mFKilpXw" source="_8yBPIqoUEeqEM7mFKilpXw" target="_8yBOhKoUEeqEM7mFKilpXw" relationshipRef="_8yDD6aoUEeqEM7mFKilpXw">          <bendpoint x="889" y="660"/>          <bendpoint x="888" y="660"/>        </connection>        <connection xsi:type="Relationship" identifier="_8yB2DaoUEeqEM7mFKilpXw" source="_8yB2C6oUEeqEM7mFKilpXw" target="_8yBPIqoUEeqEM7mFKilpXw" relationshipRef="_8yDD66oUEeqEM7mFKilpXw">          <bendpoint x="1096" y="661"/>          <bendpoint x="1096" y="661"/>        </connection>        <connection xsi:type="Relationship" identifier="_8yB2F6oUEeqEM7mFKilpXw" source="_8yB2C6oUEeqEM7mFKilpXw" target="_8yB2FKoUEeqEM7mFKilpXw" relationshipRef="_8yDD7aoUEeqEM7mFKilpXw">          <bendpoint x="1316" y="650"/>          <bendpoint x="1316" y="650"/>        </connection>        <connection xsi:type="Relationship" identifier="_8yB2H6oUEeqEM7mFKilpXw" source="_8yB116oUEeqEM7mFKilpXw" target="_8yBPIaoUEeqEM7mFKilpXw" relationshipRef="_8yDD76oUEeqEM7mFKilpXw">          <bendpoint x="1201" y="531"/>          <bendpoint x="991" y="530"/>        </connection>        <connection xsi:type="Relationship" identifier="_8yB2L6oUEeqEM7mFKilpXw" source="_8yB2J6oUEeqEM7mFKilpXw" target="_8yB2JqoUEeqEM7mFKilpXw" relationshipRef="_8yDD8aoUEeqEM7mFKilpXw">          <bendpoint x="1201" y="805"/>          <bendpoint x="1201" y="806"/>        </connection>        <connection xsi:type="Relationship" identifier="_8yB2MqoUEeqEM7mFKilpXw" source="_8yB2JqoUEeqEM7mFKilpXw" target="_8yB2KKoUEeqEM7mFKilpXw" relationshipRef="_8yDD86oUEeqEM7mFKilpXw">          <bendpoint x="1316" y="781"/>          <bendpoint x="1316" y="781"/>        </connection>        <connection xsi:type="Relationship" identifier="_8yB2OqoUEeqEM7mFKilpXw" source="_8yB2J6oUEeqEM7mFKilpXw" target="_8yB2KaoUEeqEM7mFKilpXw" relationshipRef="_8yDD9aoUEeqEM7mFKilpXw">          <bendpoint x="1316" y="828"/>          <bendpoint x="1316" y="828"/>        </connection>        <connection xsi:type="Relationship" identifier="_8yB2Q6oUEeqEM7mFKilpXw" source="_8yB2JqoUEeqEM7mFKilpXw" target="_8yBPQ6oUEeqEM7mFKilpXw" relationshipRef="_8yDD96oUEeqEM7mFKilpXw">          <bendpoint x="1096" y="779"/>          <bendpoint x="1096" y="779"/>        </connection>        <connection xsi:type="Relationship" identifier="_8yB2S6oUEeqEM7mFKilpXw" source="_8yBOsqoUEeqEM7mFKilpXw" target="_8yBPD6oUEeqEM7mFKilpXw" relationshipRef="_8yDD-aoUEeqEM7mFKilpXw">          <bendpoint x="1101" y="50"/>          <bendpoint x="1101" y="146"/>        </connection>        <connection xsi:type="Relationship" identifier="_8yB2U6oUEeqEM7mFKilpXw" source="_8yBOsqoUEeqEM7mFKilpXw" target="_8yB1tKoUEeqEM7mFKilpXw" relationshipRef="_8yDD-6oUEeqEM7mFKilpXw">          <bendpoint x="1316" y="50"/>          <bendpoint x="1316" y="97"/>        </connection>        <connection xsi:type="Relationship" identifier="_8yB2W6oUEeqEM7mFKilpXw" source="_8yB116oUEeqEM7mFKilpXw" target="_8yB1-qoUEeqEM7mFKilpXw" relationshipRef="_8yDD_aoUEeqEM7mFKilpXw">          <bendpoint x="1316" y="497"/>          <bendpoint x="1316" y="545"/>        </connection>        <connection xsi:type="Relationship" identifier="_8yB2Y6oUEeqEM7mFKilpXw" source="_8yB2C6oUEeqEM7mFKilpXw" target="_8yB2FaoUEeqEM7mFKilpXw" relationshipRef="_8yDD_6oUEeqEM7mFKilpXw">          <bendpoint x="1316" y="666"/>          <bendpoint x="1316" y="703"/>        </connection>        <connection xsi:type="Relationship" identifier="_8yB2bKoUEeqEM7mFKilpXw" source="_8yB2aqoUEeqEM7mFKilpXw" target="_8yBPTKoUEeqEM7mFKilpXw" relationshipRef="_8yDEAaoUEeqEM7mFKilpXw">          <bendpoint x="1201" y="866"/>          <bendpoint x="991" y="867"/>        </connection>        <connection xsi:type="Relationship" identifier="_8yB2dqoUEeqEM7mFKilpXw" source="_8yB2aqoUEeqEM7mFKilpXw" target="_8yB2dKoUEeqEM7mFKilpXw" relationshipRef="_8yDEA6oUEeqEM7mFKilpXw">          <bendpoint x="1316" y="874"/>          <bendpoint x="1316" y="874"/>        </connection>        <connection xsi:type="Relationship" identifier="_8yB2fqoUEeqEM7mFKilpXw" source="_8yB2aqoUEeqEM7mFKilpXw" target="_8yB2c6oUEeqEM7mFKilpXw" relationshipRef="_8yDEBaoUEeqEM7mFKilpXw">          <bendpoint x="1316" y="889"/>          <bendpoint x="1316" y="920"/>        </connection>        <connection xsi:type="Relationship" identifier="_8yB2iKoUEeqEM7mFKilpXw" source="_8yB2haoUEeqEM7mFKilpXw" target="_8yB2hqoUEeqEM7mFKilpXw" relationshipRef="_8yDEB6oUEeqEM7mFKilpXw">          <bendpoint x="1316" y="968"/>          <bendpoint x="1316" y="968"/>        </connection>        <connection xsi:type="Relationship" identifier="_8yB2kKoUEeqEM7mFKilpXw" source="_8yB2haoUEeqEM7mFKilpXw" target="_8yB2h6oUEeqEM7mFKilpXw" relationshipRef="_8yDECaoUEeqEM7mFKilpXw">          <bendpoint x="1316" y="973"/>          <bendpoint x="1316" y="1013"/>        </connection>        <connection xsi:type="Relationship" identifier="_8yB2maoUEeqEM7mFKilpXw" source="_8yB2haoUEeqEM7mFKilpXw" target="_8yBPTaoUEeqEM7mFKilpXw" relationshipRef="_8yDEC6oUEeqEM7mFKilpXw">          <bendpoint x="1201" y="949"/>          <bendpoint x="991" y="949"/>        </connection>        <connection xsi:type="Relationship" identifier="_8yB2o6oUEeqEM7mFKilpXw" source="_8yB2oKoUEeqEM7mFKilpXw" target="_8yB2oaoUEeqEM7mFKilpXw" relationshipRef="_8yDEDaoUEeqEM7mFKilpXw">          <bendpoint x="1316" y="1067"/>          <bendpoint x="1316" y="1067"/>        </connection>        <connection xsi:type="Relationship" identifier="_8yB2q6oUEeqEM7mFKilpXw" source="_8yB2oKoUEeqEM7mFKilpXw" target="_8yB2oqoUEeqEM7mFKilpXw" relationshipRef="_8yDED6oUEeqEM7mFKilpXw">          <bendpoint x="1316" y="1072"/>          <bendpoint x="1316" y="1111"/>        </connection>        <connection xsi:type="Relationship" identifier="_8yB2tKoUEeqEM7mFKilpXw" source="_8yB2oKoUEeqEM7mFKilpXw" target="_8yBPXqoUEeqEM7mFKilpXw" relationshipRef="_8yDEEaoUEeqEM7mFKilpXw">          <bendpoint x="1096" y="1055"/>          <bendpoint x="1096" y="1055"/>        </connection>        <connection xsi:type="Relationship" identifier="_8yB2vqoUEeqEM7mFKilpXw" source="_8yB2u6oUEeqEM7mFKilpXw" target="_8yB2vKoUEeqEM7mFKilpXw" relationshipRef="_8yDEE6oUEeqEM7mFKilpXw">          <bendpoint x="1316" y="1160"/>          <bendpoint x="1316" y="1160"/>        </connection>        <connection xsi:type="Relationship" identifier="_8yB2xqoUEeqEM7mFKilpXw" source="_8yB2u6oUEeqEM7mFKilpXw" target="_8yB2vaoUEeqEM7mFKilpXw" relationshipRef="_8yDEFaoUEeqEM7mFKilpXw">          <bendpoint x="1286" y="1166"/>          <bendpoint x="1286" y="1196"/>        </connection>        <connection xsi:type="Relationship" identifier="_8yB20aoUEeqEM7mFKilpXw" source="_8yB2zqoUEeqEM7mFKilpXw" target="_8yB2z6oUEeqEM7mFKilpXw" relationshipRef="_8yDEF6oUEeqEM7mFKilpXw">          <bendpoint x="1316" y="1248"/>          <bendpoint x="1316" y="1281"/>        </connection>        <connection xsi:type="Relationship" identifier="_8yB22aoUEeqEM7mFKilpXw" source="_8yB2zqoUEeqEM7mFKilpXw" target="_8yB20KoUEeqEM7mFKilpXw" relationshipRef="_8yDEGaoUEeqEM7mFKilpXw">          <bendpoint x="1316" y="1242"/>          <bendpoint x="1316" y="1242"/>        </connection>        <connection xsi:type="Relationship" identifier="_8yB25KoUEeqEM7mFKilpXw" source="_8yB24aoUEeqEM7mFKilpXw" target="_8yB246oUEeqEM7mFKilpXw" relationshipRef="_8yDEG6oUEeqEM7mFKilpXw">          <bendpoint x="1318" y="1318"/>          <bendpoint x="1319" y="1318"/>        </connection>        <connection xsi:type="Relationship" identifier="_8yB27KoUEeqEM7mFKilpXw" source="_8yB24aoUEeqEM7mFKilpXw" target="_8yB24qoUEeqEM7mFKilpXw" relationshipRef="_8yDEHaoUEeqEM7mFKilpXw">          <bendpoint x="1275" y="1310"/>          <bendpoint x="1276" y="1370"/>        </connection>        <connection xsi:type="Relationship" identifier="_8yB29aoUEeqEM7mFKilpXw" source="_8yB24aoUEeqEM7mFKilpXw" target="_8yB1h6oUEeqEM7mFKilpXw" relationshipRef="_8yDEH6oUEeqEM7mFKilpXw">          <bendpoint x="1096" y="1305"/>          <bendpoint x="1096" y="1305"/>        </connection>        <connection xsi:type="Relationship" identifier="_8yB2_aoUEeqEM7mFKilpXw" source="_8yB2zqoUEeqEM7mFKilpXw" target="_8yB1hqoUEeqEM7mFKilpXw" relationshipRef="_8yDEIaoUEeqEM7mFKilpXw">          <bendpoint x="1096" y="1239"/>          <bendpoint x="1096" y="1239"/>        </connection>        <connection xsi:type="Relationship" identifier="_8yB3BaoUEeqEM7mFKilpXw" source="_8yB2u6oUEeqEM7mFKilpXw" target="_8yB1haoUEeqEM7mFKilpXw" relationshipRef="_8yDEI6oUEeqEM7mFKilpXw">          <bendpoint x="1096" y="1161"/>          <bendpoint x="1096" y="1161"/>        </connection>        <connection xsi:type="Relationship" identifier="_8yB3DqoUEeqEM7mFKilpXw" source="_8yB3DKoUEeqEM7mFKilpXw" target="_8yB3DaoUEeqEM7mFKilpXw" relationshipRef="_8yDEJaoUEeqEM7mFKilpXw">          <bendpoint x="1318" y="1398"/>          <bendpoint x="1319" y="1433"/>        </connection>        <connection xsi:type="Relationship" identifier="_8yB3F6oUEeqEM7mFKilpXw" source="_8yB3DKoUEeqEM7mFKilpXw" target="_8yB1iKoUEeqEM7mFKilpXw" relationshipRef="_8yDEJ6oUEeqEM7mFKilpXw">          <bendpoint x="1096" y="1394"/>          <bendpoint x="1096" y="1394"/>        </connection>        <connection xsi:type="Relationship" identifier="_8yB3H6oUEeqEM7mFKilpXw" source="_8yBO86oUEeqEM7mFKilpXw" target="_8yBOdqoUEeqEM7mFKilpXw" relationshipRef="_8yDEKaoUEeqEM7mFKilpXw">          <bendpoint x="694" y="1155"/>          <bendpoint x="522" y="1156"/>        </connection>        <connection xsi:type="Relationship" identifier="_8yB3KaoUEeqEM7mFKilpXw" source="_8yB3JqoUEeqEM7mFKilpXw" target="_8yB3KKoUEeqEM7mFKilpXw" relationshipRef="_8yDEK6oUEeqEM7mFKilpXw">          <bendpoint x="1318" y="1501"/>          <bendpoint x="1319" y="1501"/>        </connection>        <connection xsi:type="Relationship" identifier="_8yB3MaoUEeqEM7mFKilpXw" source="_8yB3JqoUEeqEM7mFKilpXw" target="_8yB3J6oUEeqEM7mFKilpXw" relationshipRef="_8yDELaoUEeqEM7mFKilpXw">          <bendpoint x="1318" y="1503"/>          <bendpoint x="1319" y="1556"/>        </connection>        <connection xsi:type="Relationship" identifier="_8yB3OqoUEeqEM7mFKilpXw" source="_8yB3JqoUEeqEM7mFKilpXw" target="_8yB1qaoUEeqEM7mFKilpXw" relationshipRef="_8yDEL6oUEeqEM7mFKilpXw">          <bendpoint x="1096" y="1491"/>          <bendpoint x="1096" y="1491"/>        </connection>        <connection xsi:type="Relationship" identifier="_8yB3Q6oUEeqEM7mFKilpXw" source="_8yBOgKoUEeqEM7mFKilpXw" target="_8yB3QaoUEeqEM7mFKilpXw" relationshipRef="_8yDEMaoUEeqEM7mFKilpXw">          <bendpoint x="373" y="59"/>          <bendpoint x="372" y="893"/>        </connection>        <connection xsi:type="Relationship" identifier="_8yB3S6oUEeqEM7mFKilpXw" source="_8yBOf6oUEeqEM7mFKilpXw" target="_8yB3QaoUEeqEM7mFKilpXw" relationshipRef="_8yDEM6oUEeqEM7mFKilpXw">          <bendpoint x="373" y="234"/>          <bendpoint x="372" y="897"/>        </connection>        <connection xsi:type="Relationship" identifier="_8yB3U6oUEeqEM7mFKilpXw" source="_8yBOdKoUEeqEM7mFKilpXw" target="_8yB3QaoUEeqEM7mFKilpXw" relationshipRef="_8yDENaoUEeqEM7mFKilpXw">          <bendpoint x="371" y="545"/>          <bendpoint x="370" y="901"/>        </connection>        <connection xsi:type="Relationship" identifier="_8yB3W6oUEeqEM7mFKilpXw" source="_8yBOdaoUEeqEM7mFKilpXw" target="_8yB3QaoUEeqEM7mFKilpXw" relationshipRef="_8yDEN6oUEeqEM7mFKilpXw">          <bendpoint x="366" y="703"/>          <bendpoint x="365" y="905"/>        </connection>        <connection xsi:type="Relationship" identifier="_8yB3Y6oUEeqEM7mFKilpXw" source="_8yBOc6oUEeqEM7mFKilpXw" target="_8yB3QaoUEeqEM7mFKilpXw" relationshipRef="_8yDEOaoUEeqEM7mFKilpXw">          <bendpoint x="366" y="795"/>          <bendpoint x="365" y="908"/>        </connection>        <connection xsi:type="Relationship" identifier="_8yB3a6oUEeqEM7mFKilpXw" source="_8yBOcqoUEeqEM7mFKilpXw" target="_8yB3QaoUEeqEM7mFKilpXw" relationshipRef="_8yDEO6oUEeqEM7mFKilpXw">          <bendpoint x="373" y="899"/>          <bendpoint x="372" y="899"/>        </connection>        <connection xsi:type="Relationship" identifier="_8yB3c6oUEeqEM7mFKilpXw" source="_8yBOeKoUEeqEM7mFKilpXw" target="_8yB3QaoUEeqEM7mFKilpXw" relationshipRef="_8yDEPaoUEeqEM7mFKilpXw">          <bendpoint x="373" y="1013"/>          <bendpoint x="372" y="916"/>        </connection>        <connection xsi:type="Relationship" identifier="_8yB3e6oUEeqEM7mFKilpXw" source="_8yBOdqoUEeqEM7mFKilpXw" target="_8yB3QaoUEeqEM7mFKilpXw" relationshipRef="_8yDEP6oUEeqEM7mFKilpXw">          <bendpoint x="373" y="1117"/>          <bendpoint x="372" y="920"/>        </connection>        <connection xsi:type="Relationship" identifier="_8yB3g6oUEeqEM7mFKilpXw" source="_8yBOd6oUEeqEM7mFKilpXw" target="_8yB3QaoUEeqEM7mFKilpXw" relationshipRef="_8yDEQaoUEeqEM7mFKilpXw">          <bendpoint x="376" y="1397"/>          <bendpoint x="375" y="923"/>        </connection>        <connection xsi:type="Relationship" identifier="_8yCckaoUEeqEM7mFKilpXw" source="_8yBOeqoUEeqEM7mFKilpXw" target="_8yB3QaoUEeqEM7mFKilpXw" relationshipRef="_8yDEQ6oUEeqEM7mFKilpXw">          <bendpoint x="382" y="1498"/>          <bendpoint x="382" y="927"/>        </connection>        <connection xsi:type="Relationship" identifier="_8yCcmaoUEeqEM7mFKilpXw" source="_8yBOeaoUEeqEM7mFKilpXw" target="_8yB3QaoUEeqEM7mFKilpXw" relationshipRef="_8yDERaoUEeqEM7mFKilpXw">          <bendpoint x="382" y="1596"/>          <bendpoint x="382" y="931"/>        </connection>        <connection xsi:type="Relationship" identifier="_8yCcoaoUEeqEM7mFKilpXw" source="_8yBOfKoUEeqEM7mFKilpXw" target="_8yB3QaoUEeqEM7mFKilpXw" relationshipRef="_8yDER6oUEeqEM7mFKilpXw">          <bendpoint x="384" y="1838"/>          <bendpoint x="384" y="942"/>        </connection>        <connection xsi:type="Relationship" identifier="_8yCcqaoUEeqEM7mFKilpXw" source="_8yBOe6oUEeqEM7mFKilpXw" target="_8yB3QaoUEeqEM7mFKilpXw" relationshipRef="_8yDESaoUEeqEM7mFKilpXw">          <bendpoint x="384" y="1915"/>          <bendpoint x="384" y="946"/>        </connection>        <connection xsi:type="Relationship" identifier="_8yCcsaoUEeqEM7mFKilpXw" source="_8yBO9aoUEeqEM7mFKilpXw" target="_8yBOdqoUEeqEM7mFKilpXw" relationshipRef="_8yDES6oUEeqEM7mFKilpXw">          <bendpoint x="781" y="1171"/>          <bendpoint x="535" y="1172"/>        </connection>        <connection xsi:type="Relationship" identifier="_8yCcuaoUEeqEM7mFKilpXw" source="_8yBO9KoUEeqEM7mFKilpXw" target="_8yBOdqoUEeqEM7mFKilpXw" relationshipRef="_8yDETaoUEeqEM7mFKilpXw">          <bendpoint x="781" y="1205"/>          <bendpoint x="567" y="1205"/>        </connection>        <connection xsi:type="Relationship" identifier="_8yCcwaoUEeqEM7mFKilpXw" source="_8yBOfaoUEeqEM7mFKilpXw" target="_8yB3QaoUEeqEM7mFKilpXw" relationshipRef="_8yDET6oUEeqEM7mFKilpXw">          <bendpoint x="384" y="1670"/>          <bendpoint x="384" y="935"/>        </connection>        <connection xsi:type="Relationship" identifier="_8yCcyaoUEeqEM7mFKilpXw" source="_8yBOfqoUEeqEM7mFKilpXw" target="_8yB3QaoUEeqEM7mFKilpXw" relationshipRef="_8yDEUaoUEeqEM7mFKilpXw">          <bendpoint x="384" y="1751"/>          <bendpoint x="384" y="938"/>        </connection>        <connection xsi:type="Relationship" identifier="_8yCc3qoUEeqEM7mFKilpXw" source="_8yCc3KoUEeqEM7mFKilpXw" target="_8yCc26oUEeqEM7mFKilpXw" relationshipRef="_8yDEU6oUEeqEM7mFKilpXw">          <bendpoint x="599" y="399"/>          <bendpoint x="509" y="399"/>        </connection>        <connection xsi:type="Relationship" identifier="_8yCc5qoUEeqEM7mFKilpXw" source="_8yCc3KoUEeqEM7mFKilpXw" target="_8yCc3KoUEeqEM7mFKilpXw" relationshipRef="_8yDEVaoUEeqEM7mFKilpXw">          <bendpoint x="548" y="423"/>          <bendpoint x="548" y="383"/>          <bendpoint x="588" y="383"/>        </connection>        <connection xsi:type="Relationship" identifier="_8yCc8KoUEeqEM7mFKilpXw" source="_8yBO16oUEeqEM7mFKilpXw" target="_8yCc3KoUEeqEM7mFKilpXw" relationshipRef="_8yDEV6oUEeqEM7mFKilpXw">          <bendpoint x="764" y="378"/>          <bendpoint x="630" y="378"/>        </connection>        <connection xsi:type="Relationship" identifier="_8yCc-KoUEeqEM7mFKilpXw" source="_8yBOgqoUEeqEM7mFKilpXw" target="_8yCc3KoUEeqEM7mFKilpXw" relationshipRef="_8yDEWaoUEeqEM7mFKilpXw">          <bendpoint x="715" y="419"/>          <bendpoint x="714" y="419"/>        </connection>        <connection xsi:type="Relationship" identifier="_8yCdAKoUEeqEM7mFKilpXw" source="_8yBO4aoUEeqEM7mFKilpXw" target="_8yCc3KoUEeqEM7mFKilpXw" relationshipRef="_8yDEW6oUEeqEM7mFKilpXw">          <bendpoint x="715" y="469"/>          <bendpoint x="714" y="469"/>        </connection>        <connection xsi:type="Relationship" identifier="_8yCdCKoUEeqEM7mFKilpXw" source="_8yBOg6oUEeqEM7mFKilpXw" target="_8yCc3KoUEeqEM7mFKilpXw" relationshipRef="_8yDEXaoUEeqEM7mFKilpXw">          <bendpoint x="786" y="513"/>          <bendpoint x="643" y="514"/>        </connection>        <connection xsi:type="Relationship" identifier="_8yCdEKoUEeqEM7mFKilpXw" source="_8yBOhKoUEeqEM7mFKilpXw" target="_8yCc3KoUEeqEM7mFKilpXw" relationshipRef="_8yDEX6oUEeqEM7mFKilpXw">          <bendpoint x="764" y="556"/>          <bendpoint x="599" y="557"/>        </connection>        <connection xsi:type="Relationship" identifier="_8yCdGKoUEeqEM7mFKilpXw" source="_8yCc3KoUEeqEM7mFKilpXw" target="_8yBO16oUEeqEM7mFKilpXw" relationshipRef="_8yDEYaoUEeqEM7mFKilpXw">          <bendpoint x="676" y="398"/>          <bendpoint x="827" y="398"/>        </connection>        <connection xsi:type="Relationship" identifier="_8yCdIKoUEeqEM7mFKilpXw" source="_8yCc3KoUEeqEM7mFKilpXw" target="_8yBOgqoUEeqEM7mFKilpXw" relationshipRef="_8yDEY6oUEeqEM7mFKilpXw">          <bendpoint x="714" y="439"/>          <bendpoint x="786" y="439"/>        </connection>        <connection xsi:type="Relationship" identifier="_8yCdKKoUEeqEM7mFKilpXw" source="_8yCc3KoUEeqEM7mFKilpXw" target="_8yBOhKoUEeqEM7mFKilpXw" relationshipRef="_8yDEZaoUEeqEM7mFKilpXw">          <bendpoint x="684" y="577"/>          <bendpoint x="827" y="576"/>        </connection>        <connection xsi:type="Relationship" identifier="_8yCdMKoUEeqEM7mFKilpXw" source="_8yBOhaoUEeqEM7mFKilpXw" target="_8yCc3KoUEeqEM7mFKilpXw" relationshipRef="_8yDEZ6oUEeqEM7mFKilpXw">          <bendpoint x="764" y="607"/>          <bendpoint x="621" y="607"/>        </connection>        <connection xsi:type="Relationship" identifier="_8yCdOKoUEeqEM7mFKilpXw" source="_8yCc3KoUEeqEM7mFKilpXw" target="_8yBOhaoUEeqEM7mFKilpXw" relationshipRef="_8yDEaaoUEeqEM7mFKilpXw">          <bendpoint x="706" y="627"/>          <bendpoint x="827" y="627"/>        </connection>        <connection xsi:type="Relationship" identifier="_8yCdQKoUEeqEM7mFKilpXw" source="_8yCc2KoUEeqEM7mFKilpXw" target="_8yB3QaoUEeqEM7mFKilpXw" relationshipRef="_8yDEa6oUEeqEM7mFKilpXw">          <bendpoint x="210" y="957"/>          <bendpoint x="210" y="958"/>        </connection>        <connection xsi:type="Relationship" identifier="_8yCdSKoUEeqEM7mFKilpXw" source="_8yBOeqoUEeqEM7mFKilpXw" target="_8yCc0qoUEeqEM7mFKilpXw" relationshipRef="_8yDEbaoUEeqEM7mFKilpXw">          <bendpoint x="382" y="1485"/>          <bendpoint x="382" y="458"/>        </connection>        <connection xsi:type="Relationship" identifier="_8yCdUKoUEeqEM7mFKilpXw" source="_8yCc0aoUEeqEM7mFKilpXw" target="_8yCc0qoUEeqEM7mFKilpXw" relationshipRef="_8yDEb6oUEeqEM7mFKilpXw">          <bendpoint x="210" y="489"/>          <bendpoint x="210" y="490"/>        </connection>        <connection xsi:type="Relationship" identifier="_8yCdWKoUEeqEM7mFKilpXw" source="_8yCc16oUEeqEM7mFKilpXw" target="_8yCc1aoUEeqEM7mFKilpXw" relationshipRef="_8yDEcaoUEeqEM7mFKilpXw">          <bendpoint x="210" y="797"/>          <bendpoint x="210" y="798"/>        </connection>        <connection xsi:type="Relationship" identifier="_8yCdYKoUEeqEM7mFKilpXw" source="_8yCc1aoUEeqEM7mFKilpXw" target="_8yB3QaoUEeqEM7mFKilpXw" relationshipRef="_8yDEc6oUEeqEM7mFKilpXw">          <bendpoint x="210" y="838"/>          <bendpoint x="210" y="838"/>        </connection>        <connection xsi:type="Relationship" identifier="_8yCdaKoUEeqEM7mFKilpXw" source="_8yCc1qoUEeqEM7mFKilpXw" target="_8yCc0KoUEeqEM7mFKilpXw" relationshipRef="_8yDEdaoUEeqEM7mFKilpXw">          <bendpoint x="210" y="635"/>          <bendpoint x="210" y="635"/>        </connection>        <connection xsi:type="Relationship" identifier="_8yCdcKoUEeqEM7mFKilpXw" source="_8yCc06oUEeqEM7mFKilpXw" target="_8yCc2aoUEeqEM7mFKilpXw" relationshipRef="_8yDEd6oUEeqEM7mFKilpXw">          <bendpoint x="210" y="348"/>          <bendpoint x="210" y="347"/>        </connection>        <connection xsi:type="Relationship" identifier="_8yCdeKoUEeqEM7mFKilpXw" source="_8yBOdqoUEeqEM7mFKilpXw" target="_8yCc2aoUEeqEM7mFKilpXw" relationshipRef="_8yDEeaoUEeqEM7mFKilpXw">          <bendpoint x="373" y="1104"/>          <bendpoint x="372" y="377"/>        </connection>        <connection xsi:type="Relationship" identifier="_8yCdgKoUEeqEM7mFKilpXw" source="_8yBOfKoUEeqEM7mFKilpXw" target="_8yCc2qoUEeqEM7mFKilpXw" relationshipRef="_8yDEe6oUEeqEM7mFKilpXw">          <bendpoint x="384" y="1825"/>          <bendpoint x="384" y="224"/>        </connection>        <connection xsi:type="Relationship" identifier="_8yCdiKoUEeqEM7mFKilpXw" source="_8yBOe6oUEeqEM7mFKilpXw" target="_8yCc0KoUEeqEM7mFKilpXw" relationshipRef="_8yDEfaoUEeqEM7mFKilpXw">          <bendpoint x="384" y="1902"/>          <bendpoint x="384" y="665"/>        </connection>        <connection xsi:type="Relationship" identifier="_8yCdkaoUEeqEM7mFKilpXw" source="_8yCc1KoUEeqEM7mFKilpXw" target="_8yCc2qoUEeqEM7mFKilpXw" relationshipRef="_8yDEf6oUEeqEM7mFKilpXw">          <bendpoint x="210" y="198"/>          <bendpoint x="210" y="198"/>        </connection>        <connection xsi:type="Relationship" identifier="_8yCdmaoUEeqEM7mFKilpXw" source="_8yBOc6oUEeqEM7mFKilpXw" target="_8yCc1aoUEeqEM7mFKilpXw" relationshipRef="_8yDEgaoUEeqEM7mFKilpXw">          <bendpoint x="366" y="777"/>          <bendpoint x="365" y="777"/>        </connection>        <connection xsi:type="Relationship" identifier="_8yCdoaoUEeqEM7mFKilpXw" source="_8yBOdKoUEeqEM7mFKilpXw" target="_8yCc1aoUEeqEM7mFKilpXw" relationshipRef="_8yDEg6oUEeqEM7mFKilpXw">          <bendpoint x="371" y="535"/>          <bendpoint x="370" y="759"/>        </connection>      </view>      <view identifier="_8yCdqKoUEeqEM7mFKilpXw">        <name xml:lang="en">Technology</name>        <node xsi:type="Element" identifier="_8yCdqqoUEeqEM7mFKilpXw" h="60" w="130" x="230" y="120" elementRef="_8yCdrKoUEeqEM7mFKilpXw"/>      </view>    </diagrams>  </views></model>
