<?xml version="1.0" encoding="UTF-8"?><model xmlns="http://www.opengroup.org/xsd/archimate/3.0/" xmlns:xsi="http://www.w3.org/2001/XMLSchema-instance" identifier="_drDNYOhEEeq2bLi4YwKcBg">  <name xml:lang="en">CRAFT TALK</name>  <elements>    <element xsi:type="BusinessRole" identifier="_hr_DMMp3EDi62ezn1J8SPw">      <name xml:lang="en">Менеджер по управлению отношениями</name>      <documentation/>    </element>    <element xsi:type="BusinessRole" identifier="_iMxcEMp3EDi62ezn1J8SPw">      <name xml:lang="en">Настройки приложения</name>      <documentation/>    </element>    <element xsi:type="BusinessRole" identifier="_jW5s4Mp3EDi62ezn1J8SPw">      <name xml:lang="en">Инженер инфраструктуры приложения</name>      <documentation/>    </element>    <element xsi:type="BusinessRole" identifier="_rQnbIMp3EDi62ezn1J8SPw">      <name xml:lang="en">Разработчик приложения</name>      <documentation/>    </element>    <element xsi:type="BusinessRole" identifier="_ybhioMp3EDi62ezn1J8SPw">      <name xml:lang="en">Владелец инфраструктуры</name>      <documentation/>    </element>    <element xsi:type="BusinessRole" identifier="_E0Pw8Mp5EDi62ezn1J8SPw">      <name xml:lang="en">Инженер приложения</name>      <documentation/>    </element>    <element xsi:type="BusinessService" identifier="_bin0gNPIEDi5SI72OAN_iQ">      <name xml:lang="en">СЕРВИС НАШЕГО КЛИЕНТА</name>      <documentation/>    </element>    <element xsi:type="BusinessService" identifier="_frH1kNYmEDiKFrARxFNwIw">      <name xml:lang="en">Service</name>      <documentation/>    </element>    <element xsi:type="BusinessRole" identifier="_jC7kQNPIEDi5SI72OAN_iQ">      <name xml:lang="en">Клиент нашего клиента</name>      <documentation/>    </element>    <element xsi:type="BusinessRole" identifier="_lfK9MNPIEDi5SI72OAN_iQ">      <name xml:lang="en">Оператор</name>      <documentation/>    </element>    <element xsi:type="BusinessRole" identifier="_nK5fMNPIEDi5SI72OAN_iQ">      <name xml:lang="en">Владелец сервиса (наш клиент)</name>      <documentation/>    </element>    <element xsi:type="BusinessFunction" identifier="_rAPZENPIEDi5SI72OAN_iQ">      <name xml:lang="en">Организует сервис</name>      <documentation/>    </element>    <element xsi:type="BusinessFunction" identifier="_yfuCYNPIEDi5SI72OAN_iQ">      <name xml:lang="en">Предоставляет сервис</name>      <documentation/>    </element>    <element xsi:type="BusinessFunction" identifier="_2BrtQNPIEDi5SI72OAN_iQ">      <name xml:lang="en">Получает сервис</name>      <documentation/>    </element>    <element xsi:type="BusinessFunction" identifier="_8pPQENPIEDi5SI72OAN_iQ">      <name xml:lang="en">Реализует и поддерживает сервис</name>      <documentation/>    </element>    <element xsi:type="BusinessFunction" identifier="__3kGcMp2EDi62ezn1J8SPw">      <name xml:lang="en">Организация взаимодействия</name>      <documentation/>    </element>    <element xsi:type="BusinessFunction" identifier="_YwIigMp3EDi62ezn1J8SPw">      <name xml:lang="en">Договорная работа</name>      <documentation/>    </element>    <element xsi:type="BusinessFunction" identifier="_QhhiUMp3EDi62ezn1J8SPw">      <name xml:lang="en">Ценовые переговоры</name>      <documentation/>    </element>    <element xsi:type="BusinessFunction" identifier="_jSi4INPJEDi5SI72OAN_iQ">      <name xml:lang="en">Инженерия приложений</name>      <documentation/>    </element>    <element xsi:type="BusinessFunction" identifier="_EYvvcMpzEDi62ezn1J8SPw">      <name xml:lang="en">Презентации </name>      <documentation/>    </element>    <element xsi:type="BusinessFunction" identifier="_HVJ2MMpzEDi62ezn1J8SPw">      <name xml:lang="en">Бизнес-анализ и формирование ТЗ</name>      <documentation/>    </element>    <element xsi:type="BusinessFunction" identifier="_mTzNMNPKEDi5SI72OAN_iQ">      <name xml:lang="en">Проектирование приложения</name>      <documentation/>    </element>    <element xsi:type="BusinessFunction" identifier="_QlZ5kMpzEDi62ezn1J8SPw">      <name xml:lang="en">Инженерия инфраструктурыприложения</name>      <documentation/>    </element>    <element xsi:type="BusinessFunction" identifier="_IZfLkMp0EDi62ezn1J8SPw">      <name xml:lang="en">Обеспечение непрерывности и доступности</name>      <documentation/>    </element>    <element xsi:type="BusinessFunction" identifier="_VFV9INPKEDi5SI72OAN_iQ">      <name xml:lang="en">Развертывание</name>      <documentation/>    </element>    <element xsi:type="BusinessFunction" identifier="_6eCR4NPKEDi5SI72OAN_iQ">      <name xml:lang="en">Проектирование инфраструктуры</name>      <documentation/>    </element>    <element xsi:type="BusinessFunction" identifier="_neq64Mp0EDi62ezn1J8SPw">      <name xml:lang="en">Обеспечение инфраструктуры</name>      <documentation/>    </element>    <element xsi:type="BusinessFunction" identifier="_o23yAMp2EDi62ezn1J8SPw">      <name xml:lang="en">Педоставление инфраструктуры </name>      <documentation/>    </element>    <element xsi:type="BusinessFunction" identifier="_uKJCcMp2EDi62ezn1J8SPw">      <name xml:lang="en">Предоставление приложений</name>      <documentation/>    </element>    <element xsi:type="BusinessActor" identifier="_tpgkkNPMEDi5SI72OAN_iQ">      <name xml:lang="en">Владелец сервиса</name>      <documentation/>    </element>    <element xsi:type="BusinessService" identifier="_3DEU8NPMEDi5SI72OAN_iQ">      <name xml:lang="en">Сервис</name>      <documentation/>    </element>    <element xsi:type="BusinessFunction" identifier="_SeOpkNPNEDi5SI72OAN_iQ">      <name xml:lang="en">Оперативное управление</name>      <documentation/>    </element>    <element xsi:type="BusinessProcess" identifier="_f-gNINPMEDi5SI72OAN_iQ">      <name xml:lang="en">Процессы привлечения</name>      <documentation/>    </element>    <element xsi:type="BusinessProcess" identifier="_fW2-UNPMEDi5SI72OAN_iQ">      <name xml:lang="en">Процессы реализации</name>      <documentation/>    </element>    <element xsi:type="BusinessProcess" identifier="_gdzYQNPMEDi5SI72OAN_iQ">      <name xml:lang="en">Процессы обеспечения</name>      <documentation/>    </element>    <element xsi:type="BusinessFunction" identifier="_T4Af8NPNEDi5SI72OAN_iQ">      <name xml:lang="en">Стратегическое управление</name>      <documentation/>    </element>    <element xsi:type="BusinessRole" identifier="_u0t-ANPNEDi5SI72OAN_iQ">      <name xml:lang="en">Собственник</name>      <documentation/>    </element>    <element xsi:type="BusinessRole" identifier="_xoHSsNPNEDi5SI72OAN_iQ">      <name xml:lang="en">Исполнительный орган</name>      <documentation/>    </element>    <element xsi:type="BusinessProcess" identifier="_KNT04NPQEDi5SI72OAN_iQ">      <name xml:lang="en">Процессы стратегитческого управления</name>      <documentation/>    </element>    <element xsi:type="BusinessFunction" identifier="_MfZzUNPQEDi5SI72OAN_iQ">      <name xml:lang="en">Матрица бизнес-модели</name>      <documentation/>    </element>    <element xsi:type="BusinessFunction" identifier="_Q490kNPQEDi5SI72OAN_iQ">      <name xml:lang="en">Создание бизнес-модели</name>      <documentation/>    </element>    <element xsi:type="BusinessFunction" identifier="_Vc-yUNPQEDi5SI72OAN_iQ">      <name xml:lang="en">Бюджетирование</name>      <documentation/>    </element>    <element xsi:type="BusinessFunction" identifier="_ZbTCANPQEDi5SI72OAN_iQ">      <name xml:lang="en">Назначение исполнительных органов</name>      <documentation/>    </element>    <element xsi:type="BusinessObject" identifier="_ssCS4NPQEDi5SI72OAN_iQ">      <name xml:lang="en">Object</name>      <documentation/>    </element>    <element xsi:type="BusinessObject" identifier="_vRWvUNPQEDi5SI72OAN_iQ">      <name xml:lang="en">Цели и показатели</name>      <documentation/>    </element>    <element xsi:type="BusinessObject" identifier="_vxUBwNPQEDi5SI72OAN_iQ">      <name xml:lang="en">Диаграммы и регламенты процессов</name>      <documentation/>    </element>    <element xsi:type="BusinessObject" identifier="_waTUYNPQEDi5SI72OAN_iQ">      <name xml:lang="en">Ролевая структура</name>      <documentation/>    </element>    <element xsi:type="BusinessObject" identifier="_xawEwNPQEDi5SI72OAN_iQ">      <name xml:lang="en">Оргструктура</name>      <documentation/>    </element>    <element xsi:type="BusinessObject" identifier="_4qlIgNPQEDi5SI72OAN_iQ">      <name xml:lang="en">Матрица компетенций</name>      <documentation/>    </element>    <element xsi:type="BusinessObject" identifier="_74E_QNPQEDi5SI72OAN_iQ">      <name xml:lang="en">Бизнес-объекты</name>      <documentation/>    </element>    <element xsi:type="BusinessObject" identifier="_W2ODwNVdEDi5SI72OAN_iQ">      <name xml:lang="en">Класс объектов: Партнеры</name>      <documentation/>    </element>    <element xsi:type="BusinessObject" identifier="_ZzcC0NVdEDi5SI72OAN_iQ">      <name xml:lang="en">Подкласс: Партнеры по предоставлению инфраструктуры</name>      <documentation/>    </element>    <element xsi:type="BusinessObject" identifier="_cEuI8NVdEDi5SI72OAN_iQ">      <name xml:lang="en">Класс Обращения</name>      <documentation/>    </element>    <element xsi:type="BusinessObject" identifier="_eqRO4NVdEDi5SI72OAN_iQ">      <name xml:lang="en">ЭкземплярКрафттолк</name>      <documentation/>    </element>    <element xsi:type="BusinessObject" identifier="_nN6D4NVdEDi5SI72OAN_iQ">      <name xml:lang="en">Подкласс: Вендоры</name>      <documentation/>    </element>    <element xsi:type="BusinessObject" identifier="_rG8K8NVdEDi5SI72OAN_iQ">      <name xml:lang="en">Подкласс:Партнеры по поддержке инфраструктуры</name>      <documentation/>    </element>    <element xsi:type="BusinessObject" identifier="_JRVtANVeEDi5SI72OAN_iQ">      <name xml:lang="en">Класс:Сделки</name>      <documentation/>    </element>    <element xsi:type="BusinessObject" identifier="_NOamkNVeEDi5SI72OAN_iQ">      <name xml:lang="en">Класс:Продукты</name>      <documentation/>    </element>    <element xsi:type="BusinessObject" identifier="_XiYwwNVeEDi5SI72OAN_iQ">      <name xml:lang="en">Подкласс: Модели сервисов</name>      <documentation/>    </element>    <element xsi:type="BusinessObject" identifier="_X9lfANVeEDi5SI72OAN_iQ">      <name xml:lang="en">Подкласс: Сервисы</name>      <documentation/>    </element>    <element xsi:type="BusinessObject" identifier="_j9oJcNVeEDi5SI72OAN_iQ">      <name xml:lang="en">Экз. </name>      <documentation/>    </element>    <element xsi:type="BusinessObject" identifier="_polhINVeEDi5SI72OAN_iQ">      <name xml:lang="en">Экз. </name>      <documentation/>    </element>    <element xsi:type="BusinessObject" identifier="_xxb3kNVeEDi5SI72OAN_iQ">      <name xml:lang="en">Экз. </name>      <documentation/>    </element>    <element xsi:type="BusinessObject" identifier="_-o7HYNVeEDi5SI72OAN_iQ">      <name xml:lang="en">Экз. </name>      <documentation/>    </element>    <element xsi:type="BusinessObject" identifier="_PR8IENVfEDi5SI72OAN_iQ">      <name xml:lang="en">Класс предметные компетенции</name>      <documentation/>    </element>    <element xsi:type="BusinessObject" identifier="_f6sDANVfEDi5SI72OAN_iQ">      <name xml:lang="en">Компетенция по моделированию инфраструктуры </name>      <documentation/>    </element>    <element xsi:type="BusinessObject" identifier="_9XopMNVfEDi5SI72OAN_iQ">      <name xml:lang="en">Экз.</name>      <documentation/>    </element>    <element xsi:type="BusinessObject" identifier="_MmziENVgEDi5SI72OAN_iQ">      <name xml:lang="en">Компетенция по бизнес моделированию</name>      <documentation/>    </element>    <element xsi:type="BusinessObject" identifier="_QQ_U0NVgEDi5SI72OAN_iQ">      <name xml:lang="en">Класс: Роли</name>      <documentation/>    </element>    <element xsi:type="BusinessObject" identifier="_UetScNVgEDi5SI72OAN_iQ">      <name xml:lang="en">Инженер инфраструктуры крафттолк</name>      <documentation/>    </element>    <element xsi:type="BusinessObject" identifier="_ZaGOYNVgEDi5SI72OAN_iQ">      <name xml:lang="en">Инженер приложения крафттолк</name>      <documentation/>    </element>    <element xsi:type="BusinessObject" identifier="_cmwXoNVgEDi5SI72OAN_iQ">      <name xml:lang="en">Менеджер по управлению сделками</name>      <documentation/>    </element>    <element xsi:type="BusinessObject" identifier="_1UfnQNVhEDi5SI72OAN_iQ">      <name xml:lang="en">Класс объектов: Владельцы сервисов</name>      <documentation/>    </element>    <element xsi:type="BusinessObject" identifier="_IaPJENViEDi5SI72OAN_iQ">      <name xml:lang="en">Экз</name>      <documentation/>    </element>    <element xsi:type="BusinessObject" identifier="_lX-DsNViEDi5SI72OAN_iQ">      <name xml:lang="en">Партнеры по привлечению</name>      <documentation/>    </element>    <element xsi:type="BusinessObject" identifier="_sbaRQNViEDi5SI72OAN_iQ">      <name xml:lang="en">Object</name>      <documentation/>    </element>    <element xsi:type="BusinessObject" identifier="_9aj6ANViEDi5SI72OAN_iQ">      <name xml:lang="en">Класс контакты</name>      <documentation/>    </element>    <element xsi:type="BusinessObject" identifier="_-QSoINViEDi5SI72OAN_iQ">      <name xml:lang="en">Экз</name>      <documentation/>    </element>  </elements>  <relationships>    <relationship xsi:type="Specialization" identifier="_VhNH0NPMEDi5SI72OAN_iQ" source="_HVJ2MMpzEDi62ezn1J8SPw" target="_6eCR4NPKEDi5SI72OAN_iQ">      <name xml:lang="en"/>      <documentation/>    </relationship>    <relationship xsi:type="Flow" identifier="_iQYTsNPNEDi5SI72OAN_iQ" source="_f-gNINPMEDi5SI72OAN_iQ" target="_fW2-UNPMEDi5SI72OAN_iQ">      <name xml:lang="en"/>      <documentation/>    </relationship>    <relationship xsi:type="Flow" identifier="_jSreMNPNEDi5SI72OAN_iQ" source="_fW2-UNPMEDi5SI72OAN_iQ" target="_3DEU8NPMEDi5SI72OAN_iQ">      <name xml:lang="en"/>      <documentation/>    </relationship>    <relationship xsi:type="Serving" identifier="_mqcrQNPNEDi5SI72OAN_iQ" source="_gdzYQNPMEDi5SI72OAN_iQ" target="_f-gNINPMEDi5SI72OAN_iQ">      <name xml:lang="en"/>      <documentation/>    </relationship>    <relationship xsi:type="Serving" identifier="_nNwMoNPNEDi5SI72OAN_iQ" source="_gdzYQNPMEDi5SI72OAN_iQ" target="_fW2-UNPMEDi5SI72OAN_iQ">      <name xml:lang="en"/>      <documentation/>    </relationship>    <relationship xsi:type="Serving" identifier="_uMTscNPIEDi5SI72OAN_iQ" source="_nK5fMNPIEDi5SI72OAN_iQ" target="_rAPZENPIEDi5SI72OAN_iQ">      <name xml:lang="en"/>      <documentation/>    </relationship>    <relationship xsi:type="Realization" identifier="_u0nCkNPIEDi5SI72OAN_iQ" source="_rAPZENPIEDi5SI72OAN_iQ" target="_bin0gNPIEDi5SI72OAN_iQ">      <name xml:lang="en"/>      <documentation/>    </relationship>    <relationship xsi:type="Serving" identifier="_zlA2gNPIEDi5SI72OAN_iQ" source="_lfK9MNPIEDi5SI72OAN_iQ" target="_yfuCYNPIEDi5SI72OAN_iQ">      <name xml:lang="en"/>      <documentation/>    </relationship>    <relationship xsi:type="Realization" identifier="_2uskQNPIEDi5SI72OAN_iQ" source="_2BrtQNPIEDi5SI72OAN_iQ" target="_bin0gNPIEDi5SI72OAN_iQ">      <name xml:lang="en"/>      <documentation/>    </relationship>    <relationship xsi:type="Serving" identifier="_3Nmt0NPIEDi5SI72OAN_iQ" source="_jC7kQNPIEDi5SI72OAN_iQ" target="_2BrtQNPIEDi5SI72OAN_iQ">      <name xml:lang="en"/>      <documentation/>    </relationship>    <relationship xsi:type="Composition" identifier="_tBlJQNPJEDi5SI72OAN_iQ" source="_8pPQENPIEDi5SI72OAN_iQ" target="__3kGcMp2EDi62ezn1J8SPw">      <name xml:lang="en"/>      <documentation/>    </relationship>    <relationship xsi:type="Composition" identifier="_tkclwNPJEDi5SI72OAN_iQ" source="_8pPQENPIEDi5SI72OAN_iQ" target="_jSi4INPJEDi5SI72OAN_iQ">      <name xml:lang="en"/>      <documentation/>    </relationship>    <relationship xsi:type="Composition" identifier="_YrEGoNPKEDi5SI72OAN_iQ" source="_8pPQENPIEDi5SI72OAN_iQ" target="_QlZ5kMpzEDi62ezn1J8SPw">      <name xml:lang="en"/>      <documentation/>    </relationship>    <relationship xsi:type="Serving" identifier="_klsFkNPKEDi5SI72OAN_iQ" source="_hr_DMMp3EDi62ezn1J8SPw" target="__3kGcMp2EDi62ezn1J8SPw">      <name xml:lang="en"/>      <documentation/>    </relationship>    <relationship xsi:type="Serving" identifier="__oXBsNPKEDi5SI72OAN_iQ" source="_jW5s4Mp3EDi62ezn1J8SPw" target="_QlZ5kMpzEDi62ezn1J8SPw">      <name xml:lang="en"/>      <documentation/>    </relationship>    <relationship xsi:type="Serving" identifier="_F_zE4NPLEDi5SI72OAN_iQ" source="_E0Pw8Mp5EDi62ezn1J8SPw" target="_jSi4INPJEDi5SI72OAN_iQ">      <name xml:lang="en"/>      <documentation/>    </relationship>    <relationship xsi:type="Composition" identifier="_cjCBQNPLEDi5SI72OAN_iQ" source="_QlZ5kMpzEDi62ezn1J8SPw" target="_neq64Mp0EDi62ezn1J8SPw">      <name xml:lang="en"/>      <documentation/>    </relationship>    <relationship xsi:type="Assignment" identifier="_nVXicNPLEDi5SI72OAN_iQ" source="_ybhioMp3EDi62ezn1J8SPw" target="_o23yAMp2EDi62ezn1J8SPw">      <name xml:lang="en"/>      <documentation/>    </relationship>    <relationship xsi:type="Assignment" identifier="_n9OzsNPLEDi5SI72OAN_iQ" source="_rQnbIMp3EDi62ezn1J8SPw" target="_uKJCcMp2EDi62ezn1J8SPw">      <name xml:lang="en"/>      <documentation/>    </relationship>    <relationship xsi:type="Association" identifier="_8jsE4NPMEDi5SI72OAN_iQ" source="_tpgkkNPMEDi5SI72OAN_iQ" target="_3DEU8NPMEDi5SI72OAN_iQ">      <name xml:lang="en"/>      <documentation/>    </relationship>    <relationship xsi:type="Serving" identifier="_g2Xz0NPNEDi5SI72OAN_iQ" source="_T4Af8NPNEDi5SI72OAN_iQ" target="_SeOpkNPNEDi5SI72OAN_iQ">      <name xml:lang="en"/>      <documentation/>    </relationship>    <relationship xsi:type="Serving" identifier="_v2arkNPNEDi5SI72OAN_iQ" source="_u0t-ANPNEDi5SI72OAN_iQ" target="_T4Af8NPNEDi5SI72OAN_iQ">      <name xml:lang="en"/>      <documentation/>    </relationship>    <relationship xsi:type="Serving" identifier="_2GuMANPNEDi5SI72OAN_iQ" source="_xoHSsNPNEDi5SI72OAN_iQ" target="_SeOpkNPNEDi5SI72OAN_iQ">      <name xml:lang="en"/>      <documentation/>    </relationship>    <relationship xsi:type="Composition" identifier="_O8hWANPQEDi5SI72OAN_iQ" source="_KNT04NPQEDi5SI72OAN_iQ" target="_MfZzUNPQEDi5SI72OAN_iQ">      <name xml:lang="en"/>      <documentation/>    </relationship>    <relationship xsi:type="Composition" identifier="_S7H5kNPQEDi5SI72OAN_iQ" source="_KNT04NPQEDi5SI72OAN_iQ" target="_Q490kNPQEDi5SI72OAN_iQ">      <name xml:lang="en"/>      <documentation/>    </relationship>    <relationship xsi:type="Composition" identifier="_WX7XoNPQEDi5SI72OAN_iQ" source="_KNT04NPQEDi5SI72OAN_iQ" target="_Vc-yUNPQEDi5SI72OAN_iQ">      <name xml:lang="en"/>      <documentation/>    </relationship>    <relationship xsi:type="Composition" identifier="_aQ3_INPQEDi5SI72OAN_iQ" source="_KNT04NPQEDi5SI72OAN_iQ" target="_ZbTCANPQEDi5SI72OAN_iQ">      <name xml:lang="en"/>      <documentation/>    </relationship>    <relationship xsi:type="Association" identifier="_uMSksNPQEDi5SI72OAN_iQ" source="_ssCS4NPQEDi5SI72OAN_iQ" target="_Q490kNPQEDi5SI72OAN_iQ">      <name xml:lang="en"/>      <documentation/>    </relationship>    <relationship xsi:type="Aggregation" identifier="_n4qRENVdEDi5SI72OAN_iQ" source="_W2ODwNVdEDi5SI72OAN_iQ" target="_nN6D4NVdEDi5SI72OAN_iQ">      <name xml:lang="en"/>      <documentation/>    </relationship>    <relationship xsi:type="Aggregation" identifier="_zfg_cNVdEDi5SI72OAN_iQ" source="_W2ODwNVdEDi5SI72OAN_iQ" target="_rG8K8NVdEDi5SI72OAN_iQ">      <name xml:lang="en"/>      <documentation/>    </relationship>    <relationship xsi:type="Aggregation" identifier="_3gndYNVdEDi5SI72OAN_iQ" source="_W2ODwNVdEDi5SI72OAN_iQ" target="_ZzcC0NVdEDi5SI72OAN_iQ">      <name xml:lang="en"/>      <documentation/>    </relationship>    <relationship xsi:type="Aggregation" identifier="_AycOENVeEDi5SI72OAN_iQ" source="_nN6D4NVdEDi5SI72OAN_iQ" target="_eqRO4NVdEDi5SI72OAN_iQ">      <name xml:lang="en"/>      <documentation/>    </relationship>    <relationship xsi:type="Aggregation" identifier="_ZRKmwNVeEDi5SI72OAN_iQ" source="_NOamkNVeEDi5SI72OAN_iQ" target="_XiYwwNVeEDi5SI72OAN_iQ">      <name xml:lang="en"/>      <documentation/>    </relationship>    <relationship xsi:type="Aggregation" identifier="_bkFEkNVeEDi5SI72OAN_iQ" source="_NOamkNVeEDi5SI72OAN_iQ" target="_X9lfANVeEDi5SI72OAN_iQ">      <name xml:lang="en"/>      <documentation/>    </relationship>    <relationship xsi:type="Aggregation" identifier="_l67joNVeEDi5SI72OAN_iQ" source="_XiYwwNVeEDi5SI72OAN_iQ" target="_j9oJcNVeEDi5SI72OAN_iQ">      <name xml:lang="en"/>      <documentation/>    </relationship>    <relationship xsi:type="Aggregation" identifier="_qZTzcNVeEDi5SI72OAN_iQ" source="_X9lfANVeEDi5SI72OAN_iQ" target="_polhINVeEDi5SI72OAN_iQ">      <name xml:lang="en"/>      <documentation/>    </relationship>    <relationship xsi:type="Aggregation" identifier="_znO7kNVeEDi5SI72OAN_iQ" source="_cEuI8NVdEDi5SI72OAN_iQ" target="_xxb3kNVeEDi5SI72OAN_iQ">      <name xml:lang="en"/>      <documentation/>    </relationship>    <relationship xsi:type="Aggregation" identifier="__igawNVeEDi5SI72OAN_iQ" source="_JRVtANVeEDi5SI72OAN_iQ" target="_-o7HYNVeEDi5SI72OAN_iQ">      <name xml:lang="en"/>      <documentation/>    </relationship>    <relationship xsi:type="Aggregation" identifier="_-tdMoNVfEDi5SI72OAN_iQ" source="_ZzcC0NVdEDi5SI72OAN_iQ" target="_9XopMNVfEDi5SI72OAN_iQ">      <name xml:lang="en"/>      <documentation/>    </relationship>    <relationship xsi:type="Aggregation" identifier="_KBLjoNVgEDi5SI72OAN_iQ" source="_PR8IENVfEDi5SI72OAN_iQ" target="_f6sDANVfEDi5SI72OAN_iQ">      <name xml:lang="en"/>      <documentation/>    </relationship>    <relationship xsi:type="Aggregation" identifier="_nHsm0NVgEDi5SI72OAN_iQ" source="_QQ_U0NVgEDi5SI72OAN_iQ" target="_UetScNVgEDi5SI72OAN_iQ">      <name xml:lang="en"/>      <documentation/>    </relationship>    <relationship xsi:type="Aggregation" identifier="_nve_kNVgEDi5SI72OAN_iQ" source="_QQ_U0NVgEDi5SI72OAN_iQ" target="_ZaGOYNVgEDi5SI72OAN_iQ">      <name xml:lang="en"/>      <documentation/>    </relationship>    <relationship xsi:type="Aggregation" identifier="_ok49kNVgEDi5SI72OAN_iQ" source="_QQ_U0NVgEDi5SI72OAN_iQ" target="_cmwXoNVgEDi5SI72OAN_iQ">      <name xml:lang="en"/>      <documentation/>    </relationship>    <relationship xsi:type="Aggregation" identifier="_JKlA4NViEDi5SI72OAN_iQ" source="_1UfnQNVhEDi5SI72OAN_iQ" target="_IaPJENViEDi5SI72OAN_iQ">      <name xml:lang="en"/>      <documentation/>    </relationship>    <relationship xsi:type="Aggregation" identifier="_mck7UNViEDi5SI72OAN_iQ" source="_W2ODwNVdEDi5SI72OAN_iQ" target="_lX-DsNViEDi5SI72OAN_iQ">      <name xml:lang="en"/>      <documentation/>    </relationship>    <relationship xsi:type="Aggregation" identifier="_tL-LgNViEDi5SI72OAN_iQ" source="_lX-DsNViEDi5SI72OAN_iQ" target="_sbaRQNViEDi5SI72OAN_iQ">      <name xml:lang="en"/>      <documentation/>    </relationship>    <relationship xsi:type="Aggregation" identifier="__BJdUNViEDi5SI72OAN_iQ" source="_9aj6ANViEDi5SI72OAN_iQ" target="_-QSoINViEDi5SI72OAN_iQ">      <name xml:lang="en"/>      <documentation/>    </relationship>    <relationship xsi:type="Realization" identifier="_lxMb8NYmEDiKFrARxFNwIw" source="_yfuCYNPIEDi5SI72OAN_iQ" target="_frH1kNYmEDiKFrARxFNwIw">      <name xml:lang="en"/>      <documentation/>    </relationship>    <relationship xsi:type="Realization" identifier="_mqVDYNYmEDiKFrARxFNwIw" source="_2BrtQNPIEDi5SI72OAN_iQ" target="_frH1kNYmEDiKFrARxFNwIw">      <name xml:lang="en"/>      <documentation/>    </relationship>    <relationship xsi:type="Realization" identifier="_pJ1ywNYmEDiKFrARxFNwIw" source="_8pPQENPIEDi5SI72OAN_iQ" target="_frH1kNYmEDiKFrARxFNwIw">      <name xml:lang="en"/>      <documentation/>    </relationship>  </relationships>  <views>    <diagrams>      <view identifier="_drD0cehEEeq2bLi4YwKcBg">        <name xml:lang="en">archimate-diagram</name>        <node xsi:type="Element" identifier="_QljDgMpzEDi62ezn1J8SPw" h="320" w="180" x="833" y="297" elementRef="_QlZ5kMpzEDi62ezn1J8SPw">          <node xsi:type="Element" identifier="_IZpjoMp0EDi62ezn1J8SPw" h="60" w="130" x="852" y="528" elementRef="_IZfLkMp0EDi62ezn1J8SPw"/>          <node xsi:type="Element" identifier="_VFZAcNPKEDi5SI72OAN_iQ" h="60" w="130" x="852" y="447" elementRef="_VFV9INPKEDi5SI72OAN_iQ"/>          <node xsi:type="Element" identifier="_6eEuINPKEDi5SI72OAN_iQ" h="60" w="130" x="852" y="364" elementRef="_6eCR4NPKEDi5SI72OAN_iQ"/>        </node>        <node xsi:type="Element" identifier="_ne0r4Mp0EDi62ezn1J8SPw" h="196" w="170" x="1005" y="388" elementRef="_neq64Mp0EDi62ezn1J8SPw">          <node xsi:type="Element" identifier="_o27cYMp2EDi62ezn1J8SPw" h="60" w="140" x="1019" y="440" elementRef="_o23yAMp2EDi62ezn1J8SPw"/>          <node xsi:type="Element" identifier="_uKLesMp2EDi62ezn1J8SPw" h="60" w="140" x="1019" y="514" elementRef="_uKJCcMp2EDi62ezn1J8SPw"/>        </node>        <node xsi:type="Element" identifier="__3nJwMp2EDi62ezn1J8SPw" h="200" w="190" x="52" y="296" elementRef="__3kGcMp2EDi62ezn1J8SPw">          <node xsi:type="Element" identifier="_QhkloMp3EDi62ezn1J8SPw" h="60" w="130" x="82" y="344" elementRef="_QhhiUMp3EDi62ezn1J8SPw"/>          <node xsi:type="Element" identifier="_YwLl0Mp3EDi62ezn1J8SPw" h="60" w="130" x="82" y="415" elementRef="_YwIigMp3EDi62ezn1J8SPw"/>        </node>        <node xsi:type="Element" identifier="_hsL3gMp3EDi62ezn1J8SPw" h="60" w="130" x="82" y="715" elementRef="_hr_DMMp3EDi62ezn1J8SPw"/>        <node xsi:type="Element" identifier="_jXC20Mp3EDi62ezn1J8SPw" h="60" w="130" x="852" y="713" elementRef="_jW5s4Mp3EDi62ezn1J8SPw"/>        <node xsi:type="Element" identifier="_rQxMIMp3EDi62ezn1J8SPw" h="60" w="130" x="1223" y="514" elementRef="_rQnbIMp3EDi62ezn1J8SPw"/>        <node xsi:type="Element" identifier="_ybqskMp3EDi62ezn1J8SPw" h="60" w="130" x="1223" y="440" elementRef="_ybhioMp3EDi62ezn1J8SPw"/>        <node xsi:type="Element" identifier="_E0lIIMp5EDi62ezn1J8SPw" h="60" w="130" x="452" y="715" elementRef="_E0Pw8Mp5EDi62ezn1J8SPw"/>        <node xsi:type="Element" identifier="_biwXYNPIEDi5SI72OAN_iQ" h="100" w="228" x="422" y="63" elementRef="_bin0gNPIEDi5SI72OAN_iQ">          <node xsi:type="Element" identifier="_frnk0NYmEDiKFrARxFNwIw" h="60" w="130" x="471" y="93" elementRef="_frH1kNYmEDiKFrARxFNwIw"/>        </node>        <node xsi:type="Element" identifier="_jDCR8NPIEDi5SI72OAN_iQ" h="60" w="130" x="82" y="93" elementRef="_jC7kQNPIEDi5SI72OAN_iQ"/>        <node xsi:type="Element" identifier="_lfSR8NPIEDi5SI72OAN_iQ" h="60" w="130" x="916" y="107" elementRef="_lfK9MNPIEDi5SI72OAN_iQ"/>        <node xsi:type="Element" identifier="_nLAz8NPIEDi5SI72OAN_iQ" h="60" w="130" x="993" y="10" elementRef="_nK5fMNPIEDi5SI72OAN_iQ"/>        <node xsi:type="Element" identifier="_rAWt0NPIEDi5SI72OAN_iQ" h="60" w="130" x="699" y="10" elementRef="_rAPZENPIEDi5SI72OAN_iQ"/>        <node xsi:type="Element" identifier="_yf2lQNPIEDi5SI72OAN_iQ" h="60" w="130" x="699" y="107" elementRef="_yfuCYNPIEDi5SI72OAN_iQ"/>        <node xsi:type="Element" identifier="_2BzpENPIEDi5SI72OAN_iQ" h="60" w="130" x="255" y="93" elementRef="_2BrtQNPIEDi5SI72OAN_iQ"/>        <node xsi:type="Element" identifier="_8pXy8NPIEDi5SI72OAN_iQ" h="60" w="130" x="452" y="192" elementRef="_8pPQENPIEDi5SI72OAN_iQ"/>        <node xsi:type="Element" identifier="_jStQMNPJEDi5SI72OAN_iQ" h="360" w="190" x="422" y="306" elementRef="_jSi4INPJEDi5SI72OAN_iQ">          <node xsi:type="Element" identifier="_EY3rQMpzEDi62ezn1J8SPw" h="60" w="130" x="445" y="343" elementRef="_EYvvcMpzEDi62ezn1J8SPw"/>          <node xsi:type="Element" identifier="_HVSZEMpzEDi62ezn1J8SPw" h="60" w="140" x="440" y="426" elementRef="_HVJ2MMpzEDi62ezn1J8SPw"/>          <node xsi:type="Element" identifier="_iM5-8Mp3EDi62ezn1J8SPw" h="60" w="130" x="443" y="586" elementRef="_iMxcEMp3EDi62ezn1J8SPw"/>          <node xsi:type="Element" identifier="_mT2QgNPKEDi5SI72OAN_iQ" h="60" w="135" x="440" y="505" elementRef="_mTzNMNPKEDi5SI72OAN_iQ"/>        </node>        <connection xsi:type="Relationship" identifier="_uMaaINPIEDi5SI72OAN_iQ" source="_nLAz8NPIEDi5SI72OAN_iQ" target="_rAWt0NPIEDi5SI72OAN_iQ" relationshipRef="_uMTscNPIEDi5SI72OAN_iQ"/>        <connection xsi:type="Relationship" identifier="_u0vlcNPIEDi5SI72OAN_iQ" source="_rAWt0NPIEDi5SI72OAN_iQ" target="_biwXYNPIEDi5SI72OAN_iQ" relationshipRef="_u0nCkNPIEDi5SI72OAN_iQ"/>        <connection xsi:type="Relationship" identifier="_zlILQNPIEDi5SI72OAN_iQ" source="_lfSR8NPIEDi5SI72OAN_iQ" target="_yf2lQNPIEDi5SI72OAN_iQ" relationshipRef="_zlA2gNPIEDi5SI72OAN_iQ"/>        <connection xsi:type="Relationship" identifier="_2uz5ANPIEDi5SI72OAN_iQ" source="_2BzpENPIEDi5SI72OAN_iQ" target="_biwXYNPIEDi5SI72OAN_iQ" relationshipRef="_2uskQNPIEDi5SI72OAN_iQ"/>        <connection xsi:type="Relationship" identifier="_3Nv3wNPIEDi5SI72OAN_iQ" source="_jDCR8NPIEDi5SI72OAN_iQ" target="_2BzpENPIEDi5SI72OAN_iQ" relationshipRef="_3Nmt0NPIEDi5SI72OAN_iQ"/>        <connection xsi:type="Relationship" identifier="_tBuTMNPJEDi5SI72OAN_iQ" source="_8pXy8NPIEDi5SI72OAN_iQ" target="__3nJwMp2EDi62ezn1J8SPw" relationshipRef="_tBlJQNPJEDi5SI72OAN_iQ"/>        <connection xsi:type="Relationship" identifier="_tklIoNPJEDi5SI72OAN_iQ" source="_8pXy8NPIEDi5SI72OAN_iQ" target="_jStQMNPJEDi5SI72OAN_iQ" relationshipRef="_tkclwNPJEDi5SI72OAN_iQ"/>        <connection xsi:type="Relationship" identifier="_YrPFwNPKEDi5SI72OAN_iQ" source="_8pXy8NPIEDi5SI72OAN_iQ" target="_QljDgMpzEDi62ezn1J8SPw" relationshipRef="_YrEGoNPKEDi5SI72OAN_iQ"/>        <connection xsi:type="Relationship" identifier="_kl12kNPKEDi5SI72OAN_iQ" source="_hsL3gMp3EDi62ezn1J8SPw" target="__3nJwMp2EDi62ezn1J8SPw" relationshipRef="_klsFkNPKEDi5SI72OAN_iQ"/>        <connection xsi:type="Relationship" identifier="__oe9gNPKEDi5SI72OAN_iQ" source="_jXC20Mp3EDi62ezn1J8SPw" target="_QljDgMpzEDi62ezn1J8SPw" relationshipRef="__oXBsNPKEDi5SI72OAN_iQ"/>        <connection xsi:type="Relationship" identifier="_F_7AsNPLEDi5SI72OAN_iQ" source="_E0lIIMp5EDi62ezn1J8SPw" target="_jStQMNPJEDi5SI72OAN_iQ" relationshipRef="_F_zE4NPLEDi5SI72OAN_iQ"/>        <connection xsi:type="Relationship" identifier="_cjJ9ENPLEDi5SI72OAN_iQ" source="_QljDgMpzEDi62ezn1J8SPw" target="_ne0r4Mp0EDi62ezn1J8SPw" relationshipRef="_cjCBQNPLEDi5SI72OAN_iQ"/>        <connection xsi:type="Relationship" identifier="_nVe3MNPLEDi5SI72OAN_iQ" source="_ybqskMp3EDi62ezn1J8SPw" target="_o27cYMp2EDi62ezn1J8SPw" relationshipRef="_nVXicNPLEDi5SI72OAN_iQ"/>        <connection xsi:type="Relationship" identifier="_n9WvgNPLEDi5SI72OAN_iQ" source="_rQxMIMp3EDi62ezn1J8SPw" target="_uKLesMp2EDi62ezn1J8SPw" relationshipRef="_n9OzsNPLEDi5SI72OAN_iQ"/>        <connection xsi:type="Relationship" identifier="_VhWRwNPMEDi5SI72OAN_iQ" source="_HVSZEMpzEDi62ezn1J8SPw" target="_6eEuINPKEDi5SI72OAN_iQ" relationshipRef="_VhNH0NPMEDi5SI72OAN_iQ"/>        <connection xsi:type="Relationship" identifier="_lxpu8NYmEDiKFrARxFNwIw" source="_yf2lQNPIEDi5SI72OAN_iQ" target="_frnk0NYmEDiKFrARxFNwIw" relationshipRef="_lxMb8NYmEDiKFrARxFNwIw"/>        <connection xsi:type="Relationship" identifier="_mqnXQNYmEDiKFrARxFNwIw" source="_2BzpENPIEDi5SI72OAN_iQ" target="_frnk0NYmEDiKFrARxFNwIw" relationshipRef="_mqVDYNYmEDiKFrARxFNwIw"/>        <connection xsi:type="Relationship" identifier="_pKFDUNYmEDiKFrARxFNwIw" source="_8pXy8NPIEDi5SI72OAN_iQ" target="_frnk0NYmEDiKFrARxFNwIw" relationshipRef="_pJ1ywNYmEDiKFrARxFNwIw"/>      </view>      <view identifier="_dXix8NPMEDi5SI72OAN_iQ">        <name xml:lang="en">archimate-diagram</name>        <node xsi:type="Element" identifier="_tpv1INPMEDi5SI72OAN_iQ" h="60" w="130" x="555" y="61" elementRef="_tpgkkNPMEDi5SI72OAN_iQ"/>        <node xsi:type="Element" identifier="_3DUzoNPMEDi5SI72OAN_iQ" h="60" w="130" x="555" y="329" elementRef="_3DEU8NPMEDi5SI72OAN_iQ"/>        <node xsi:type="Element" identifier="_SeehMNPNEDi5SI72OAN_iQ" h="270" w="400" x="101" y="284" elementRef="_SeOpkNPNEDi5SI72OAN_iQ">          <node xsi:type="Element" identifier="_fXFn0NPMEDi5SI72OAN_iQ" h="60" w="130" x="356" y="389" elementRef="_fW2-UNPMEDi5SI72OAN_iQ"/>          <node xsi:type="Element" identifier="_f-u2oNPMEDi5SI72OAN_iQ" h="60" w="130" x="124" y="389" elementRef="_f-gNINPMEDi5SI72OAN_iQ"/>          <node xsi:type="Element" identifier="_geCBwNPMEDi5SI72OAN_iQ" h="60" w="120" x="241" y="482" elementRef="_gdzYQNPMEDi5SI72OAN_iQ"/>        </node>        <node xsi:type="Element" identifier="_T4QXkNPNEDi5SI72OAN_iQ" h="60" w="130" x="144" y="165" elementRef="_T4Af8NPNEDi5SI72OAN_iQ"/>        <node xsi:type="Element" identifier="_u08ngNPNEDi5SI72OAN_iQ" h="60" w="130" x="144" y="54" elementRef="_u0t-ANPNEDi5SI72OAN_iQ"/>        <node xsi:type="Element" identifier="_xoXxYNPNEDi5SI72OAN_iQ" h="60" w="130" x="369" y="54" elementRef="_xoHSsNPNEDi5SI72OAN_iQ"/>        <connection xsi:type="Relationship" identifier="_8j7VcNPMEDi5SI72OAN_iQ" source="_tpv1INPMEDi5SI72OAN_iQ" target="_3DUzoNPMEDi5SI72OAN_iQ" relationshipRef="_8jsE4NPMEDi5SI72OAN_iQ"/>        <connection xsi:type="Relationship" identifier="_g2l2QNPNEDi5SI72OAN_iQ" source="_T4QXkNPNEDi5SI72OAN_iQ" target="_SeehMNPNEDi5SI72OAN_iQ" relationshipRef="_g2Xz0NPNEDi5SI72OAN_iQ"/>        <connection xsi:type="Relationship" identifier="_iQaI4NPNEDi5SI72OAN_iQ" source="_f-u2oNPMEDi5SI72OAN_iQ" target="_fXFn0NPMEDi5SI72OAN_iQ" relationshipRef="_iQYTsNPNEDi5SI72OAN_iQ"/>        <connection xsi:type="Relationship" identifier="_jStTYNPNEDi5SI72OAN_iQ" source="_fXFn0NPMEDi5SI72OAN_iQ" target="_3DUzoNPMEDi5SI72OAN_iQ" relationshipRef="_jSreMNPNEDi5SI72OAN_iQ"/>        <connection xsi:type="Relationship" identifier="_mqegcNPNEDi5SI72OAN_iQ" source="_geCBwNPMEDi5SI72OAN_iQ" target="_f-u2oNPMEDi5SI72OAN_iQ" relationshipRef="_mqcrQNPNEDi5SI72OAN_iQ"/>        <connection xsi:type="Relationship" identifier="_nNyB0NPNEDi5SI72OAN_iQ" source="_geCBwNPMEDi5SI72OAN_iQ" target="_fXFn0NPMEDi5SI72OAN_iQ" relationshipRef="_nNwMoNPNEDi5SI72OAN_iQ"/>        <connection xsi:type="Relationship" identifier="_v2m40NPNEDi5SI72OAN_iQ" source="_u08ngNPNEDi5SI72OAN_iQ" target="_T4QXkNPNEDi5SI72OAN_iQ" relationshipRef="_v2arkNPNEDi5SI72OAN_iQ"/>        <connection xsi:type="Relationship" identifier="_2G7AUNPNEDi5SI72OAN_iQ" source="_xoXxYNPNEDi5SI72OAN_iQ" target="_SeehMNPNEDi5SI72OAN_iQ" relationshipRef="_2GuMANPNEDi5SI72OAN_iQ"/>      </view>      <view identifier="__3c0UNPPEDi5SI72OAN_iQ">        <name xml:lang="en">archimate-diagram</name>        <node xsi:type="Element" identifier="_KNsPYNPQEDi5SI72OAN_iQ" h="60" w="130" x="273" y="37" elementRef="_KNT04NPQEDi5SI72OAN_iQ"/>        <node xsi:type="Element" identifier="_MfvxkNPQEDi5SI72OAN_iQ" h="60" w="130" x="51" y="177" elementRef="_MfZzUNPQEDi5SI72OAN_iQ"/>        <node xsi:type="Element" identifier="_Q5VoANPQEDi5SI72OAN_iQ" h="60" w="130" x="198" y="177" elementRef="_Q490kNPQEDi5SI72OAN_iQ"/>        <node xsi:type="Element" identifier="_VdV-sNPQEDi5SI72OAN_iQ" h="60" w="130" x="348" y="175" elementRef="_Vc-yUNPQEDi5SI72OAN_iQ"/>        <node xsi:type="Element" identifier="_ZbsDkNPQEDi5SI72OAN_iQ" h="60" w="130" x="499" y="175" elementRef="_ZbTCANPQEDi5SI72OAN_iQ"/>        <node xsi:type="Element" identifier="_sseXwNPQEDi5SI72OAN_iQ" h="260" w="320" x="103" y="276" elementRef="_ssCS4NPQEDi5SI72OAN_iQ">          <node xsi:type="Element" identifier="_vRc18NPQEDi5SI72OAN_iQ" h="60" w="130" x="127" y="309" elementRef="_vRWvUNPQEDi5SI72OAN_iQ"/>          <node xsi:type="Element" identifier="_vxV28NPQEDi5SI72OAN_iQ" h="60" w="130" x="273" y="309" elementRef="_vxUBwNPQEDi5SI72OAN_iQ"/>          <node xsi:type="Element" identifier="_waru4NPQEDi5SI72OAN_iQ" h="60" w="130" x="273" y="380" elementRef="_waTUYNPQEDi5SI72OAN_iQ"/>          <node xsi:type="Element" identifier="_xbJGUNPQEDi5SI72OAN_iQ" h="60" w="130" x="127" y="458" elementRef="_xawEwNPQEDi5SI72OAN_iQ"/>          <node xsi:type="Element" identifier="_4rCbgNPQEDi5SI72OAN_iQ" h="60" w="130" x="127" y="380" elementRef="_4qlIgNPQEDi5SI72OAN_iQ"/>          <node xsi:type="Element" identifier="_74gdENPQEDi5SI72OAN_iQ" h="60" w="130" x="273" y="458" elementRef="_74E_QNPQEDi5SI72OAN_iQ"/>        </node>        <connection xsi:type="Relationship" identifier="_O80Q8NPQEDi5SI72OAN_iQ" source="_KNsPYNPQEDi5SI72OAN_iQ" target="_MfvxkNPQEDi5SI72OAN_iQ" relationshipRef="_O8hWANPQEDi5SI72OAN_iQ"/>        <connection xsi:type="Relationship" identifier="_S7a0gNPQEDi5SI72OAN_iQ" source="_KNsPYNPQEDi5SI72OAN_iQ" target="_Q5VoANPQEDi5SI72OAN_iQ" relationshipRef="_S7H5kNPQEDi5SI72OAN_iQ"/>        <connection xsi:type="Relationship" identifier="_WYNrgNPQEDi5SI72OAN_iQ" source="_KNsPYNPQEDi5SI72OAN_iQ" target="_VdV-sNPQEDi5SI72OAN_iQ" relationshipRef="_WX7XoNPQEDi5SI72OAN_iQ"/>        <connection xsi:type="Relationship" identifier="_aRK6ENPQEDi5SI72OAN_iQ" source="_KNsPYNPQEDi5SI72OAN_iQ" target="_ZbsDkNPQEDi5SI72OAN_iQ" relationshipRef="_aQ3_INPQEDi5SI72OAN_iQ"/>        <connection xsi:type="Relationship" identifier="_uMoi8NPQEDi5SI72OAN_iQ" source="_sseXwNPQEDi5SI72OAN_iQ" target="_Q5VoANPQEDi5SI72OAN_iQ" relationshipRef="_uMSksNPQEDi5SI72OAN_iQ"/>      </view>      <view identifier="_4lyLINVcEDi5SI72OAN_iQ">        <name xml:lang="en">archimate-diagram</name>        <node xsi:type="Element" identifier="_W2tzANVdEDi5SI72OAN_iQ" h="60" w="130" x="90" y="85" elementRef="_W2ODwNVdEDi5SI72OAN_iQ"/>        <node xsi:type="Element" identifier="_Zz9AMNVdEDi5SI72OAN_iQ" h="60" w="130" x="316" y="160" elementRef="_ZzcC0NVdEDi5SI72OAN_iQ"/>        <node xsi:type="Element" identifier="_cFQ7gNVdEDi5SI72OAN_iQ" h="60" w="130" x="86" y="342" elementRef="_cEuI8NVdEDi5SI72OAN_iQ"/>        <node xsi:type="Element" identifier="_eq1PkNVdEDi5SI72OAN_iQ" h="60" w="130" x="565" y="12" elementRef="_eqRO4NVdEDi5SI72OAN_iQ"/>        <node xsi:type="Element" identifier="_nOaaMNVdEDi5SI72OAN_iQ" h="60" w="130" x="316" y="12" elementRef="_nN6D4NVdEDi5SI72OAN_iQ"/>        <node xsi:type="Element" identifier="_rHchQNVdEDi5SI72OAN_iQ" h="60" w="130" x="316" y="85" elementRef="_rG8K8NVdEDi5SI72OAN_iQ"/>        <node xsi:type="Element" identifier="_JR5tsNVeEDi5SI72OAN_iQ" h="60" w="130" x="86" y="424" elementRef="_JRVtANVeEDi5SI72OAN_iQ"/>        <node xsi:type="Element" identifier="_NO-AMNVeEDi5SI72OAN_iQ" h="60" w="130" x="85" y="706" elementRef="_NOamkNVeEDi5SI72OAN_iQ"/>        <node xsi:type="Element" identifier="_Xi_NsNVeEDi5SI72OAN_iQ" h="60" w="130" x="311" y="667" elementRef="_XiYwwNVeEDi5SI72OAN_iQ"/>        <node xsi:type="Element" identifier="_X-KGwNVeEDi5SI72OAN_iQ" h="60" w="130" x="311" y="744" elementRef="_X9lfANVeEDi5SI72OAN_iQ"/>        <node xsi:type="Element" identifier="_j-QbkNVeEDi5SI72OAN_iQ" h="60" w="130" x="560" y="667" elementRef="_j9oJcNVeEDi5SI72OAN_iQ"/>        <node xsi:type="Element" identifier="_ppLXANVeEDi5SI72OAN_iQ" h="60" w="130" x="560" y="744" elementRef="_polhINVeEDi5SI72OAN_iQ"/>        <node xsi:type="Element" identifier="_xyEJsNVeEDi5SI72OAN_iQ" h="60" w="130" x="561" y="342" elementRef="_xxb3kNVeEDi5SI72OAN_iQ"/>        <node xsi:type="Element" identifier="_-pnD4NVeEDi5SI72OAN_iQ" h="60" w="130" x="561" y="424" elementRef="_-o7HYNVeEDi5SI72OAN_iQ"/>        <node xsi:type="Element" identifier="_PSmPYNVfEDi5SI72OAN_iQ" h="60" w="130" x="85" y="944" elementRef="_PR8IENVfEDi5SI72OAN_iQ"/>        <node xsi:type="Element" identifier="_f7WKUNVfEDi5SI72OAN_iQ" h="60" w="130" x="560" y="869" elementRef="_f6sDANVfEDi5SI72OAN_iQ"/>        <node xsi:type="Element" identifier="_9YSwgNVfEDi5SI72OAN_iQ" h="60" w="130" x="565" y="160" elementRef="_9XopMNVfEDi5SI72OAN_iQ"/>        <node xsi:type="Element" identifier="_MneQcNVgEDi5SI72OAN_iQ" h="60" w="130" x="560" y="944" elementRef="_MmziENVgEDi5SI72OAN_iQ"/>        <node xsi:type="Element" identifier="_QRwJ0NVgEDi5SI72OAN_iQ" h="60" w="130" x="80" y="1124" elementRef="_QQ_U0NVgEDi5SI72OAN_iQ"/>        <node xsi:type="Element" identifier="_UfXZwNVgEDi5SI72OAN_iQ" h="60" w="130" x="555" y="1075" elementRef="_UetScNVgEDi5SI72OAN_iQ"/>        <node xsi:type="Element" identifier="_Za5foNVgEDi5SI72OAN_iQ" h="60" w="130" x="555" y="1149" elementRef="_ZaGOYNVgEDi5SI72OAN_iQ"/>        <node xsi:type="Element" identifier="_cneJUNVgEDi5SI72OAN_iQ" h="60" w="130" x="555" y="1223" elementRef="_cmwXoNVgEDi5SI72OAN_iQ"/>        <node xsi:type="Element" identifier="_1VlzcNVhEDi5SI72OAN_iQ" h="60" w="130" x="87" y="506" elementRef="_1UfnQNVhEDi5SI72OAN_iQ"/>        <node xsi:type="Element" identifier="_Ia-I4NViEDi5SI72OAN_iQ" h="60" w="130" x="561" y="506" elementRef="_IaPJENViEDi5SI72OAN_iQ"/>        <node xsi:type="Element" identifier="_lYr1YNViEDi5SI72OAN_iQ" h="60" w="130" x="316" y="238" elementRef="_lX-DsNViEDi5SI72OAN_iQ"/>        <node xsi:type="Element" identifier="_scIC8NViEDi5SI72OAN_iQ" h="60" w="130" x="565" y="238" elementRef="_sbaRQNViEDi5SI72OAN_iQ"/>        <node xsi:type="Element" identifier="_9bV9INViEDi5SI72OAN_iQ" h="60" w="130" x="87" y="584" elementRef="_9aj6ANViEDi5SI72OAN_iQ"/>        <node xsi:type="Element" identifier="_-RErQNViEDi5SI72OAN_iQ" h="60" w="130" x="561" y="584" elementRef="_-QSoINViEDi5SI72OAN_iQ"/>        <connection xsi:type="Relationship" identifier="_n5EgwNVdEDi5SI72OAN_iQ" source="_W2tzANVdEDi5SI72OAN_iQ" target="_nOaaMNVdEDi5SI72OAN_iQ" relationshipRef="_n4qRENVdEDi5SI72OAN_iQ"/>        <connection xsi:type="Relationship" identifier="_zf72MNVdEDi5SI72OAN_iQ" source="_W2tzANVdEDi5SI72OAN_iQ" target="_rHchQNVdEDi5SI72OAN_iQ" relationshipRef="_zfg_cNVdEDi5SI72OAN_iQ"/>        <connection xsi:type="Relationship" identifier="_3hC7MNVdEDi5SI72OAN_iQ" source="_W2tzANVdEDi5SI72OAN_iQ" target="_Zz9AMNVdEDi5SI72OAN_iQ" relationshipRef="_3gndYNVdEDi5SI72OAN_iQ"/>        <connection xsi:type="Relationship" identifier="_Ay46ANVeEDi5SI72OAN_iQ" source="_nOaaMNVdEDi5SI72OAN_iQ" target="_eq1PkNVdEDi5SI72OAN_iQ" relationshipRef="_AycOENVeEDi5SI72OAN_iQ"/>        <connection xsi:type="Relationship" identifier="_ZRnSsNVeEDi5SI72OAN_iQ" source="_NO-AMNVeEDi5SI72OAN_iQ" target="_Xi_NsNVeEDi5SI72OAN_iQ" relationshipRef="_ZRKmwNVeEDi5SI72OAN_iQ"/>        <connection xsi:type="Relationship" identifier="_bkhJcNVeEDi5SI72OAN_iQ" source="_NO-AMNVeEDi5SI72OAN_iQ" target="_X-KGwNVeEDi5SI72OAN_iQ" relationshipRef="_bkFEkNVeEDi5SI72OAN_iQ"/>        <connection xsi:type="Relationship" identifier="_l7Y2oNVeEDi5SI72OAN_iQ" source="_Xi_NsNVeEDi5SI72OAN_iQ" target="_j-QbkNVeEDi5SI72OAN_iQ" relationshipRef="_l67joNVeEDi5SI72OAN_iQ"/>        <connection xsi:type="Relationship" identifier="_qZxtgNVeEDi5SI72OAN_iQ" source="_X-KGwNVeEDi5SI72OAN_iQ" target="_ppLXANVeEDi5SI72OAN_iQ" relationshipRef="_qZTzcNVeEDi5SI72OAN_iQ"/>        <connection xsi:type="Relationship" identifier="_znsOkNVeEDi5SI72OAN_iQ" source="_cFQ7gNVdEDi5SI72OAN_iQ" target="_xyEJsNVeEDi5SI72OAN_iQ" relationshipRef="_znO7kNVeEDi5SI72OAN_iQ"/>        <connection xsi:type="Relationship" identifier="__i-74NVeEDi5SI72OAN_iQ" source="_JR5tsNVeEDi5SI72OAN_iQ" target="_-pnD4NVeEDi5SI72OAN_iQ" relationshipRef="__igawNVeEDi5SI72OAN_iQ"/>        <connection xsi:type="Relationship" identifier="_-uCbcNVfEDi5SI72OAN_iQ" source="_Zz9AMNVdEDi5SI72OAN_iQ" target="_9YSwgNVfEDi5SI72OAN_iQ" relationshipRef="_-tdMoNVfEDi5SI72OAN_iQ"/>        <connection xsi:type="Relationship" identifier="_KBtvINVgEDi5SI72OAN_iQ" source="_PSmPYNVfEDi5SI72OAN_iQ" target="_f7WKUNVfEDi5SI72OAN_iQ" relationshipRef="_KBLjoNVgEDi5SI72OAN_iQ"/>        <connection xsi:type="Relationship" identifier="_nIOyUNVgEDi5SI72OAN_iQ" source="_QRwJ0NVgEDi5SI72OAN_iQ" target="_UfXZwNVgEDi5SI72OAN_iQ" relationshipRef="_nHsm0NVgEDi5SI72OAN_iQ"/>        <connection xsi:type="Relationship" identifier="_nwvj0NVgEDi5SI72OAN_iQ" source="_QRwJ0NVgEDi5SI72OAN_iQ" target="_Za5foNVgEDi5SI72OAN_iQ" relationshipRef="_nve_kNVgEDi5SI72OAN_iQ"/>        <connection xsi:type="Relationship" identifier="_omHsoNVgEDi5SI72OAN_iQ" source="_QRwJ0NVgEDi5SI72OAN_iQ" target="_cneJUNVgEDi5SI72OAN_iQ" relationshipRef="_ok49kNVgEDi5SI72OAN_iQ"/>        <connection xsi:type="Relationship" identifier="_JLKPsNViEDi5SI72OAN_iQ" source="_1VlzcNVhEDi5SI72OAN_iQ" target="_Ia-I4NViEDi5SI72OAN_iQ" relationshipRef="_JKlA4NViEDi5SI72OAN_iQ"/>        <connection xsi:type="Relationship" identifier="_mdI8ANViEDi5SI72OAN_iQ" source="_W2tzANVdEDi5SI72OAN_iQ" target="_lYr1YNViEDi5SI72OAN_iQ" relationshipRef="_mck7UNViEDi5SI72OAN_iQ"/>        <connection xsi:type="Relationship" identifier="_tMjaUNViEDi5SI72OAN_iQ" source="_lYr1YNViEDi5SI72OAN_iQ" target="_scIC8NViEDi5SI72OAN_iQ" relationshipRef="_tL-LgNViEDi5SI72OAN_iQ"/>        <connection xsi:type="Relationship" identifier="__Bv6QNViEDi5SI72OAN_iQ" source="_9bV9INViEDi5SI72OAN_iQ" target="_-RErQNViEDi5SI72OAN_iQ" relationshipRef="__BJdUNViEDi5SI72OAN_iQ"/>      </view>    </diagrams>  </views></model>
