{"id":"id-770c4aed-d34a-4ab8-bb3a-83aebdbe0ca7","name":"Report API","documentation":"","file":"../../raw-data/github/xml/Report API.xml","format":"XML","source":"","timestamp":"15-06-2023 04:10:57","tags":[],"archiVersion":"","language":"en","elements":[{"id":"d5e07a32-6946-4bcc-811f-e7b5999333f6","name":"uib sec team","type":"BusinessActor","layer":"business","documentation":""},{"id":"a8506955-88e4-4bc7-8d0f-31605c1429e2","name":"haproxy","type":"ApplicationComponent","layer":"application","documentation":""},{"id":"facfc8e6-4d40-4327-8b98-788994c2fb28","name":"webgui","type":"ApplicationService","layer":"application","documentation":""},{"id":"ae423f1b-38ad-4899-add1-18e09255ced1","name":"uib instance db","type":"DataObject","layer":"application","documentation":""},{"id":"id-078a3eb6-ef57-4c1b-a530-c1bb09b54b5a","name":"collection script","type":"ApplicationProcess","layer":"application","documentation":""},{"id":"c747207f-3c65-4621-8a8f-0c3dbf07e109","name":"api key","type":"DataObject","layer":"application","documentation":""},{"id":"id-31fe0116-858b-49a1-9aeb-162669423492","name":"haproxy","type":"ApplicationComponent","layer":"application","documentation":""},{"id":"id-5ab0f80b-0c70-4d20-a46a-014f44bb8875","name":"report api","type":"ApplicationComponent","layer":"application","documentation":"https://github.com/norcams/report-app"},{"id":"b85cf3fe-3a98-4c04-9ab4-97deb3317c81","name":"report db","type":"DataObject","layer":"application","documentation":""},{"id":"id-038e2a78-82b5-4df6-9b52-48a1e9672120","name":"systemd script","type":"ApplicationProcess","layer":"application","documentation":"https://github.com/norcams/report-utils/"},{"id":"cc045c7b-1385-48c5-b086-cab01c24fd4a","name":"api key","type":"DataObject","layer":"application","documentation":""},{"id":"d3964242-0f95-4ad3-9412-49f4816018d2","name":"owner script","type":"ApplicationProcess","layer":"application","documentation":"https://github.com/norcams/himlarcli/blob/master/sync_owners.py"},{"id":"e3d8a556-8ebe-4784-b6b5-8bf26ccf5e96","name":"get instance","type":"ApplicationInterface","layer":"application","documentation":"https://report.nrec.no/api/ui/#!/Instance/api_instance_get_instances"},{"id":"c10978b4-d6a2-4494-a317-e483539c2e46","name":"post instance","type":"ApplicationInterface","layer":"application","documentation":"https://report.nrec.no/api/ui/#!/Instance/api_instance_put_instance"},{"id":"id-99786691-b6c7-44dc-bcca-60f99fdc0907","name":"report.nrec.no","type":"ApplicationService","layer":"application","documentation":"https://report.nrec.no/"},{"id":"id-905ba938-e4f8-4dca-92d1-b2dd0dda5660","name":"owner script","type":"ApplicationProcess","layer":"application","documentation":"https://github.com/norcams/himlarcli/blob/master/sync_owners.py"},{"id":"id-0ae91566-0282-4e91-80ae-f2090cee3de7","name":"report db","type":"DataObject","layer":"application","documentation":""},{"id":"d3d0f3f9-5825-4c23-885a-d0e2725c87df","name":"report api","type":"ApplicationComponent","layer":"application","documentation":"https://github.com/norcams/report-app"},{"id":"id-23b80c7e-1753-4b94-bac7-c3bb78bf8349","name":"haproxy","type":"ApplicationComponent","layer":"application","documentation":""},{"id":"id-3db29318-4e06-4e12-a642-99622bed3a7e","name":"api key","type":"DataObject","layer":"application","documentation":""},{"id":"id-156c71b7-75d2-4c1b-8b3c-a84f45b2bb7b","name":"systemd script","type":"ApplicationProcess","layer":"application","documentation":"https://github.com/norcams/report-utils/"},{"id":"edddea15-f35a-4a54-8d57-a6b15bd56491","name":"bgo","type":"Facility","layer":"technology","documentation":""},{"id":"id-151a285a-c9bb-4f4f-84ee-2b3346762ed7","name":"bgo-compute","type":"Equipment","layer":"technology","documentation":""},{"id":"id-7885f687-b406-4980-9716-775462d9c4e2","name":"bgo-controller","type":"Equipment","layer":"technology","documentation":""},{"id":"id-408ed713-4b4c-4a80-8f58-5ee2970e6497","name":"bgo-db-global","type":"Node","layer":"technology","documentation":""},{"id":"id-0d22c5e4-bb66-4acc-9a5d-b2e7d41bf309","name":"instance","type":"Node","layer":"technology","documentation":""},{"id":"f7f57460-d944-4088-8f68-0f93cbee6dc9","name":"bgo-report","type":"Node","layer":"technology","documentation":""},{"id":"id-82d0dd4d-0ffe-4fc4-8925-f45dc6159f0d","name":"bgo-api","type":"Node","layer":"technology","documentation":""},{"id":"id-0e35167e-360d-4e67-b4ce-979f6e69241f","name":"bgo-proxy","type":"Node","layer":"technology","documentation":""},{"id":"e51d8834-e7a2-430c-9b0b-f04111bf63c0","name":"uib","type":"Facility","layer":"technology","documentation":""},{"id":"id-761cc35a-36aa-4ef7-b1dc-327c31a31b76","name":"uib-ha","type":"Equipment","layer":"technology","documentation":""},{"id":"id-4cf653c8-ff9c-4612-800a-4a9abed60608","name":"tjinfo","type":"Node","layer":"technology","documentation":""},{"id":"id-0768a097-f887-4446-8cb7-6d4a9f1bd3b2","name":"osl","type":"Facility","layer":"technology","documentation":""},{"id":"id-102ac652-22b7-44a4-a513-a9c7025538ad","name":"osl-compute","type":"Equipment","layer":"technology","documentation":""},{"id":"dcf30ca1-f172-4d02-a2f8-d9cc649f3d50","name":"osl-controller","type":"Equipment","layer":"technology","documentation":""},{"id":"dcc52380-3dbe-40cb-80c3-99ab4f2bfce3","name":"osl-db-global","type":"Node","layer":"technology","documentation":""},{"id":"b23daeaa-8389-431c-ae69-2ae617b8ec95","name":"osl-api","type":"Node","layer":"technology","documentation":""},{"id":"id-24dcf4a5-3184-41c1-b887-d00490a5de3d","name":"instance","type":"Node","layer":"technology","documentation":""},{"id":"cc08ebb9-451a-4058-9487-7fa6cc2d3455","name":"osl-report","type":"Node","layer":"technology","documentation":""},{"id":"bfac4c34-8813-49e6-b5a3-4fc52a517393","name":"osl-proxy","type":"Node","layer":"technology","documentation":""}],"relationships":[{"id":"id-5bafc17d-c211-41b1-8e63-a4d455646ece","sourceId":"edddea15-f35a-4a54-8d57-a6b15bd56491","targetId":"id-7885f687-b406-4980-9716-775462d9c4e2","type":"Composition","name":"","documentation":""},{"id":"id-363693ec-4372-4de3-9941-48a746fd25a5","sourceId":"id-7885f687-b406-4980-9716-775462d9c4e2","targetId":"id-408ed713-4b4c-4a80-8f58-5ee2970e6497","type":"Serving","name":"","documentation":""},{"id":"id-525a0e45-760f-41e5-a30d-8f22d6df1a35","sourceId":"edddea15-f35a-4a54-8d57-a6b15bd56491","targetId":"id-151a285a-c9bb-4f4f-84ee-2b3346762ed7","type":"Composition","name":"","documentation":""},{"id":"id-4eb5bfef-82d2-4b05-ba04-4e33123c6b42","sourceId":"id-151a285a-c9bb-4f4f-84ee-2b3346762ed7","targetId":"id-0d22c5e4-bb66-4acc-9a5d-b2e7d41bf309","type":"Serving","name":"","documentation":""},{"id":"id-4cfb2451-5a84-4708-993d-3a06e9736e07","sourceId":"id-0d22c5e4-bb66-4acc-9a5d-b2e7d41bf309","targetId":"id-038e2a78-82b5-4df6-9b52-48a1e9672120","type":"Serving","name":"","documentation":""},{"id":"id-07952fa7-bf28-4b7e-9a86-41151913e6ce","sourceId":"id-7885f687-b406-4980-9716-775462d9c4e2","targetId":"id-82d0dd4d-0ffe-4fc4-8925-f45dc6159f0d","type":"Serving","name":"","documentation":""},{"id":"e083e65f-1433-4cbe-808c-3aff67929a26","sourceId":"id-7885f687-b406-4980-9716-775462d9c4e2","targetId":"f7f57460-d944-4088-8f68-0f93cbee6dc9","type":"Serving","name":"","documentation":""},{"id":"a9eac8ad-1a9c-477f-af05-811e42acca66","sourceId":"f7f57460-d944-4088-8f68-0f93cbee6dc9","targetId":"id-5ab0f80b-0c70-4d20-a46a-014f44bb8875","type":"Serving","name":"","documentation":""},{"id":"id-8d7c7a6c-8cad-4b5e-864f-fff9f18e9fbe","sourceId":"id-82d0dd4d-0ffe-4fc4-8925-f45dc6159f0d","targetId":"id-31fe0116-858b-49a1-9aeb-162669423492","type":"Serving","name":"","documentation":""},{"id":"id-991df578-f776-4b56-80d7-100705a8b5da","sourceId":"e51d8834-e7a2-430c-9b0b-f04111bf63c0","targetId":"id-761cc35a-36aa-4ef7-b1dc-327c31a31b76","type":"Composition","name":"","documentation":""},{"id":"id-8916415c-5596-44e5-b560-e3ef984546d2","sourceId":"id-761cc35a-36aa-4ef7-b1dc-327c31a31b76","targetId":"a8506955-88e4-4bc7-8d0f-31605c1429e2","type":"Serving","name":"","documentation":""},{"id":"id-91ddb403-a1c9-4935-81f9-d1e81e32b594","sourceId":"e51d8834-e7a2-430c-9b0b-f04111bf63c0","targetId":"id-4cf653c8-ff9c-4612-800a-4a9abed60608","type":"Composition","name":"","documentation":""},{"id":"bc75c038-f94f-4492-8ade-241ad0093335","sourceId":"a8506955-88e4-4bc7-8d0f-31605c1429e2","targetId":"id-99786691-b6c7-44dc-bcca-60f99fdc0907","type":"Serving","name":"","documentation":""},{"id":"id-10904c29-eacd-4356-ab6a-7a47c7827fbf","sourceId":"cc045c7b-1385-48c5-b086-cab01c24fd4a","targetId":"id-5ab0f80b-0c70-4d20-a46a-014f44bb8875","type":"Association","name":"","documentation":""},{"id":"id-44dcab8e-ecae-4f65-9f78-54a43f81394e","sourceId":"id-038e2a78-82b5-4df6-9b52-48a1e9672120","targetId":"c10978b4-d6a2-4494-a317-e483539c2e46","type":"Flow","name":"","documentation":""},{"id":"id-22ea07e7-dd08-4141-b825-1ea581610e7f","sourceId":"id-7885f687-b406-4980-9716-775462d9c4e2","targetId":"id-0e35167e-360d-4e67-b4ce-979f6e69241f","type":"Serving","name":"","documentation":""},{"id":"id-564901f8-196d-40cf-a1bc-338c41576f0c","sourceId":"id-0e35167e-360d-4e67-b4ce-979f6e69241f","targetId":"d3964242-0f95-4ad3-9412-49f4816018d2","type":"Serving","name":"","documentation":""},{"id":"e402a1b7-c32d-48ec-a7b0-83b15845f4db","sourceId":"d3964242-0f95-4ad3-9412-49f4816018d2","targetId":"b85cf3fe-3a98-4c04-9ab4-97deb3317c81","type":"Access","name":"","documentation":""},{"id":"id-3a94377e-4a5c-4d73-ba30-b1ff6a530887","sourceId":"id-5ab0f80b-0c70-4d20-a46a-014f44bb8875","targetId":"b85cf3fe-3a98-4c04-9ab4-97deb3317c81","type":"Access","name":"","documentation":""},{"id":"id-36166f03-9313-4cec-93c2-40850449a61a","sourceId":"a8506955-88e4-4bc7-8d0f-31605c1429e2","targetId":"id-31fe0116-858b-49a1-9aeb-162669423492","type":"Serving","name":"","documentation":""},{"id":"id-54ad2a99-2e30-4982-88e0-81ae28aae761","sourceId":"id-31fe0116-858b-49a1-9aeb-162669423492","targetId":"id-5ab0f80b-0c70-4d20-a46a-014f44bb8875","type":"Serving","name":"","documentation":""},{"id":"id-240c984c-4be6-4b2c-ac65-3d991b2e1fd1","sourceId":"c10978b4-d6a2-4494-a317-e483539c2e46","targetId":"id-99786691-b6c7-44dc-bcca-60f99fdc0907","type":"Association","name":"","documentation":""},{"id":"id-998d433e-bc53-4524-8307-e6b2a7342cb3","sourceId":"id-408ed713-4b4c-4a80-8f58-5ee2970e6497","targetId":"b85cf3fe-3a98-4c04-9ab4-97deb3317c81","type":"Access","name":"","documentation":""},{"id":"a553e4f2-ede9-4d9c-846d-3ee595390a89","sourceId":"id-408ed713-4b4c-4a80-8f58-5ee2970e6497","targetId":"b85cf3fe-3a98-4c04-9ab4-97deb3317c81","type":"Association","name":"","documentation":""},{"id":"id-8aaf23d3-daa1-42b5-9445-78260c43b93a","sourceId":"dcf30ca1-f172-4d02-a2f8-d9cc649f3d50","targetId":"id-0768a097-f887-4446-8cb7-6d4a9f1bd3b2","type":"Composition","name":"","documentation":""},{"id":"id-6294161b-9b7f-47f9-838f-d57c508aa66a","sourceId":"id-102ac652-22b7-44a4-a513-a9c7025538ad","targetId":"id-0768a097-f887-4446-8cb7-6d4a9f1bd3b2","type":"Composition","name":"","documentation":""},{"id":"id-37f46c4f-8289-4355-ad38-4647d55c7c6e","sourceId":"dcf30ca1-f172-4d02-a2f8-d9cc649f3d50","targetId":"bfac4c34-8813-49e6-b5a3-4fc52a517393","type":"Serving","name":"","documentation":""},{"id":"ea25030c-8467-47fd-a07f-7125e38c0d48","sourceId":"dcf30ca1-f172-4d02-a2f8-d9cc649f3d50","targetId":"dcc52380-3dbe-40cb-80c3-99ab4f2bfce3","type":"Serving","name":"","documentation":""},{"id":"id-41068917-34ca-4744-b36f-76a84450e3a3","sourceId":"dcf30ca1-f172-4d02-a2f8-d9cc649f3d50","targetId":"cc08ebb9-451a-4058-9487-7fa6cc2d3455","type":"Serving","name":"","documentation":""},{"id":"id-13c2e47d-dd66-408d-9b73-f0e009ac3de8","sourceId":"dcf30ca1-f172-4d02-a2f8-d9cc649f3d50","targetId":"b23daeaa-8389-431c-ae69-2ae617b8ec95","type":"Serving","name":"","documentation":""},{"id":"ff76e1bd-0033-4e00-8677-57b1d228e725","sourceId":"dcc52380-3dbe-40cb-80c3-99ab4f2bfce3","targetId":"id-0ae91566-0282-4e91-80ae-f2090cee3de7","type":"Association","name":"","documentation":""},{"id":"a74bb8c3-886b-4928-9f55-39def33c0c4f","sourceId":"b23daeaa-8389-431c-ae69-2ae617b8ec95","targetId":"id-23b80c7e-1753-4b94-bac7-c3bb78bf8349","type":"Serving","name":"","documentation":""},{"id":"b6b4917c-105c-4c43-9402-f70a50cd2fc0","sourceId":"cc08ebb9-451a-4058-9487-7fa6cc2d3455","targetId":"d3d0f3f9-5825-4c23-885a-d0e2725c87df","type":"Serving","name":"","documentation":""},{"id":"id-3d65d5c5-36c2-4762-b1c5-7eba81959d3d","sourceId":"bfac4c34-8813-49e6-b5a3-4fc52a517393","targetId":"id-905ba938-e4f8-4dca-92d1-b2dd0dda5660","type":"Serving","name":"","documentation":""},{"id":"e12cbcfd-7237-4ecd-8d95-c912c6a33131","sourceId":"id-3db29318-4e06-4e12-a642-99622bed3a7e","targetId":"id-0ae91566-0282-4e91-80ae-f2090cee3de7","type":"Association","name":"","documentation":""},{"id":"ef98926d-5da2-4c33-b741-62417704a835","sourceId":"a8506955-88e4-4bc7-8d0f-31605c1429e2","targetId":"id-23b80c7e-1753-4b94-bac7-c3bb78bf8349","type":"Serving","name":"","documentation":""},{"id":"fa318ba7-d116-4abf-a783-61b8ec359db6","sourceId":"id-23b80c7e-1753-4b94-bac7-c3bb78bf8349","targetId":"d3d0f3f9-5825-4c23-885a-d0e2725c87df","type":"Serving","name":"","documentation":""},{"id":"dd5f15cb-de0e-4181-88c2-ac34b1c499c2","sourceId":"d3d0f3f9-5825-4c23-885a-d0e2725c87df","targetId":"id-0ae91566-0282-4e91-80ae-f2090cee3de7","type":"Access","name":"","documentation":""},{"id":"c44bc6eb-5659-4f58-945c-d24c274ebea0","sourceId":"id-905ba938-e4f8-4dca-92d1-b2dd0dda5660","targetId":"id-0ae91566-0282-4e91-80ae-f2090cee3de7","type":"Access","name":"","documentation":""},{"id":"id-5831eecb-5b79-4c0c-b836-5a1c8ff425d0","sourceId":"id-102ac652-22b7-44a4-a513-a9c7025538ad","targetId":"id-24dcf4a5-3184-41c1-b887-d00490a5de3d","type":"Serving","name":"","documentation":""},{"id":"d5f33cbb-9579-44a9-9870-e88fcddc4973","sourceId":"id-24dcf4a5-3184-41c1-b887-d00490a5de3d","targetId":"id-156c71b7-75d2-4c1b-8b3c-a84f45b2bb7b","type":"Serving","name":"","documentation":""},{"id":"e8d0ec14-fd21-45c8-91ba-bd20cc5338f6","sourceId":"id-156c71b7-75d2-4c1b-8b3c-a84f45b2bb7b","targetId":"c10978b4-d6a2-4494-a317-e483539c2e46","type":"Flow","name":"","documentation":""},{"id":"id-20536df7-7d49-4870-955b-2333ab707b77","sourceId":"e3d8a556-8ebe-4784-b6b5-8bf26ccf5e96","targetId":"id-99786691-b6c7-44dc-bcca-60f99fdc0907","type":"Association","name":"","documentation":""},{"id":"id-6135942d-0264-4254-b847-aec5e21e4724","sourceId":"e3d8a556-8ebe-4784-b6b5-8bf26ccf5e96","targetId":"id-078a3eb6-ef57-4c1b-a530-c1bb09b54b5a","type":"Flow","name":"","documentation":""},{"id":"eef88305-ab7e-4235-822c-90c573eef800","sourceId":"id-078a3eb6-ef57-4c1b-a530-c1bb09b54b5a","targetId":"ae423f1b-38ad-4899-add1-18e09255ced1","type":"Access","name":"","documentation":""},{"id":"id-1a1baf9b-d5c9-4841-bce7-670ac605af78","sourceId":"facfc8e6-4d40-4327-8b98-788994c2fb28","targetId":"ae423f1b-38ad-4899-add1-18e09255ced1","type":"Access","name":"","documentation":""},{"id":"bd74e76a-c7de-49c6-832d-2d86e0f16cf9","sourceId":"id-4cf653c8-ff9c-4612-800a-4a9abed60608","targetId":"id-078a3eb6-ef57-4c1b-a530-c1bb09b54b5a","type":"Serving","name":"","documentation":""},{"id":"id-98f3914f-26bb-4b04-919d-ea353886f13f","sourceId":"id-4cf653c8-ff9c-4612-800a-4a9abed60608","targetId":"ae423f1b-38ad-4899-add1-18e09255ced1","type":"Association","name":"","documentation":""},{"id":"id-1eb0c862-a8f3-4c8b-b57c-605ba664c39c","sourceId":"id-4cf653c8-ff9c-4612-800a-4a9abed60608","targetId":"facfc8e6-4d40-4327-8b98-788994c2fb28","type":"Serving","name":"","documentation":""},{"id":"id-9e38615b-af87-4b0f-b7c0-19a62d325f7c","sourceId":"id-078a3eb6-ef57-4c1b-a530-c1bb09b54b5a","targetId":"c747207f-3c65-4621-8a8f-0c3dbf07e109","type":"Access","name":"","documentation":""},{"id":"dd4b7c1f-a157-40c1-8216-04c612ac31f2","sourceId":"facfc8e6-4d40-4327-8b98-788994c2fb28","targetId":"d5e07a32-6946-4bcc-811f-e7b5999333f6","type":"Flow","name":"","documentation":""}],"views":[{"id":"a57181b7-ed42-4492-a8d6-54ce01cb515c","name":"Default View","viewpoint":"","documentation":""},{"id":"id-39126956-2d7a-4764-88c3-509af42fc8c7","name":"UiB Sec view","viewpoint":"","documentation":""}]}