{"identifier":"https://me.big.tuwien.ac.at/EAModelSet/7c8b6ef5","archimateId":"7c8b6ef5","name":"Tutorial ArchiMate","description":"","formats":["XML","CSV","JSON","ARCHIMATE"],"source":"GitHub","repository":"lorsatti/AgileDev","license":"Not found","sourceFile":"raw-data/github/archimate/tutorialarchimate.archimate","sourceFormat":"ARCHIMATE","timestamp":"2023-07-06T09:29:17","tags":[],"duplicates":[],"language":"en","elements":[{"id":"5ffa87e3","name":"Accept Damage Claim","type":"BusinessProcess","layer":"business"},{"id":"b1a6f360","name":"Business Actor","type":"BusinessActor","layer":"business"},{"id":"047289a4","name":"Business Actor","type":"BusinessActor","layer":"business"},{"id":"f973e5a9","name":"Business Event","type":"BusinessEvent","layer":"business"},{"id":"4088302f","name":"Business Interaction","type":"BusinessInteraction","layer":"business"},{"id":"7a77302a","name":"Business Interface","type":"BusinessInterface","layer":"business"},{"id":"978b0757","name":"Business Object","type":"BusinessObject","layer":"business"},{"id":"f521a19b","name":"Business Process","type":"BusinessProcess","layer":"business"},{"id":"76667cd5","name":"Business Role","type":"BusinessRole","layer":"business"},{"id":"2c159f6f","name":"Business Role","type":"BusinessRole","layer":"business"},{"id":"8f115367","name":"Business Service","type":"BusinessService","layer":"business"},{"id":"6225c05d","name":"Customer Info","type":"BusinessObject","layer":"business"},{"id":"f120cbd4","name":"Damage Claim","type":"BusinessObject","layer":"business"},{"id":"b13b4aa8","name":"Damage Occured","type":"BusinessEvent","layer":"business"},{"id":"da624149","name":"Evaluate Damage Claim","type":"BusinessProcess","layer":"business"},{"id":"e503c599","name":"Insurrance Policy","type":"BusinessObject","layer":"business"},{"id":"a1ac18dd","name":"Meaning","type":"Meaning","layer":"motivation"},{"id":"7b0d47a8","name":"Pay","type":"BusinessProcess","layer":"business"},{"id":"2ea88bdb","name":"Register Damage","type":"BusinessProcess","layer":"business"},{"id":"0fa23d54","name":"Value","type":"Value","layer":"motivation"},{"id":"af2be141","name":"Data Object","type":"DataObject","layer":"application"},{"id":"f6efb5b0","name":"Application Service","type":"ApplicationService","layer":"application"},{"id":"e221080d","name":"Application Function","type":"ApplicationFunction","layer":"application"},{"id":"cabbe968","name":"Application Component","type":"ApplicationComponent","layer":"application"},{"id":"ccf774c6","name":"Application Interface","type":"ApplicationInterface","layer":"application"},{"id":"2fadd6ff","name":"Application Component","type":"ApplicationComponent","layer":"application"},{"id":"6a22992d","name":"Artifact","type":"Artifact","layer":"technology"},{"id":"76485697","name":"System Software","type":"SystemSoftware","layer":"technology"},{"id":"7ce23f84","name":"Infrastructure Service","type":"TechnologyService","layer":"technology"},{"id":"8894926b","name":"Device","type":"Device","layer":"technology"},{"id":"566c8c20","name":"Infrastructure Interface","type":"TechnologyInterface","layer":"technology"},{"id":"f9b85f33","name":"Network","type":"CommunicationNetwork","layer":"technology"}],"relationships":[{"id":"81cc6304","sourceId":"a1ac18dd","targetId":"978b0757","type":"Association"},{"id":"b881531a","sourceId":"f521a19b","targetId":"978b0757","type":"Access"},{"id":"3065d35b","sourceId":"f973e5a9","targetId":"f521a19b","type":"Triggering"},{"id":"e82ad18d","sourceId":"f521a19b","targetId":"8f115367","type":"Realization"},{"id":"01277c08","sourceId":"0fa23d54","targetId":"8f115367","type":"Association"},{"id":"2205942a","sourceId":"76667cd5","targetId":"f521a19b","type":"Assignment"},{"id":"c61cb31e","sourceId":"b1a6f360","targetId":"76667cd5","type":"Assignment"},{"id":"53bb4584","sourceId":"af2be141","targetId":"978b0757","type":"Realization"},{"id":"2cba84bf","sourceId":"e221080d","targetId":"af2be141","type":"Access"},{"id":"77efc425","sourceId":"f6efb5b0","targetId":"f521a19b","type":"Serving"},{"id":"3358aa97","sourceId":"e221080d","targetId":"f6efb5b0","type":"Realization"},{"id":"ce219228","sourceId":"7a77302a","targetId":"8f115367","type":"Assignment"},{"id":"430c73f1","sourceId":"ccf774c6","targetId":"f6efb5b0","type":"Assignment"},{"id":"bc6c10ea","sourceId":"76667cd5","targetId":"ccf774c6","type":"Association"},{"id":"ac9b59e9","sourceId":"6a22992d","targetId":"af2be141","type":"Realization"},{"id":"49fb4455","sourceId":"f9b85f33","targetId":"8894926b","type":"Association"},{"id":"f217ed27","sourceId":"cabbe968","targetId":"566c8c20","type":"Association"},{"id":"a9d13b68","sourceId":"cabbe968","targetId":"e221080d","type":"Assignment"},{"id":"d0a196ee","sourceId":"7ce23f84","targetId":"e221080d","type":"Serving"},{"id":"a585a87f","sourceId":"76485697","targetId":"7ce23f84","type":"Realization"},{"id":"b1417f70","sourceId":"8894926b","targetId":"76485697","type":"Assignment"},{"id":"cdc7084f","sourceId":"76485697","targetId":"6a22992d","type":"Assignment"},{"id":"2eaa7de9","sourceId":"76667cd5","targetId":"7a77302a","type":"Composition"},{"id":"54604954","sourceId":"cabbe968","targetId":"ccf774c6","type":"Composition"},{"id":"53cc93b6","sourceId":"8894926b","targetId":"566c8c20","type":"Composition"},{"id":"51b57aa8","sourceId":"b13b4aa8","targetId":"2ea88bdb","type":"Triggering"},{"id":"ac4e89ed","sourceId":"2ea88bdb","targetId":"5ffa87e3","type":"Triggering"},{"id":"431d197c","sourceId":"5ffa87e3","targetId":"da624149","type":"Triggering"},{"id":"db0be9c6","sourceId":"da624149","targetId":"7b0d47a8","type":"Triggering"},{"id":"4aeec17b","sourceId":"2ea88bdb","targetId":"f120cbd4","type":"Access"},{"id":"34857074","sourceId":"5ffa87e3","targetId":"f120cbd4","type":"Access"},{"id":"a9079f8d","sourceId":"da624149","targetId":"f120cbd4","type":"Access"},{"id":"e57c9fe2","sourceId":"2ea88bdb","targetId":"6225c05d","type":"Access"},{"id":"088bc1c5","sourceId":"5ffa87e3","targetId":"6225c05d","type":"Access"},{"id":"d89a0149","sourceId":"7b0d47a8","targetId":"6225c05d","type":"Access"},{"id":"a8303ab9","sourceId":"5ffa87e3","targetId":"e503c599","type":"Access"}],"views":[{"id":"80b375e9","name":"Default View","viewpoint":""},{"id":"45903863","name":"What is ArchiMate","viewpoint":""},{"id":"23a05264","name":"Core Concepts","viewpoint":""},{"id":"1fccc77b","name":"Domain Model","viewpoint":""}]}